Workbook

Sheet Summary
A1: Spinney External Works — Budget Summary
A2: Last updated: | B2: 46246 | C2: All figures gross (as payable). Invoiced / Paid pull automatically from the Invoice Register; Contingency remaining pulls from the Drawdown sheet.
A4: Cost centre | B4: Supplier | C4: Committed £ | D4: Invoiced £ | E4: Paid £ | F4: Remaining vs committed £ | G4: Notes
A5: Decking materials | B5: V4 Wood Flooring Ltd | C5: 32228.99 | D5: =SUMIF('Invoice Register'!$B:$B,$A5,'Invoice Register'!$F:$F) -> 32228.99 | E5: =SUMIFS('Invoice Register'!$F:$F,'Invoice Register'!$B:$B,$A5,'Invoice Register'!$G:$G,"<>") -> 32228.99 | F5: =C5-D5 -> 0 | G5: Order amended to all Ashwood + flexible bullnose (1 Jul). PAID IN FULL 9 Jul, ref V4FQ-15584. 25% restocking on over-ordering — unlikely given curved design + offcuts project, but noted.
A6: Decking labour | B6: LG Building and Roofing Ltd | C6: 17600 | D6: =SUMIF('Invoice Register'!$B:$B,$A6,'Invoice Register'!$F:$F) -> 6400 | E6: =SUMIFS('Invoice Register'!$F:$F,'Invoice Register'!$B:$B,$A6,'Invoice Register'!$G:$G,"<>") -> 6400 | F6: =C6-D6 -> 11200 | G6: Labour £17,600 (no VAT). Stage 1 (£4,400) invoiced/paid 20 Aug, full price. Cash instalment (£2,000, 4 Sep) — CORRECTED: cash payments DO get the 10% discount (same as chimney/coping), retiring £2,222.22 of quoted value. £6,400 cash paid to date, equivalent to £6,622.22 of quoted value — £10,977.78 quoted value remaining. Rubbish removal (£1,200) transferred 10 Aug to pooled skip fund — see that row, not double-counted here.
A7: Contingency | B7: — | C7: 5000 | D7: =SUMIF('Invoice Register'!$B:$B,$A7,'Invoice Register'!$F:$F) -> 480.98 | E7: =SUMIFS('Invoice Register'!$F:$F,'Invoice Register'!$B:$B,$A7,'Invoice Register'!$G:$G,"<>") -> 480.98 | F7: =C7-D7 -> 4519.02 | G7: Covers: fence move/repair labour; soakaway fix before decking; drainage by garage; extra curved-decking labour; cement & bricks; coping condensation-prep (£250, PAID 14 Aug via bank transfer, INV-0288). Luke's labour drawn from this pot attracts the 10% discount (extended 20 Jul) — note the condensation-prep item was paid by bank transfer, not cash, so discount doesn't apply there. See Contingency Drawdown sheet.
A8: Chimney repair | B8: LG Building and Roofing Ltd | C8: 4700 | D8: =SUMIF('Invoice Register'!$B:$B,$A8,'Invoice Register'!$F:$F) -> 4700.01 | E8: =SUMIFS('Invoice Register'!$F:$F,'Invoice Register'!$B:$B,$A8,'Invoice Register'!$G:$G,"<>") -> 4700.01 | F8: =C8-D8 -> -0.01 | G8: Quoted 2 Jun: £3,200 labour (invoiced full price, INV-0286) + £1,500 scaffold share. Cowl upgrade (£62.90) and TP account materials reclassified out 17 Aug — see Contingency and Materials (pooled) rows. This is now a clean quote-vs-actual labour figure.
A9: Coping stones repair | B9: LG Building and Roofing Ltd | C9: 5310 | D9: =SUMIF('Invoice Register'!$B:$B,$A9,'Invoice Register'!$F:$F) -> 5310 | E9: =SUMIFS('Invoice Register'!$F:$F,'Invoice Register'!$B:$B,$A9,'Invoice Register'!$G:$G,"<>") -> 5310 | F9: =C9-D9 -> 0 | G9: Quoted 3 Jun: £3,800 labour, confirmed 7 Aug as £3,610 blended (50% cash @10% disc. + 50% invoiced) + £1,700 scaffold share. Condensation-prep (£276.42) and TP account materials share (£277.29) reclassified out — see Contingency and Materials (pooled) rows. RISK: coping-stone damage on removal could substantially increase cost.
A10: Materials (pooled) | B10: Merchant trade accounts | C10: 1130 | D10: =SUMIF('Invoice Register'!$B:$B,$A10,'Invoice Register'!$F:$F) -> 1120.69 | E10: =SUMIFS('Invoice Register'!$F:$F,'Invoice Register'!$B:$B,$A10,'Invoice Register'!$G:$G,"<>") -> 1120.69 | F10: =C10-D10 -> 9.31 | G10: Pooled chimney (£480) + coping (£650) materials budget — decision 20 Jul. Purchased via merchant trade accounts (Dry Lining Supplies, Travis Perkins etc.), cleared on receipts. Detail on Materials Receipts sheet.
A11: Rubbish removal (pooled skips) | B11: Skip Hire Comparison Ltd / future providers | C11: 1360 | D11: =SUMIF('Invoice Register'!$B:$B,$A11,'Invoice Register'!$F:$F) -> 780 | E11: =SUMIFS('Invoice Register'!$F:$F,'Invoice Register'!$B:$B,$A11,'Invoice Register'!$G:$G,"<>") -> 780 | F11: =C11-D11 -> 580 | G11: Transferred 10 Aug from chimney/coping/decking rubbish-removal quotes (£80+£80+£1,200). Original skip (Skip Hire Comparison Ltd) cancelled 11 Aug, refunded — replaced same-day by Elmbridge Mini Skips (2 skips, £780 total, settled 12 Aug). Provisional — more skips expected, especially during decking. Detail on Skip Hire Log sheet.
A12: Core project (Luke's ~£56,800 outline) | C12: =C5+C6+C7 -> 54828.99 | D12: =D5+D6+D7 -> 39109.97 | E12: =E5+E6+E7 -> 39109.97 | F12: =F5+F6+F7 -> 15719.02
A13: Chimney + coping incl. pooled materials | C13: =C8+C9+C10 -> 11140 | D13: =D8+D9+D10 -> 11130.7 | E13: =E8+E9+E10 -> 11130.7 | F13: =F8+F9+F10 -> 9.3
A14: PROJECT TOTAL | C14: =C11+C12+C13 -> 67328.99 | D14: =D11+D12+D13 -> 51020.67 | E14: =E11+E12+E13 -> 51020.67 | F14: =F11+F12+F13 -> 16308.32
A15: Contingency remaining: | B15: ='Contingency Drawdown'!$D$4 -> 4519.02

Sheet Budget vs Actual
A1: Spinney External Works — Budget vs Actual
A2: Snapshot as of 17 Aug 2026 (Week 5) — refresh narrative each batched update session; table figures pull from Summary sheet.
A4: Snapshot
A5: Week 5 — overall, we are running close to plan. Chimney, coping, and decking materials all landed on or under quote; decking labour's first stage matches the quoted rate exactly. Materials pool is back under its cap after a refund. Contingency is barely touched. Nothing here suggests a budget problem.
A7: • Chimney | B7: £0 variance — labour invoiced at the full quoted £3,200, no discount applied (non-cash terms).
A8: • Coping | B8: £190 UNDER quote — half the labour was settled in cash at the agreed 10% discount (£1,710 vs £1,900), the other half invoiced at full price. This is the one place the discount policy shows up as a measurable saving.
A9: • Decking (labour + V4 materials) | B9: Materials fully paid to the V4 proforma exactly. Labour: Stage 1 (£4,400) invoiced full price, plus a £2,000 cash instalment (4 Sep, 10% discount applies) — £6,400 paid so far, £11,200 quoted value remaining across future stages.
A10: • Scaffold (pooled, chimney + coping combined) | B10: £0 variance — this was never split-quoted per workstream, just one £3,200 job (£2,000 paid on erection, £1,200 due on strike). Treating it as its own pooled line avoids implying a false per-workstream comparison.
A11: • Materials (pooled, chimney + coping) | B11: Back under the £1,130 cap — a £72.23 refund from Dry Lining Supplies (unused monocouche + other returned items) landed 19 Aug, more than offsetting the earlier £62.90 overage from pooling Luke's Travis Perkins account purchases.
A12: • Rubbish removal (pooled, all 3 workstreams) | B12: £780 spent of £1,360 so far — looks healthy, but this needs a caveat: decking's £1,200 share (88% of the pool) hasn't been tested yet, and the two skips used so far carried spoil from chimney, coping, AND the soakaway/decking-prep groundworks, not cleanly attributable to any one workstream.
A13: • Contingency | B13: £480.98 drawn of the £5,000 pot (condensation-prep £276.42 + chimney cowl upgrade £62.90 + V4 screw top-up £141.66) — £4,519.02 remaining. All three are genuine scope additions beyond the original quotes, which is exactly what this pot is for.
A15: Budget vs Actual — detail
A16: Cost centre | B16: Quote / Budget £ | C16: Actual £ | D16: Variance £ | E16: Note
A17: Chimney (labour) | B17: 3200 | C17: 3200 | D17: 0 | E17: Invoiced full price (INV-0286) — non-cash, no discount
A18: Coping (labour) | B18: 3800 | C18: 3610 | D18: -190 | E18: 50% cash @10% disc. + 50% invoiced — favourable
A19: Decking (labour) | B19: 17600 | C19: 6400 | D19: -11200 | E19: Stage 1 (£4,400, invoiced, full price) + cash instalment (£2,000, 10% discount, retires £2,222.22 of quoted value) — £11,200 quoted value remaining, mix of future cash/invoice TBC.
A20: Decking materials (V4) | B20: 32228.99 | C20: 32228.99 | D20: 0 | E20: Proforma matched exactly, paid in full 9 Jul
A21: Scaffold (pooled, chimney+coping) | B21: 3200 | C21: 3200 | D21: 0 | E21: Never split-quoted — one combined job. £2,000 paid, £1,200 due on strike
A22: Materials (pooled, chimney+coping) | B22: 1130 | C22: 1120.69 | D22: -9.31 | E22: Back under the £1,130 cap after a £72.23 refund from Dry Lining Supplies (unused monocouche + other returned items) landed 19 Aug — was £62.92 over before the refund.
A23: Rubbish removal (pooled, all 3 workstreams) | B23: 1360 | C23: 780 | D23: -580 | E23: Decking's £1,200 share largely untested — see snapshot caveat
A24: Contingency | B24: 5000 | C24: 480.98 | D24: -4519.02 | E24: £480.98 drawn (condensation-prep £276.42 + chimney cowl £62.90 + V4 screw top-up £141.66) — £4,519.02 remaining. Variance here just means 'not yet drawn', not a saving.
A25: TOTAL (as spent/committed to date) | B25: 67518.99 | C25: 51020.66 | D25: -16498.33 | E25: Contingency now included at its £5,000 named budget value, matching Summary's convention.
A27: Reconciliation check
A28: Summary's PROJECT TOTAL uses each cost centre's committed/ceiling figure — for Chimney, Coping, and Decking that's the real actual; for Materials, Rubbish, and Contingency (all pooled/reserve buckets) it's the provisional cap, not what's been spent so far. Recomputed on that same basis below to confirm nothing here is missing or double-counted against Summary.
A30: Chimney (actual) | C30: 4700
A31: Coping (actual) | C31: 5310
A32: Decking labour (actual) | C32: 17600
A33: Decking materials (actual) | C33: 32228.99
A34: Materials pooled (at £1,130 cap, per Summary) | C34: 1130
A35: Rubbish removal pooled (at £1,360 cap, per Summary) | C35: 1360
A36: Contingency (at £5,000 cap, per Summary) | C36: 5000
A37: Recomputed total (Summary basis) | C37: 67328.99
A38: Summary PROJECT TOTAL (committed) | C38: =Summary!C14 -> 67328.99
A39: Difference — should be £0.00 | C39: =67328.99-C38 -> 0

Sheet Invoicing Schedule
A1: Invoicing Schedule — expected invoice events
A2: Terms: 10% labour discount on all Luke phases except decking labour and scaffolding. Chimney & coping settle as SINGLE CASH PAYMENTS on phase completion (agreed Lara/Ryan 20 Jul; TBC with Luke 21 Jul). Log every payment on the Invoice Register — this sheet is expectations, the Register is the record.
A4: # | B4: Cost centre | C4: Trigger event | D4: Payee | E4: Basis | F4: Est. £ | G4: Status | H4: Notes
A5: 1 | B5: Decking materials | C5: Order placed — PAID IN FULL 9 Jul | D5: V4 Wood Flooring Ltd | E5: Invoice V4FQ-15584 | F5: 32228.99 | G5: Paid
A6: 2 | B6: Chimney + Coping (scaffold) | C6: Erection complete (17–18 Jul) — PAID | D6: Scaffolder (via Trevor) | E6: £2,000 cash (of £3,200 combined) | F6: 2000 | G6: Paid | H6: Logged in Register: £937.50 chimney + £1,062.50 coping
A7: 3 | B7: Chimney + Coping (scaffold) | C7: Strike, after Gate 1 sign-off | D7: Scaffolder (via Trevor) | E7: £1,200 cash balance on strike | F7: 1200 | G7: Agreed | H7: Log in Register: £562.50 chimney + £637.50 coping
A8: 4 | B8: Chimney repair | C8: INVOICED & PAID 24 Jul (non-cash) | D8: LG Building and Roofing Ltd | E8: £3,200 labour less £111.70 prepaid = £3,088.30. Full price — no discount. | F8: 3200 | G8: Paid | H8: £3,200 labour invoiced & paid 24 Jul (£3,088.30 after £111.70 prepayment deduction). Rubbish removal (£80) transferred 10 Aug to pooled skip fund — no longer owed to Luke.
A9: 5 | B9: Coping stones repair | C9: 50% CASH — PAID 7 Aug | D9: LG Building and Roofing Ltd | E9: 50% of base labour (£1,710.00), 10% cash discount. Based on original £3,800 quote only. | F9: 1710 | G9: Paid | H9: Excludes condensation-prep addition — price not yet finalised (see separate row).
A10: 6 | B10: Coping stones repair | C10: 50% INVOICED — due next week | D10: LG Building and Roofing Ltd | E10: 50% of base labour (£1,900.00) full price. Rubbish removal transferred to pooled skip fund 10 Aug. | F10: 1900 | G10: Paid 14 Aug | H10: INVOICED 13 Aug as part of Luke's INV-0288 (£2,150 total, due 14 Aug) — that invoice also includes the £250 condensation-prep item, now tracked separately under Contingency. No longer includes rubbish removal — see Rubbish removal (pooled skips) row.
A11: 7 | B11: Coping stones repair | C11: Additional scope — condensation-escape prep (price TBC) | D11: LG Building and Roofing Ltd | E11: Combined labour + materials, Luke's estimate — price NOT yet finalised | F11: 250 | G11: Price TBC — not finalised (7 Aug) | H11: Terms confirmed 7 Aug: 100% cash (labour + materials) once priced. Separate from the base coping 50/50 split.
A12: 8 | B12: Decking labour | C12: Stage 1 (25%, INV-0289) PAID 20 Aug — 4 stages confirmed, flat 25% each | D12: LG Building and Roofing Ltd | E12: £17,600 labour total across stages, at quoted rates. CORRECTED 4 Sep: cash payments DO get the 10% discount (same as chimney/coping) — only invoiced stages are full price. Rubbish removal transferred to pooled skip fund. | F12: 17600 | G12: Stage 1 paid, 25% down | H12: Stage 1 (£4,400) invoiced/paid 20 Aug, full price. Cash top-up (£2,000, 4 Sep) retires £2,222.22 of quoted value at the 10% discount. Remaining quoted value: £10,977.78. Exact milestone triggers for future stages still TBC.
A13: 9 | B13: Materials (pooled) | C13: Periodic — on receipts | D13: Merchant trade accounts (Dry Lining Supplies, TP etc.) | E13: Pooled £1,130 budget (chimney £480 + coping £650) | F13: 1130 | G13: Agreed in principle | H13: Log each receipt in Register + Materials Receipts sheet
A14: 10 | B14: Contingency | C14: Rainy-day tasks 100% on completion; named extras as incurred | D14: LG Building / merchants | E14: £5,000 pot — fence labour, soakaway fix, garage drainage, curved-deck extras, cement & bricks. Labour at 10% discount | F14: 5000 | G14: Approved 20 Jul — first draw 14 Aug | H14: Curved-decking extra labour discount TBC. First draw: coping condensation-prep (£250, named purpose #6), paid 14 Aug via bank transfer, INV-0288. £4,750 of the £5,000 pot remaining. Each drawdown also on Contingency Drawdown sheet.
A15: 11 | B15: Chimney repair | C15: Additional material — stainless steel cowl | D15: StoveWorldUK (paid direct, project account) | E15: Order #147399, 10 Aug 2026 | F15: 62.9 | G15: Paid | H15: 5" stainless steel chimney pot hanger cowl — replaces original spec (decision logged 7 Aug), prevents rusting. Arrives Fri 14 Aug — likely last item before scaffold strike.
A16: 11 | B16: Rubbish removal (pooled skips) | C16: Periodic — as skips are needed | D16: Skip Hire Comparison Ltd / future providers | E16: Provisional £1,360 (transferred from chimney/coping/decking rubbish quotes) | F16: 1360 | G16: Approved 10 Aug | H16: First skip £344.16 paid 10 Aug, delivery 11 Aug. More skips expected during decking — budget is provisional, watch like the materials pool. Log each skip in Register + Skip Hire Log sheet.
E17: SCHEDULE TOTAL (all rows): | F17: =SUM(F5:F16) -> 67641.89
E18: Summary tab committed total: | F18: =Summary!$C$14 -> 67328.99
E19: Difference (must be £0.00): | F19: =F17-F18 -> 312.9

Sheet Cost Lines
A1: Cost Lines — every line item from LG estimates and the V4 invoice
A2: Source documents: LG chimney estimate 2 Jun 2026 · LG coping estimate 3 Jun 2026 · LG decking estimate 3 Jun 2026 · V4 invoice V4FQ-15584, 9 Jul 2026.
A4: Cost centre | B4: Supplier | C4: Line item | D4: Qty | E4: Unit £ | F4: Line total £ | G4: VAT | H4: Payment route | I4: Notes
A5: Chimney repair | B5: LG Building | C5: Labour — remove render, k-rend sealer, base + top coat, render crown, storm-dry cream | F5: 3200 | G5: No VAT | H5: LG invoice | I5: INVOICED 24 Jul (INV-0286), full price £3,200 less £111.70 prepaid = £3,088.30. Non-cash, so 10% discount does not apply. Rubbish removal £80 outstanding.
A6: Chimney repair | B6: Scaffolder (direct) | C6: Tubular scaffolding — all four sides of chimney and crown | F6: 1500 | G6: Inc VAT | H6: Paid directly | I6: Combined £3,200, cash terms (20 Jul): £2,000 paid following erection; £1,200 balance on strike.
A7: Materials (pooled) | B7: Merchant trade accounts | C7: Materials (chimney estimate — pooled 20 Jul) | F7: 480 | G7: Inc VAT | H7: Trade accounts — cleared on receipts
A8: Chimney repair | B8: LG Building | C8: Rubbish removal | F8: 0 | G8: Inc VAT | H8: LG invoice | I8: TRANSFERRED 10 Aug to pooled Rubbish removal (skips) fund — family now supplies skips directly rather than Luke arranging disposal. No longer owed to Luke.
A9: Coping stones repair | B9: LG Building | C9: Labour — remove/reset copings, slate cap, render, lead flashings to parapet rear | F9: 3610 | G9: No VAT | H9: LG invoice | I9: CONFIRMED 7 Aug, based on original £3,800 quote: 50% cash (£1710.00 @ 10% discount) due same day, 50% invoiced (£1900.00 full price) due next week, timed after back gutters are complete — see Invoicing Schedule. RISK: coping-stone damage on removal could substantially increase cost. Condensation-prep addition (£250) reclassified to Contingency 13 Aug — no longer part of this total.
A10: Coping stones repair | B10: Scaffolder (direct) | C10: Tubular scaffolding with winch system | F10: 1700 | G10: Inc VAT | H10: Paid directly | I10: Combined £3,200, cash terms (20 Jul): £2,000 paid following erection; £1,200 balance on strike.
A11: Materials (pooled) | B11: Merchant trade accounts | C11: Materials (coping estimate — pooled 20 Jul) | F11: 650 | G11: Inc VAT | H11: Trade accounts — cleared on receipts
A12: Coping stones repair | B12: LG Building | C12: Rubbish removal | F12: 0 | G12: Inc VAT | H12: LG invoice | I12: TRANSFERRED 10 Aug to pooled Rubbish removal (skips) fund. Removed from next week's invoice (now £1,900, not £1,980).
A13: Decking labour | B13: LG Building | C13: Labour — remove old decking & frame, construct composite frame, install deck to spec | F13: 17600 | G13: No VAT | H13: LG invoice | I13: RISK: pending structure/ground assessment. CORRECTED 4 Sep: cash payments DO get the 10% discount (same as chimney/coping) — only invoiced stages are full price. Progress: Stage 1 (£4,400) invoiced 20 Aug + £2,000 cash instalment 4 Sep (retires £2,222.22 of quoted value) — £6,400 cash paid to date, equivalent to £6,622.22 of quoted value — £10,977.78 quoted value remaining.
A14: Decking labour | B14: LG Building | C14: Rubbish removal (8-yard skips ×2, possibly 3) | F14: 0 | G14: Inc VAT | H14: LG invoice | I14: TRANSFERRED 10 Aug to pooled Rubbish removal (skips) fund.
A15: Decking materials | B15: V4 Wood Flooring | C15: Millboard Ashwood 176mm Moulded Lastane (144.90 m²) | D15: 230 | E15: 66.49 | F15: 15292.7 | G15: In net | H15: V4 invoice — PAID
A16: Decking materials | B16: V4 Wood Flooring | C16: Millboard Ashwood Moulded Lastane — MFN360H | D16: 18 | E16: 58.09 | F16: 1045.62 | G16: In net | H16: V4 invoice — PAID
A17: Decking materials | B17: V4 Wood Flooring | C17: Millboard Ashwood Moulded Lastane — MEBB360H (flexible bullnose) | D17: 15 | E17: 72.25 | F17: 1083.75 | G17: In net | H17: V4 invoice — PAID | I17: For curved upper level
A18: Decking materials | B18: V4 Wood Flooring | C18: Millboard Step Edge — Ashwood Moulded Lastane | D18: 15 | E18: 59.89 | F18: 898.35 | G18: In net | H18: V4 invoice — PAID
A19: Decking materials | B19: V4 Wood Flooring | C19: Stainless steel screws 45mm — boxes | D19: 24 | E19: 32.08 | F19: 770 | G19: In net | H19: V4 invoice — PAID
A20: Decking materials | B20: V4 Wood Flooring | C20: Durafix Trimhead 35mm SS screws — box of 100 (FT35P100) | D20: 6 | E20: 10.25 | F20: 61.5 | G20: In net | H20: V4 invoice — PAID
A21: Decking materials | B21: V4 Wood Flooring | C21: Plas-Pro bearer/joist black 3.0m 50×125mm composite (P1205B300) | D21: 266 | E21: 28.4 | F21: 7554.4 | G21: In net | H21: V4 invoice — PAID | I21: Subframe — the bulk of the tonnage
A22: Decking materials | B22: V4 Wood Flooring | C22: Subframe hexhead screws — box of 50 (FH90P050) | D22: 16 | E22: 7.87 | F22: 125.92 | G22: In net | H22: V4 invoice — PAID | I22: Original 16 boxes delivered in full, confirmed 12 Aug. TOP-UP REQUESTED 20 Aug: Luke has asked for 15 more boxes (same item, FH90P050) — substructure screw consumption running ahead of the original estimate. Not yet ordered/invoiced. Estimated cost £141.66 inc VAT (15 x £7.87 + 20% VAT, matching original per-unit price) — treat as V4 Phase 3 once ordered. Not yet added to committed total.
A23: Decking materials | B23: V4 Wood Flooring | C23: Millboard touch-up paint — Ashwood (AP500H) | D23: 1 | E23: 15 | F23: 15 | G23: In net | H23: V4 invoice — PAID
A24: Decking materials | B24: V4 Wood Flooring | C24: Millboard multi-spacer — pack of 10 (FP36P010) | D24: 1 | E24: 10.25 | F24: 10.25 | G24: In net | H24: V4 invoice — PAID
A25: Decking materials | B25: V4 Wood Flooring | C25: VAT on order | F25: 5371.5 | G25: VAT | H25: V4 invoice — PAID | I25: Net £26,857.49 + VAT = £32,228.99
A26: Contingency | B26: TBC | C26: Contingency pot — fence labour, garage drainage, curved-deck labour, cement & bricks, coping condensation-prep (£250, reclassified 13 Aug). Soakaway fix cancelled 1 Sep, nothing drawn. Pipe investigation resolved 4 Sep — no leak, no repair needed, no draw required. | F26: 5000 | G26: — | H26: As incurred | I26: Track on Contingency Drawdown sheet. Labour invoices from this pot at 10% discount (extended 20 Jul); materials (cement/bricks) full price. Curved-decking extra labour: discount status TBC with Luke. Coping condensation-prep (£250) added as named purpose #6, 13 Aug — payment method (cash vs invoice) pending confirmation.
A27: Contingency | B27: LG Building and Roofing Ltd | C27: Named purpose #6 — Coping condensation-escape prep: re-bed 3 bricks; reinforce parapet corners with fibreglass mesh; fit 4 weep holes to front face above internal damp-course membrane (slate DPC capped in plastic DPM). Reclassified from Coping 13 Aug — same item, moved to keep coping's committed total accurate rather than inflate it. | F27: 250 | G27: TBC | H27: Contingency drawdown | I27: PRICED 13 Aug via Luke's invoice INV-0288: £250. Terms originally agreed as 100% cash; confirmed 14 Aug instead paid via bank transfer, bundled with the coping £1,900 balance. PAID 14 Aug.
A28: Contingency | B28: StoveWorldUK | C28: Named purpose #7 — Chimney cowl upgrade: 5" Stainless Steel Chimney Pot Hanger Cowl (order #147399), replaces original spec | D28: 1 | E28: 62.9 | F28: 62.9 | G28: Inc VAT | H28: Paid direct by Ryan (project account) | I28: Decision logged 7 Aug (stainless steel, prevent rusting). Cost finalised 10 Aug, received 12 Aug, fitted 17 Aug. RECLASSIFIED 17 Aug from Chimney to Contingency — genuine scope addition beyond the original quote, same treatment as coping condensation-prep (#6). Paid direct by Ryan.
A29: Materials (pooled) | B29: LG Building and Roofing Ltd (Travis Perkins account) | C29: Luke's Travis Perkins account materials, 3 invoices 17 Jul-5 Aug (render/masonry consumables + lead flashing) — pooled with chimney+coping materials, same simplified treatment as Dry Lining Supplies. | F29: 481.26 | G29: Inc VAT | H29: Reimbursement to Luke | I29: SIMPLIFIED 18 Aug: previously split chimney/coping 50/50 — now pooled as one line, consistent with how Dry Lining Supplies purchases were always treated (not split by workstream). DPC roll (£26.42) stays separately in Contingency (purpose #6, condensation-prep) as it's additional scope, not pool materials.
C30: (merged into row above, 18 Aug) | F30: 0 | G30: Inc VAT | H30: Reimbursement to Luke | I30: RECLASSIFIED 17 Aug: lead flashing reattributed from chimney to coping (original quote explicitly scopes 'lead flashings to parapet rear' under coping's labour). Both items within originally-quoted scope, so routed through Materials pool per agreed rule rather than Coping's own Cost Lines.
A31: Contingency | B31: V4 Wood Flooring Ltd | C31: Named purpose #8 — V4 screw top-up: 15 more boxes of Timberfix structural subframe screws (FH90P050), quote V4FQ-17702 | F31: 141.66 | G31: Inc VAT | H31: Bank transfer | I31: Requested by Luke 20 Aug, ordered 24 Aug, PAID. Substructure screw consumption ran ahead of the original 16-box estimate. Same item/supplier as the original V4 order, but treated as an additional-scope purchase per Ryan's direction — routed through Contingency rather than inflating the Decking materials (V4) line, which stays matched to its original proforma.
A32: Rubbish removal (pooled skips) | B32: Skip Hire Comparison Ltd / future providers | C32: Provisional pooled budget — transferred from chimney (£80) + coping (£80) + decking (£1,200) rubbish-removal quotes, 10 Aug. Family now supplies skips directly. | F32: 1360 | G32: — | H32: Paid direct by Ryan (project account) | I32: First skip ordered 10 Aug (£344.16, 8yd, delivery 11 Aug). More skips expected during decking — budget is provisional, to be watched like the materials pool. Detail on Skip Hire Log sheet.
C33: TOTAL (all lines) | F33: =SUM(F5:F32) -> 68264.81

Sheet Invoice Register
A1: Invoice & Payment Register — add a row per invoice received
A2: Yellow cells are inputs. Cost centre must match the Summary sheet names exactly (dropdown-free by design — copy from row 5). Paid date empty = outstanding.
A4: Invoice date | B4: Cost centre | C4: Supplier | D4: Reference | E4: Description | F4: Amount £ (gross) | G4: Paid date | H4: Method | I4: Notes
A5: 46212 | B5: Decking materials | C5: V4 Wood Flooring Ltd | D5: V4FQ-15584 | E5: Millboard Ashwood decking + Plas-Pro subframe, fixings (144.9 m²) | F5: 32228.99 | G5: 46212 | H5: Amex | I5: Paid in full at order
A6: 46223 | B6: Materials (pooled) | C6: Dry Lining Supplies Ltd | D6: RECB000NNIVB49XWEXOG | E6: Render materials (shared chimney+coping): mesh, Weberend Aid ×6, beads, SBR, rubble sacks | F6: 311.98 | G6: 46223 | H6: Pay By Link | I6: Project-materials share of £423.69 receipt
A7: 46223 | B7: Chimney repair | C7: Dry Lining Supplies Ltd | D7: RECB000NNIVB49XWEXOG | E7: Folding work platform 600mm — Luke's equipment, non-project | F7: 111.71 | G7: 46223 | H7: Pay By Link | I7: PREPAYMENT vs chimney phase-start invoice: pay £1,528.29 of the £1,640 when it lands
A8: 46223 | B8: Chimney repair | C8: Scaffolder (via Trevor) | D8: Cash | E8: Scaffold erection payment — chimney share (pro-rata of £2,000 cash) | F8: 937.5 | G8: 46223 | H8: Cash | I8: £2,000 paid following erection 17–18 Jul; amend date cell if payment day differed
A9: 46227 | B9: Chimney repair | C9: LG Building and Roofing Ltd | D9: INV-0286 | E9: Chimney labour, invoiced (£3,200 less £111.70 work-platform prepayment). Rubbish removal £80 NOT included — outstanding. | F9: 3088.3 | G9: 46227 | H9: Bank transfer | I9: Invoiced (non-cash) — full price, no 10% discount. £80 rubbish removal still outstanding.
A10: 46225 | B10: Materials (pooled) | C10: Dry Lining Supplies | D10: 914751798 | E10: Weber Pral M Silver Pearl x10, Plastic 15mm Stop Bead 3m x3 (shared render finish) | F10: 162.96 | G10: 46225 | H10: Pay By Link | I10: Second pooled-materials trip
A11: 46238 | B11: Materials (pooled) | C11: Dry Lining Supplies Ltd | D11: RECB000NNIVB6DIPDFCW | E11: Weberend Ocr x3, Weber Pral M Silver Pearl x4, Stop Bead x6, Drip Bead x2, Sikabond SBR x1 (coping render) | F11: 148.53 | G11: 46238 | H11: Pay By Link | I11: Coping stones render materials. Receipt received 4 Aug (till David, 07:31).
A12: 46241 | B12: Coping stones repair | C12: LG Building and Roofing Ltd | D12: Cash | E12: Coping 50% cash labour payment (base labour only, 10% discount). Condensation-prep addition NOT included — price not yet finalised. | F12: 1710 | G12: 46241 | H12: Cash | I12: Confirmed 7 Aug: 50% cash / 50% invoice split on original £3,800 quote. Remainder £1,980.00 (incl. rubbish) to be invoiced next week. £250 addition separate, price TBC.
A13: 46244 | B13: Contingency | C13: StoveWorldUK | D13: Order #147399 | E13: 5" Stainless Steel Chimney Pot Hanger Cowl — replaces original spec | F13: 62.9 | G13: 46244 | H13: Card (Ryan, project account) | I13: Named purpose #7 (chimney cowl upgrade). RECLASSIFIED 17 Aug from Chimney repair — genuine scope addition beyond original quote.
A14: 46244 | B14: Rubbish removal (pooled skips) | C14: Skip Hire Comparison Ltd | D14: D81F29CE-0002 | E14: 8 cubic yard skip, delivery 11 Aug | F14: 344.16 | G14: 46244 | H14: Card (Ryan, project account) | I14: First skip. Replaces chimney/coping/decking rubbish-removal quotes — transferred to this pooled fund 10 Aug. CANCELLED 11 Aug — original supplier delayed delivery; refunded in full (receipt 3362-9782), see row below.
A15: 46245 | B15: Rubbish removal (pooled skips) | C15: Skip Hire Comparison Ltd | D15: Refund 3362-9782 (orig. inv. D81F29CE-0002) | E15: Refund — original skip cancelled after supplier delivery delay | F15: -344.16 | G15: 46247 | H15: — | I15: Refund confirmed received 13 Aug 2026 — cleared in 2 working days, faster than the 5-10 day estimate.
A16: 46245 | B16: Rubbish removal (pooled skips) | C16: Elmbridge Mini Skips | D16: INV-11373 / ref 25996 | E16: 8 cubic yard skip — delivery, replaces cancelled Skip Hire Comparison booking | F16: 390 | G16: 46246 | H16: TBC | I16: Settled 12 Aug 2026. Skip delivered filled 11 Aug; collected and swapped for empty 12 Aug.
... A30: 46269 | B30: Decking labour | C30: LG Building and Roofing Ltd | D30: Cash | E30: Decking labour — cash instalment (10% discount applies) | F30: 2000 | G30: 46269 | H30: Cash | I30: Retires £2,222.22 of quoted value at the 10% cash discount (£2,000 paid = 90%). Not a full 25% stage — partial/interim payment. Total paid to date: £6,400 (Stage 1 £4,400 invoiced + this £2,000 cash). Quoted value remaining: £10,977.78.

Sheet Skip Hire Log
A1: Skip Hire Log — pooled rubbish-removal drawdown
A2: Provisional pooled budget £1,360 (transferred 10 Aug from chimney £80 + coping £80 + decking £1,200 rubbish-removal quotes). Family now supplies skips directly rather than Luke arranging disposal. Log every skip here AND on the Invoice Register (cost centre: Rubbish removal (pooled skips)) — this sheet is skip detail, the Register is the money record. Unlike the materials pool, more skips are expected — budget may need topping up.
A4: Opening pool: | B4: 1360 | C4: Remaining: | D4: =B4-SUM(E8:E40) -> 580
A7: Date | B7: Provider | C7: Skip details | D7: Phase / use | E7: Amount £ | F7: Running remaining £
A8: 46244 | B8: Skip Hire Comparison Ltd | C8: 8 cubic yard, general waste, delivery 11 Aug (ref D81F29CE-0002) — CANCELLED 11 Aug (supplier delayed), refunded in full (receipt 3362-9782) | D8: Above-ground works (chimney/coping) | E8: 344.16 | F8: =IF(E8="","",$B$4-SUM($E$8:E8)) -> 1015.84
A9: 46245 | B9: Skip Hire Comparison Ltd | C9: Refund — cancelled booking, receipt 3362-9782, 5-10 working days to clear | D9: Refund (cancelled skip) | E9: -344.16 | F9: =IF(E9="","",$B$4-SUM($E$8:E9)) -> 1360
A10: 46245 | B10: Elmbridge Mini Skips | C10: 8 cubic yard, delivery — filled, awaiting exchange (INV-11373, ref 25996) | D10: Above-ground works (chimney/coping) | E10: 390 | F10: =IF(E10="","",$B$4-SUM($E$8:E10)) -> 970
A11: 46246 | B11: Elmbridge Mini Skips | C11: 8 cubic yard, exchange — collects filled skip, delivers empty (INV-11375, ref 26030) | D11: Above-ground works (chimney/coping) | E11: 390 | F11: =IF(E11="","",$B$4-SUM($E$8:E11)) -> 580
F12: =IF(E12="","",$B$4-SUM($E$8:E12))
F13: =IF(E13="","",$B$4-SUM($E$8:E13))
F14: =IF(E14="","",$B$4-SUM($E$8:E14))
F15: =IF(E15="","",$B$4-SUM($E$8:E15))
F16: =IF(E16="","",$B$4-SUM($E$8:E16))
F17: =IF(E17="","",$B$4-SUM($E$8:E17))
F18: =IF(E18="","",$B$4-SUM($E$8:E18))
F19: =IF(E19="","",$B$4-SUM($E$8:E19))
F20: =IF(E20="","",$B$4-SUM($E$8:E20))
F21: =IF(E21="","",$B$4-SUM($E$8:E21))
F22: =IF(E22="","",$B$4-SUM($E$8:E22))
F23: =IF(E23="","",$B$4-SUM($E$8:E23))
... F25: =IF(E25="","",$B$4-SUM($E$8:E25))

Sheet Materials Receipts
A1: Materials Receipts — pooled budget drawdown
A2: Pooled budget £1,130 (chimney £480 + coping £650, pooled 20 Jul). Log every merchant receipt here AND on the Invoice Register (cost centre: Materials (pooled)) — this sheet is the pool detail, the Register is the money record. NOTE: pool is over cap after adding Luke's Travis Perkins account materials (now paid in full, 18 Aug) — flagged deliberately, not hidden; cap left at £1,130 rather than raised. PENDING 18 Aug: 5 bags of unused monocouche (Weber Pral M) returned to Dry Lining Supplies — refund expected within a couple of working days. Calculated from receipts: Weber Pral M Silver Pearl consistently £12.62/bag inc VAT (£126.20/10 on 22 Jul, £50.48/4 on 4 Aug) × 5 bags = £63.10 expected refund. Not yet logged as received — add Paid date once the credit note actually lands.
A4: Opening pool: | B4: 1130 | C4: Remaining: | D4: =B4-SUM(E8:E40) -> -62.9
A7: Date | B7: Merchant | C7: Items (summary) | D7: Phase / use | E7: Amount £ | F7: Running remaining £
A8: 46223 | B8: Dry Lining Supplies Ltd | C8: Render mesh, Weberend Aid ×6, angle/stop beads, rubble sacks, Bond It SBR 5l (project share; £111.71 platform excluded — Luke's equipment) | D8: Render (chimney + coping, shared) | E8: 311.98 | F8: =IF(E8="","",$B$4-SUM($E$8:E8)) -> 818.02
A9: 46225 | B9: Dry Lining Supplies | C9: Weber Pral M Silver Pearl x10 (£126.20), Plastic 15mm Stop Bead 3m x3 (£9.60), inc VAT | D9: Render finish (chimney + coping, shared) | E9: 162.96 | F9: =IF(E9="","",$B$4-SUM($E$8:E9)) -> 655.06
A10: 46238 | B10: Dry Lining Supplies Ltd | C10: Weberend Ocr x3 (£29.13), Weber Pral M Silver Pearl x4 (£50.48), Stop Bead x6 (£19.20), Drip Bead x2 (£7.42), Sikabond SBR (£17.54), inc VAT | D10: Render (coping stones) | E10: 148.53 | F10: =IF(E10="","",$B$4-SUM($E$8:E10)) -> 506.53
A11: 46250 | B11: SoftWash UK | C11: Render Cleaner Gel X Pro, 5 Litres (order F4UJ62VLQ) | D11: Render cleanup (chimney + coping, shared) | E11: 47.99 | F11: =IF(E11="","",$B$4-SUM($E$8:E11)) -> 458.54
A12: 46251 | B12: LG Building and Roofing Ltd (Travis Perkins account) | C12: Render/masonry consumables + lead flashing, 3 invoices 17 Jul-5 Aug (1047678330 / 1047972816 / 1048887075) — pooled, not split by workstream | D12: Render (chimney + coping, pooled) | E12: 481.26 | F12: =IF(E12="","",$B$4-SUM($E$8:E12)) -> -22.72
F13: =IF(E13="","",$B$4-SUM($E$8:E13))
A14: 46244 | B14: LG Building and Roofing Ltd (Travis Perkins account, INV 1049120278) | C14: Cleaning/finishing consumables (trigger spray, decorating cloth) — pooled, not split by workstream | D14: Render (chimney + coping, pooled) | E14: 40.18 | F14: =IF(E14="","",$B$4-SUM($E$8:E14)) -> -62.9
F15: =IF(E15="","",$B$4-SUM($E$8:E15))
F16: =IF(E16="","",$B$4-SUM($E$8:E16))
F17: =IF(E17="","",$B$4-SUM($E$8:E17))
F18: =IF(E18="","",$B$4-SUM($E$8:E18))
F19: =IF(E19="","",$B$4-SUM($E$8:E19))
F20: =IF(E20="","",$B$4-SUM($E$8:E20))
F21: =IF(E21="","",$B$4-SUM($E$8:E21))
F22: =IF(E22="","",$B$4-SUM($E$8:E22))
F23: =IF(E23="","",$B$4-SUM($E$8:E23))
F24: =IF(E24="","",$B$4-SUM($E$8:E24))
F25: =IF(E25="","",$B$4-SUM($E$8:E25))

Sheet Contingency Drawdown
A1: Contingency Drawdown — £5,000 pot (agreed Lara/Luke, 1 Jul 2026)
A2: Named purposes: fence move/repair labour · ~~soakaway fix before decking~~ CANCELLED 1 Sep, cost-benefit not worth it, nothing drawn · drainage by the garage · additional curved-decking labour · cement & bricks · coping condensation-prep (£276.42, purpose #6) · chimney cowl upgrade (£62.90, purpose #7) · V4 screw top-up (£141.66, purpose #8). Luke's labour from this pot invoiced at 10% discount (extended 20 Jul) — condensation-prep, the cowl, and the screw top-up were all bank transfer/direct paid, not cash, so no discount applied to any of them. Curved-decking extra labour discount status TBC. Pipe investigation (task 2.2) RESOLVED 4 Sep: no leaking pipe found — damp ground was condensation trapped under old decking, not a plumbing fault. No repair needed, purpose #9 not required. Excavation continues for decking widening (straight-line, distinct from curved-decking-labour purpose above), tracked under decking substructure, not contingency.
A4: Opening pot: | B4: 5000 | C4: Remaining: | D4: =B4-SUM(D8:D40) -> 4519.02
A7: Date | B7: Purpose | C7: Supplier / detail | D7: Amount £ | E7: Running remaining £
A8: 46248 | B8: Coping condensation-escape prep (named purpose #6) | C8: LG Building and Roofing Ltd (INV-0288) | D8: 250 | E8: =IF(D8="","",$B$4-SUM($D$8:D8)) -> 4750
A9: 46251 | B9: Coping condensation-prep material (Damplas DPC roll, named purpose #6) | C9: LG Building and Roofing Ltd (Travis Perkins account) | D9: 26.42 | E9: =IF(D9="","",$B$4-SUM($D$8:D9)) -> 4723.58
A10: 46251 | B10: Chimney cowl upgrade — stainless steel (named purpose #7) | C10: StoveWorldUK (order #147399) | D10: 62.9 | E10: =IF(D10="","",$B$4-SUM($D$8:D10)) -> 4660.68
A11: 46258 | B11: V4 screw top-up — 15 boxes structural subframe screws (named purpose #8) | C11: V4 Wood Flooring Ltd (V4FQ-17702) | D11: 141.66 | E11: =IF(D11="","",$B$4-SUM($D$8:D11)) -> 4519.02
E12: =IF(D12="","",$B$4-SUM($D$8:D12))
E13: =IF(D13="","",$B$4-SUM($D$8:D13))
E14: =IF(D14="","",$B$4-SUM($D$8:D14))
E15: =IF(D15="","",$B$4-SUM($D$8:D15))
E16: =IF(D16="","",$B$4-SUM($D$8:D16))
E17: =IF(D17="","",$B$4-SUM($D$8:D17))
E18: =IF(D18="","",$B$4-SUM($D$8:D18))
E19: =IF(D19="","",$B$4-SUM($D$8:D19))
E20: =IF(D20="","",$B$4-SUM($D$8:D20))
E21: =IF(D21="","",$B$4-SUM($D$8:D21))
E22: =IF(D22="","",$B$4-SUM($D$8:D22))
E23: =IF(D23="","",$B$4-SUM($D$8:D23))
... E25: =IF(D25="","",$B$4-SUM($D$8:D25))
