Workbook

Sheet Summary
A1: Spinney External Works — Budget Summary
A2: Last updated: | B2: 46216 | C2: All figures gross (as payable). Invoiced / Paid pull automatically from the Invoice Register; Contingency remaining pulls from the Drawdown sheet.
A4: Cost centre | B4: Supplier | C4: Committed £ | D4: Invoiced £ | E4: Paid £ | F4: Remaining vs committed £ | G4: Notes
A5: Decking materials | B5: V4 Wood Flooring Ltd | C5: 32228.99 | D5: =SUMIF('Invoice Register'!$B:$B,$A5,'Invoice Register'!$F:$F) -> 32228.99 | E5: =SUMIFS('Invoice Register'!$F:$F,'Invoice Register'!$B:$B,$A5,'Invoice Register'!$G:$G,"<>") -> 32228.99 | F5: =C5-D5 -> 0 | G5: Order amended to all Ashwood + flexible bullnose (1 Jul). PAID IN FULL 9 Jul, ref V4FQ-15584. 25% restocking on over-ordering — unlikely given curved design + offcuts project, but noted.
A6: Decking labour & rubbish | B6: LG Building and Roofing Ltd | C6: 18800 | D6: =SUMIF('Invoice Register'!$B:$B,$A6,'Invoice Register'!$F:$F) -> 0 | E6: =SUMIFS('Invoice Register'!$F:$F,'Invoice Register'!$B:$B,$A6,'Invoice Register'!$G:$G,"<>") -> 0 | F6: =C6-D6 -> 18800 | G6: £17,600 labour (no VAT) + £1,200 rubbish removal. RISK: price 'fairly accurate' pending Luke's structure/ground assessment.
A7: Contingency | B7: — | C7: 5000 | D7: =SUMIF('Invoice Register'!$B:$B,$A7,'Invoice Register'!$F:$F) -> 0 | E7: =SUMIFS('Invoice Register'!$F:$F,'Invoice Register'!$B:$B,$A7,'Invoice Register'!$G:$G,"<>") -> 0 | F7: =C7-D7 -> 5000 | G7: Covers: fence move/repair labour; soakaway fix before decking; drainage by garage; extra curved-decking labour; cement & bricks. Luke's labour drawn from this pot attracts the 10% discount (extended 20 Jul). See Contingency Drawdown sheet.
A8: Chimney repair | B8: LG Building and Roofing Ltd | C8: 4460 | D8: =SUMIF('Invoice Register'!$B:$B,$A8,'Invoice Register'!$F:$F) -> 1049.21 | E8: =SUMIFS('Invoice Register'!$F:$F,'Invoice Register'!$B:$B,$A8,'Invoice Register'!$G:$G,"<>") -> 1049.21 | F8: =C8-D8 -> 3410.79 | G8: Quoted separately (2 Jun). Labour £2,880 (10% discount, 20 Jul) no VAT + £80 rubbish; scaffolding £1,500 share of combined invoice; materials in pooled budget.
A9: Coping stones repair | B9: LG Building and Roofing Ltd | C9: 5200 | D9: =SUMIF('Invoice Register'!$B:$B,$A9,'Invoice Register'!$F:$F) -> 1062.5 | E9: =SUMIFS('Invoice Register'!$F:$F,'Invoice Register'!$B:$B,$A9,'Invoice Register'!$G:$G,"<>") -> 1062.5 | F9: =C9-D9 -> 4137.5 | G9: Quoted separately (3 Jun). Labour £3,420 (10% discount, 20 Jul) no VAT + £80 rubbish; scaffolding £1,700 share. RISK: damage to coping stones on removal could substantially increase cost. Materials in pooled budget.
A10: Materials (pooled) | B10: Merchant trade accounts | C10: 1130 | D10: =SUMIF('Invoice Register'!$B:$B,$A10,'Invoice Register'!$F:$F) -> 311.98 | E10: =SUMIFS('Invoice Register'!$F:$F,'Invoice Register'!$B:$B,$A10,'Invoice Register'!$G:$G,"<>") -> 311.98 | F10: =C10-D10 -> 818.02 | G10: Pooled chimney (£480) + coping (£650) materials budget — decision 20 Jul. Purchased via merchant trade accounts (Dry Lining Supplies, Travis Perkins etc.), cleared on receipts. Detail on Materials Receipts sheet.
A11: Core project (Luke's ~£56,800 outline) | C11: =C5+C6+C7 -> 56028.99 | D11: =D5+D6+D7 -> 32228.99 | E11: =E5+E6+E7 -> 32228.99 | F11: =F5+F6+F7 -> 23800
A12: Chimney + coping incl. pooled materials | C12: =C8+C9+C10 -> 10790 | D12: =D8+D9+D10 -> 2423.69 | E12: =E8+E9+E10 -> 2423.69 | F12: =F8+F9+F10 -> 8366.31
A13: PROJECT TOTAL | C13: =C11+C12 -> 66818.99 | D13: =D11+D12 -> 34652.68 | E13: =E11+E12 -> 34652.68 | F13: =F11+F12 -> 32166.31
A15: Contingency remaining: | B15: ='Contingency Drawdown'!$D$4 -> 5000

Sheet Invoicing Schedule
A1: Invoicing Schedule — expected invoice events
A2: Terms: 10% labour discount on all Luke phases except decking labour and scaffolding. Chimney & coping settle as SINGLE CASH PAYMENTS on phase completion (agreed Lara/Ryan 20 Jul; TBC with Luke 21 Jul). Log every payment on the Invoice Register — this sheet is expectations, the Register is the record.
A4: # | B4: Cost centre | C4: Trigger event | D4: Payee | E4: Basis | F4: Est. £ | G4: Status | H4: Notes
A5: 1 | B5: Decking materials | C5: Order placed — PAID IN FULL 9 Jul | D5: V4 Wood Flooring Ltd | E5: Invoice V4FQ-15584 (Register row 1) | F5: 32228.99 | G5: Paid | H5: All-Ashwood + flexible bullnose; 144.9 m²
A6: 2 | B6: Chimney + Coping (scaffold) | C6: Erection complete (17–18 Jul) — PAID | D6: Scaffolder (direct) | E6: £2,000 in cash (of £3,200 combined) | F6: 2000 | G6: Paid | H6: Logged in Register: £937.50 chimney + £1,062.50 coping (pro-rata of £1,500/£1,700)
A7: 3 | B7: Chimney + Coping (scaffold) | C7: Strike, after Gate 1 sign-off | D7: Scaffolder (direct) | E7: £1,200 cash balance on strike | F7: 1200 | G7: Agreed | H7: Log in Register: £562.50 chimney + £637.50 coping
A8: 4 | B8: Chimney repair | C8: Phase completion — SINGLE cash payment | D8: LG Building and Roofing Ltd | E8: Labour £2,880 (10% disc.) + rubbish £80 = £2,960; less £111.71 prepaid (work platform) | F8: 2960 | G8: Lara/Ryan agreed — TBC Luke 21 Jul | H8: CASH DUE ON COMPLETION: £2,848.29. One-week phase — no interim invoice
A9: 5 | B9: Coping stones repair | C9: Phase completion — SINGLE cash payment | D9: LG Building and Roofing Ltd | E9: Labour £3,420 (10% disc.) + rubbish £80 = £3,500 | F9: 3500 | G9: Lara/Ryan agreed — TBC Luke 21 Jul | H9: CASH DUE ON COMPLETION: £3,500.00
A10: 6 | B10: Decking labour & rubbish | C10: 4–5 stages — triggers TBC with Luke/Lara | D10: LG Building and Roofing Ltd | E10: £18,800 total across stages. EXCLUDED from 10% labour discount | F10: 18800 | G10: Approved 20 Jul | H10: Suggested triggers: start / substructure (a) / Gate 2 / substructure (b) / Gate 3 — to be pinned
A11: 7 | B11: Materials (pooled) | C11: Periodic — on receipts | D11: Merchant trade accounts (Dry Lining Supplies, TP etc.) | E11: Pooled £1,130 budget (chimney £480 + coping £650) | F11: 1130 | G11: Agreed in principle | H11: Log each receipt in Register + Materials Receipts sheet
A12: 8 | B12: Contingency | C12: Rainy-day tasks 100% on completion; named extras as incurred | D12: LG Building / merchants | E12: £5,000 pot — fence labour, soakaway fix, garage drainage, curved-deck extras, cement & bricks. Labour at 10% discount | F12: 5000 | G12: Approved 20 Jul | H12: Curved-decking extra labour discount TBC (decking exclusion boundary). Each drawdown also on Contingency Drawdown sheet
A13: 9 | B13: Materials (pooled) | C13: Periodic — on receipts | D13: Merchant trade accounts (Dry Lining Supplies, TP etc.) | E13: SCHEDULE TOTAL (all rows): | F13: =SUM(F5:F12) -> 66818.99 | G13: Agreed in principle | H13: Pooled £1,130 budget — log each receipt in Register + Materials Receipts sheet
A14: 10 | B14: Contingency | C14: Rainy-day tasks invoiced 100% on completion; named extras as incurred | D14: LG Building / Travis Perkins | E14: Summary tab committed total: | F14: =Summary!$C$13 -> 66818.99 | G14: Approved 20 Jul | H14: Rainy-day tasks invoiced 100% on completion, labour less 10%. Curved-decking extra labour discount TBC. Each drawdown also logged on Contingency Drawdown sheet
E15: Difference (must be £0.00): | F15: =F13-F14 -> 0
E16: Summary tab committed total: | F16: =Summary!$C$13 -> 66818.99
E17: Difference (must be £0.00): | F17: =F15-F16 -> -66818.99

Sheet Cost Lines
A1: Cost Lines — every line item from LG estimates and the V4 invoice
A2: Source documents: LG chimney estimate 2 Jun 2026 · LG coping estimate 3 Jun 2026 · LG decking estimate 3 Jun 2026 · V4 invoice V4FQ-15584, 9 Jul 2026.
A4: Cost centre | B4: Supplier | C4: Line item | D4: Qty | E4: Unit £ | F4: Line total £ | G4: VAT | H4: Payment route | I4: Notes
A5: Chimney repair | B5: LG Building | C5: Labour — remove render, k-rend sealer, base + top coat, render crown, storm-dry cream | F5: 2880 | G5: No VAT | H5: LG invoice | I5: Original quote £3,200; 10% labour discount agreed 20 Jul (Ryan/Luke): −£320
A6: Chimney repair | B6: Scaffolder (direct) | C6: Tubular scaffolding — all four sides of chimney and crown | F6: 1500 | G6: Inc VAT | H6: Paid directly | I6: Combined £3,200, cash terms (20 Jul): £2,000 paid following erection; £1,200 balance on strike.
A7: Materials (pooled) | B7: Merchant trade accounts | C7: Materials (chimney estimate — pooled 20 Jul) | F7: 480 | G7: Inc VAT | H7: Trade accounts — cleared on receipts
A8: Chimney repair | B8: LG Building | C8: Rubbish removal | F8: 80 | G8: Inc VAT | H8: LG invoice
A9: Coping stones repair | B9: LG Building | C9: Labour — remove/reset copings, slate cap, render, lead flashings to parapet rear | F9: 3420 | G9: No VAT | H9: LG invoice | I9: Original quote £3,800; 10% labour discount agreed 20 Jul (Ryan/Luke): −£380. RISK: stone damage on removal could substantially increase cost
A10: Coping stones repair | B10: Scaffolder (direct) | C10: Tubular scaffolding with winch system | F10: 1700 | G10: Inc VAT | H10: Paid directly | I10: Combined £3,200, cash terms (20 Jul): £2,000 paid following erection; £1,200 balance on strike.
A11: Materials (pooled) | B11: Merchant trade accounts | C11: Materials (coping estimate — pooled 20 Jul) | F11: 650 | G11: Inc VAT | H11: Trade accounts — cleared on receipts
A12: Coping stones repair | B12: LG Building | C12: Rubbish removal | F12: 80 | G12: Inc VAT | H12: LG invoice
A13: Decking labour & rubbish | B13: LG Building | C13: Labour — remove old decking & frame, construct composite frame, install deck to spec | F13: 17600 | G13: No VAT | H13: LG invoice | I13: RISK: pending structure/ground assessment. EXCLUDED from 10% labour discount (20 Jul).
A14: Decking labour & rubbish | B14: LG Building | C14: Rubbish removal (8-yard skips ×2, possibly 3) | F14: 1200 | G14: Inc VAT | H14: LG invoice
A15: Decking materials | B15: V4 Wood Flooring | C15: Millboard Ashwood 176mm Moulded Lastane (144.90 m²) | D15: 230 | E15: 66.49 | F15: 15292.7 | G15: In net | H15: V4 invoice — PAID
A16: Decking materials | B16: V4 Wood Flooring | C16: Millboard Ashwood Moulded Lastane — MFN360H | D16: 18 | E16: 58.09 | F16: 1045.62 | G16: In net | H16: V4 invoice — PAID
A17: Decking materials | B17: V4 Wood Flooring | C17: Millboard Ashwood Moulded Lastane — MEBB360H (flexible bullnose) | D17: 15 | E17: 72.25 | F17: 1083.75 | G17: In net | H17: V4 invoice — PAID | I17: For curved upper level
A18: Decking materials | B18: V4 Wood Flooring | C18: Millboard Step Edge — Ashwood Moulded Lastane | D18: 15 | E18: 59.89 | F18: 898.35 | G18: In net | H18: V4 invoice — PAID
A19: Decking materials | B19: V4 Wood Flooring | C19: Stainless steel screws 45mm — boxes | D19: 24 | E19: 32.08 | F19: 770 | G19: In net | H19: V4 invoice — PAID
A20: Decking materials | B20: V4 Wood Flooring | C20: Durafix Trimhead 35mm SS screws — box of 100 (FT35P100) | D20: 6 | E20: 10.25 | F20: 61.5 | G20: In net | H20: V4 invoice — PAID
A21: Decking materials | B21: V4 Wood Flooring | C21: Plas-Pro bearer/joist black 3.0m 50×125mm composite (P1205B300) | D21: 266 | E21: 28.4 | F21: 7554.4 | G21: In net | H21: V4 invoice — PAID | I21: Subframe — the bulk of the tonnage
A22: Decking materials | B22: V4 Wood Flooring | C22: Subframe hexhead screws — box of 50 (FH90P050) | D22: 16 | E22: 7.87 | F22: 125.92 | G22: In net | H22: V4 invoice — PAID
A23: Decking materials | B23: V4 Wood Flooring | C23: Millboard touch-up paint — Ashwood (AP500H) | D23: 1 | E23: 15 | F23: 15 | G23: In net | H23: V4 invoice — PAID
A24: Decking materials | B24: V4 Wood Flooring | C24: Millboard multi-spacer — pack of 10 (FP36P010) | D24: 1 | E24: 10.25 | F24: 10.25 | G24: In net | H24: V4 invoice — PAID
A25: Decking materials | B25: V4 Wood Flooring | C25: VAT on order | F25: 5371.5 | G25: VAT | H25: V4 invoice — PAID | I25: Net £26,857.49 + VAT = £32,228.99
A26: Contingency | B26: TBC | C26: Contingency pot — fence labour, soakaway fix, garage drainage, curved-deck labour, cement & bricks | F26: 5000 | G26: — | H26: As incurred | I26: Track on Contingency Drawdown sheet. Labour invoices from this pot at 10% discount (extended 20 Jul); materials (cement/bricks) full price. Curved-decking extra labour: discount status TBC with Luke (decking exclusion boundary).
C27: TOTAL (all lines) | F27: =SUM(F5:F26) -> 66818.99

Sheet Invoice Register
A1: Invoice & Payment Register — add a row per invoice received
A2: Yellow cells are inputs. Cost centre must match the Summary sheet names exactly (dropdown-free by design — copy from row 5). Paid date empty = outstanding.
A4: Invoice date | B4: Cost centre | C4: Supplier | D4: Reference | E4: Description | F4: Amount £ (gross) | G4: Paid date | H4: Method | I4: Notes
A5: 46212 | B5: Decking materials | C5: V4 Wood Flooring Ltd | D5: V4FQ-15584 | E5: Millboard Ashwood decking + Plas-Pro subframe, fixings (144.9 m²) | F5: 32228.99 | G5: 46212 | H5: Amex | I5: Paid in full at order
A6: 46223 | B6: Materials (pooled) | C6: Dry Lining Supplies Ltd | D6: RECB000NNIVB49XWEXOG | E6: Render materials (shared chimney+coping): mesh, Weberend Aid ×6, beads, SBR, rubble sacks | F6: 311.98 | G6: 46223 | H6: Pay By Link | I6: Project-materials share of £423.69 receipt
A7: 46223 | B7: Chimney repair | C7: Dry Lining Supplies Ltd | D7: RECB000NNIVB49XWEXOG | E7: Folding work platform 600mm — Luke's equipment, non-project | F7: 111.71 | G7: 46223 | H7: Pay By Link | I7: PREPAYMENT vs chimney phase-start invoice: pay £1,528.29 of the £1,640 when it lands
A8: 46223 | B8: Chimney repair | C8: Scaffolder (via Trevor) | D8: Cash | E8: Scaffold erection payment — chimney share (pro-rata of £2,000 cash) | F8: 937.5 | G8: 46223 | H8: Cash | I8: £2,000 paid following erection 17–18 Jul; amend date cell if payment day differed
A9: 46223 | B9: Coping stones repair | C9: Scaffolder (via Trevor) | D9: Cash | E9: Scaffold erection payment — coping share (pro-rata of £2,000 cash) | F9: 1062.5 | G9: 46223 | H9: Cash | I9: Balance £1,200 due on strike

Sheet Materials Receipts
A1: Materials Receipts — pooled budget drawdown
A2: Pooled budget £1,130 (chimney £480 + coping £650, pooled 20 Jul). Log every merchant receipt here AND on the Invoice Register (cost centre: Materials (pooled)) — this sheet is the pool detail, the Register is the money record.
A4: Opening pool: | B4: 1130 | C4: Remaining: | D4: =B4-SUM(E8:E40) -> 818.02
A7: Date | B7: Merchant | C7: Items (summary) | D7: Phase / use | E7: Amount £ | F7: Running remaining £
A8: 46223 | B8: Dry Lining Supplies Ltd | C8: Render mesh, Weberend Aid ×6, angle/stop beads, rubble sacks, Bond It SBR 5l (project share; £111.71 platform excluded — Luke's equipment) | D8: Render (chimney + coping, shared) | E8: 311.98 | F8: =IF(E8="","",$B$4-SUM($E$8:E8)) -> 818.02
F9: =IF(E9="","",$B$4-SUM($E$8:E9))
F10: =IF(E10="","",$B$4-SUM($E$8:E10))
F11: =IF(E11="","",$B$4-SUM($E$8:E11))
F12: =IF(E12="","",$B$4-SUM($E$8:E12))
F13: =IF(E13="","",$B$4-SUM($E$8:E13))
F14: =IF(E14="","",$B$4-SUM($E$8:E14))
F15: =IF(E15="","",$B$4-SUM($E$8:E15))
F16: =IF(E16="","",$B$4-SUM($E$8:E16))
F17: =IF(E17="","",$B$4-SUM($E$8:E17))
F18: =IF(E18="","",$B$4-SUM($E$8:E18))
F19: =IF(E19="","",$B$4-SUM($E$8:E19))
F20: =IF(E20="","",$B$4-SUM($E$8:E20))
... F25: =IF(E25="","",$B$4-SUM($E$8:E25))

Sheet Contingency Drawdown
A1: Contingency Drawdown — £5,000 pot (agreed Lara/Luke, 1 Jul 2026)
A2: Named purposes: fence move/repair labour · soakaway fix before decking · drainage by the garage · additional curved-decking labour · cement & bricks. Luke's labour from this pot invoiced at 10% discount (extended 20 Jul); materials full price. Curved-decking extra labour discount status TBC.
A4: Opening pot: | B4: 5000 | C4: Remaining: | D4: =B4-SUM(D8:D40) -> 5000
A7: Date | B7: Purpose | C7: Supplier / detail | D7: Amount £ | E7: Running remaining £
E8: =IF(D8="","",$B$4-SUM($D$8:D8))
E9: =IF(D9="","",$B$4-SUM($D$8:D9))
E10: =IF(D10="","",$B$4-SUM($D$8:D10))
E11: =IF(D11="","",$B$4-SUM($D$8:D11))
E12: =IF(D12="","",$B$4-SUM($D$8:D12))
E13: =IF(D13="","",$B$4-SUM($D$8:D13))
E14: =IF(D14="","",$B$4-SUM($D$8:D14))
E15: =IF(D15="","",$B$4-SUM($D$8:D15))
E16: =IF(D16="","",$B$4-SUM($D$8:D16))
E17: =IF(D17="","",$B$4-SUM($D$8:D17))
E18: =IF(D18="","",$B$4-SUM($D$8:D18))
E19: =IF(D19="","",$B$4-SUM($D$8:D19))
... E25: =IF(D25="","",$B$4-SUM($D$8:D25))
