Workbook

Sheet Summary
A1: Spinney External Works — Budget Summary
A2: Last updated: | B2: 46216 | C2: All figures gross (as payable). Invoiced / Paid pull automatically from the Invoice Register; Contingency remaining pulls from the Drawdown sheet.
A4: Cost centre | B4: Supplier | C4: Committed £ | D4: Invoiced £ | E4: Paid £ | F4: Remaining vs committed £ | G4: Notes
A5: Decking materials | B5: V4 Wood Flooring Ltd | C5: 32228.99 | D5: =SUMIF('Invoice Register'!$B:$B,$A5,'Invoice Register'!$F:$F) -> 32228.99 | E5: =SUMIFS('Invoice Register'!$F:$F,'Invoice Register'!$B:$B,$A5,'Invoice Register'!$G:$G,"<>") -> 32228.99 | F5: =C5-D5 -> 0 | G5: Order amended to all Ashwood + flexible bullnose (1 Jul). PAID IN FULL 9 Jul, ref V4FQ-15584. 25% restocking on over-ordering — unlikely given curved design + offcuts project, but noted.
A6: Decking labour & rubbish | B6: LG Building and Roofing Ltd | C6: 18800 | D6: =SUMIF('Invoice Register'!$B:$B,$A6,'Invoice Register'!$F:$F) -> 0 | E6: =SUMIFS('Invoice Register'!$F:$F,'Invoice Register'!$B:$B,$A6,'Invoice Register'!$G:$G,"<>") -> 0 | F6: =C6-D6 -> 18800 | G6: £17,600 labour (no VAT) + £1,200 rubbish removal. RISK: price 'fairly accurate' pending Luke's structure/ground assessment.
A7: Contingency | B7: — | C7: 5000 | D7: =SUMIF('Invoice Register'!$B:$B,$A7,'Invoice Register'!$F:$F) -> 0 | E7: =SUMIFS('Invoice Register'!$F:$F,'Invoice Register'!$B:$B,$A7,'Invoice Register'!$G:$G,"<>") -> 0 | F7: =C7-D7 -> 5000 | G7: Covers: fence move/repair labour; soakaway fix before decking; drainage by garage; extra curved-decking labour; cement & bricks. See Contingency Drawdown sheet.
A8: Chimney repair | B8: LG Building and Roofing Ltd | C8: 5260 | D8: =SUMIF('Invoice Register'!$B:$B,$A8,'Invoice Register'!$F:$F) -> 0 | E8: =SUMIFS('Invoice Register'!$F:$F,'Invoice Register'!$B:$B,$A8,'Invoice Register'!$G:$G,"<>") -> 0 | F8: =C8-D8 -> 5260 | G8: Quoted separately (2 Jun). £3,200 labour no VAT; scaffolding £1,500 and materials £480 paid directly; £80 rubbish.
A9: Coping stones repair | B9: LG Building and Roofing Ltd | C9: 6230 | D9: =SUMIF('Invoice Register'!$B:$B,$A9,'Invoice Register'!$F:$F) -> 0 | E9: =SUMIFS('Invoice Register'!$F:$F,'Invoice Register'!$B:$B,$A9,'Invoice Register'!$G:$G,"<>") -> 0 | F9: =C9-D9 -> 6230 | G9: Quoted separately (3 Jun). RISK: damage to coping stones on removal could substantially increase cost.
A10: Core project (Luke's ~£56,800 outline) | C10: =C5+C6+C7 -> 56028.99 | D10: =D5+D6+D7 -> 32228.99 | E10: =E5+E6+E7 -> 32228.99 | F10: =F5+F6+F7 -> 23800
A11: Quoted separately (chimney + coping) | C11: =C8+C9 -> 11490 | D11: =D8+D9 -> 0 | E11: =E8+E9 -> 0 | F11: =F8+F9 -> 11490
A12: PROJECT TOTAL | C12: =C10+C11 -> 67518.99 | D12: =D10+D11 -> 32228.99 | E12: =E10+E11 -> 32228.99 | F12: =F10+F11 -> 35290
A14: Contingency remaining: | B14: ='Contingency Drawdown'!$D$4 -> 5000

Sheet Cost Lines
A1: Cost Lines — every line item from LG estimates and the V4 invoice
A2: Source documents: LG chimney estimate 2 Jun 2026 · LG coping estimate 3 Jun 2026 · LG decking estimate 3 Jun 2026 · V4 invoice V4FQ-15584, 9 Jul 2026.
A4: Cost centre | B4: Supplier | C4: Line item | D4: Qty | E4: Unit £ | F4: Line total £ | G4: VAT | H4: Payment route | I4: Notes
A5: Chimney repair | B5: LG Building | C5: Labour — remove render, k-rend sealer, base + top coat, render crown, storm-dry cream | F5: 3200 | G5: No VAT | H5: LG invoice
A6: Chimney repair | B6: Scaffolder (direct) | C6: Tubular scaffolding — all four sides of chimney and crown | F6: 1500 | G6: Inc VAT | H6: Paid directly
A7: Chimney repair | B7: Merchant (direct) | C7: Materials | F7: 480 | G7: Inc VAT | H7: Paid directly
A8: Chimney repair | B8: LG Building | C8: Rubbish removal | F8: 80 | G8: Inc VAT | H8: LG invoice
A9: Coping stones repair | B9: LG Building | C9: Labour — remove/reset copings, slate cap, render, lead flashings to parapet rear | F9: 3800 | G9: No VAT | H9: LG invoice | I9: RISK: stone damage on removal could substantially increase cost
A10: Coping stones repair | B10: Scaffolder (direct) | C10: Tubular scaffolding with winch system | F10: 1700 | G10: Inc VAT | H10: Paid directly
A11: Coping stones repair | B11: Merchant (direct) | C11: Materials | F11: 650 | G11: Inc VAT | H11: Paid directly
A12: Coping stones repair | B12: LG Building | C12: Rubbish removal | F12: 80 | G12: Inc VAT | H12: LG invoice
A13: Decking labour & rubbish | B13: LG Building | C13: Labour — remove old decking & frame, construct composite frame, install deck to spec | F13: 17600 | G13: No VAT | H13: LG invoice | I13: RISK: pending structure/ground assessment
A14: Decking labour & rubbish | B14: LG Building | C14: Rubbish removal (8-yard skips ×2, possibly 3) | F14: 1200 | G14: Inc VAT | H14: LG invoice
A15: Decking materials | B15: V4 Wood Flooring | C15: Millboard Ashwood 176mm Moulded Lastane (144.90 m²) | D15: 230 | E15: 66.49 | F15: 15292.7 | G15: In net | H15: V4 invoice — PAID
A16: Decking materials | B16: V4 Wood Flooring | C16: Millboard Ashwood Moulded Lastane — MFN360H | D16: 18 | E16: 58.09 | F16: 1045.62 | G16: In net | H16: V4 invoice — PAID
A17: Decking materials | B17: V4 Wood Flooring | C17: Millboard Ashwood Moulded Lastane — MEBB360H (flexible bullnose) | D17: 15 | E17: 72.25 | F17: 1083.75 | G17: In net | H17: V4 invoice — PAID | I17: For curved upper level
A18: Decking materials | B18: V4 Wood Flooring | C18: Millboard Step Edge — Ashwood Moulded Lastane | D18: 15 | E18: 59.89 | F18: 898.35 | G18: In net | H18: V4 invoice — PAID
A19: Decking materials | B19: V4 Wood Flooring | C19: Stainless steel screws 45mm — boxes | D19: 24 | E19: 32.08 | F19: 770 | G19: In net | H19: V4 invoice — PAID
A20: Decking materials | B20: V4 Wood Flooring | C20: Durafix Trimhead 35mm SS screws — box of 100 (FT35P100) | D20: 6 | E20: 10.25 | F20: 61.5 | G20: In net | H20: V4 invoice — PAID
A21: Decking materials | B21: V4 Wood Flooring | C21: Plas-Pro bearer/joist black 3.0m 50×125mm composite (P1205B300) | D21: 266 | E21: 28.4 | F21: 7554.4 | G21: In net | H21: V4 invoice — PAID | I21: Subframe — the bulk of the tonnage
A22: Decking materials | B22: V4 Wood Flooring | C22: Subframe hexhead screws — box of 50 (FH90P050) | D22: 16 | E22: 7.87 | F22: 125.92 | G22: In net | H22: V4 invoice — PAID
A23: Decking materials | B23: V4 Wood Flooring | C23: Millboard touch-up paint — Ashwood (AP500H) | D23: 1 | E23: 15 | F23: 15 | G23: In net | H23: V4 invoice — PAID
A24: Decking materials | B24: V4 Wood Flooring | C24: Millboard multi-spacer — pack of 10 (FP36P010) | D24: 1 | E24: 10.25 | F24: 10.25 | G24: In net | H24: V4 invoice — PAID
A25: Decking materials | B25: V4 Wood Flooring | C25: VAT on order | F25: 5371.5 | G25: VAT | H25: V4 invoice — PAID | I25: Net £26,857.49 + VAT = £32,228.99
A26: Contingency | B26: TBC | C26: Contingency pot — fence labour, soakaway fix, garage drainage, curved-deck labour, cement & bricks | F26: 5000 | G26: — | H26: As incurred | I26: Track on Contingency Drawdown sheet
C27: TOTAL (all lines) | F27: =SUM(F5:F26) -> 67518.99

Sheet Invoice Register
A1: Invoice & Payment Register — add a row per invoice received
A2: Yellow cells are inputs. Cost centre must match the Summary sheet names exactly (dropdown-free by design — copy from row 5). Paid date empty = outstanding.
A4: Invoice date | B4: Cost centre | C4: Supplier | D4: Reference | E4: Description | F4: Amount £ (gross) | G4: Paid date | H4: Method | I4: Notes
A5: 46212 | B5: Decking materials | C5: V4 Wood Flooring Ltd | D5: V4FQ-15584 | E5: Millboard Ashwood decking + Plas-Pro subframe, fixings (144.9 m²) | F5: 32228.99 | G5: 46212 | H5: Amex | I5: Paid in full at order

Sheet Contingency Drawdown
A1: Contingency Drawdown — £5,000 pot (agreed Lara/Luke, 1 Jul 2026)
A2: Named purposes: fence move/repair labour · soakaway fix before decking · drainage by the garage · additional curved-decking labour · cement & bricks for decking works.
A4: Opening pot: | B4: 5000 | C4: Remaining: | D4: =B4-SUM(D8:D40) -> 5000
A7: Date | B7: Purpose | C7: Supplier / detail | D7: Amount £ | E7: Running remaining £
E8: =IF(D8="","",$B$4-SUM($D$8:D8))
E9: =IF(D9="","",$B$4-SUM($D$8:D9))
E10: =IF(D10="","",$B$4-SUM($D$8:D10))
E11: =IF(D11="","",$B$4-SUM($D$8:D11))
E12: =IF(D12="","",$B$4-SUM($D$8:D12))
E13: =IF(D13="","",$B$4-SUM($D$8:D13))
E14: =IF(D14="","",$B$4-SUM($D$8:D14))
E15: =IF(D15="","",$B$4-SUM($D$8:D15))
E16: =IF(D16="","",$B$4-SUM($D$8:D16))
E17: =IF(D17="","",$B$4-SUM($D$8:D17))
E18: =IF(D18="","",$B$4-SUM($D$8:D18))
E19: =IF(D19="","",$B$4-SUM($D$8:D19))
... E25: =IF(D25="","",$B$4-SUM($D$8:D25))
