Workbook

Sheet Summary
A1: Spinney External Works — Budget Summary
A2: Last updated: | B2: 46317 | C2: All figures gross (as payable). Invoiced / Paid pull automatically from the Invoice Register; Contingency remaining pulls from the Drawdown sheet.
A4: Cost centre | B4: Supplier | C4: Committed £ | D4: Invoiced £ | E4: Paid £ | F4: Remaining vs committed £ | G4: Notes
A5: Decking materials (V4) | B5: V4 Wood Flooring Ltd | C5: 32228.99 | D5: =SUMIF('Invoice Register'!$B:$B,$A5,'Invoice Register'!$F:$F) -> 32228.99 | E5: =SUMIFS('Invoice Register'!$F:$F,'Invoice Register'!$B:$B,$A5,'Invoice Register'!$G:$G,"<>") -> 32228.99 | F5: =C5-D5 -> 0 | G5: Order amended to all Ashwood + flexible bullnose (1 Jul). PAID IN FULL 9 Jul, ref V4FQ-15584. 25% restocking on over-ordering — unlikely given curved design + offcuts project, but noted. A separate, later V4 order (£5,322.74, quote #QUO-0031, 29 Sep) for the expanded shed-area/fence-move decking scope is tracked under Contingency (named purpose #24), not here — see that sheet.
A6: Decking labour | B6: LG Building and Roofing Ltd | C6: 17600 | D6: =SUMIF('Invoice Register'!$B:$B,$A6,'Invoice Register'!$F:$F) -> 8400 | E6: =SUMIFS('Invoice Register'!$F:$F,'Invoice Register'!$B:$B,$A6,'Invoice Register'!$G:$G,"<>") -> 8400 | F6: =C6-D6 -> 9200 | G6: Labour £17,600 (no VAT). Stage 1 (£4,400) invoiced/paid 20 Aug, full price. Two cash instalments since (£2,000 each, 4 Sep + 18 Sep) — 10% discount applies to both, retiring £2,222.22 of quoted value each. £8,400 cash paid to date, equivalent to £8,844.44 of quoted value — £8,755.56 quoted value remaining. Rubbish removal (£1,200) transferred 10 Aug to pooled skip fund — see that row, not double-counted here. The separate extra labour for the curves and additional deck (INV-0293, £1,850, 9 Oct) sits under Contingency, not here; it does not change the £8,755.56 remaining.
A7: Contingency | B7: — | C7: 5000 | D7: =SUMIF('Invoice Register'!$B:$B,$A7,'Invoice Register'!$F:$F) -> 16659.97 | E7: =SUMIFS('Invoice Register'!$F:$F,'Invoice Register'!$B:$B,$A7,'Invoice Register'!$G:$G,"<>") -> 16659.97 | F7: =C7-D7 -> -11659.97 | G7: Covers: fence move/repair labour; soakaway fix before decking; drainage by garage; extra curved-decking labour; cement & bricks; coping condensation-prep (£250, PAID 14 Aug via bank transfer, INV-0288). Luke's labour drawn from this pot attracts the 10% discount (extended 20 Jul) — note the condensation-prep item was paid by bank transfer, not cash, so discount doesn't apply there. See Contingency Drawdown sheet. NEW 29 Sep — named purpose #24: V4 materials for the expanded shed-area/fence-move decking scope, £5,322.74, PAID by phone. This single draw alone takes Contingency well over the £5,000 cap — flagged, not hidden, same treatment as the Rubbish removal pooled overage. NEW 3 Oct — named purposes #25–#30: six further TP invoices (£1,093.57). The £500 paid to TP on 11 Sep cleared #5 (£108.14), £247.01 of #6 and £144.85 of Luke's invoices for other jobs (not project spend — netted off in the agreed TP settlement). TP account SETTLED: £2,313.89 paid by card 5 Oct, Luke repaid £144.85 on 6 Oct (net £2,169.04). See TP Account tab. NEW 9 Oct — LG INV-0293 £1,850 (curves £800 = purpose #4; additional deck £1,050 = purpose #32), paid by bank transfer. PENDING, not yet drawn: additional lead work ~£200 (purpose #31, Luke's estimate 2 Oct, not started) — to come from Contingency once invoiced. Luke's further extended-deck labour is not yet agreed or logged. NEW 13 Oct — named purpose #33: Toolstation saw blades and drill bits £84.97 (bought by Luke on his card, repaid in cash 13 Oct). PENDING, not yet drawn: whole-house soft wash £1,200 cash (Gorgeous Cleaning Services, purpose #34, from Mon 19 Oct). NEW 17 Oct — LG INV-0294 (£1,350, no VAT, paid by bank transfer): £350 driveway channel (named purpose #35, new scope 'Driveway channel') + £1,000 extra decking labour (named purpose #36). Still PENDING, not yet drawn: whole-house soft wash £1,200 cash (purpose #34, from Mon 19 Oct), lead work ~£200 (purpose #31, work done 16 Oct, awaiting invoice) and V4 screw top-up #3, now invoiced at £47.22 and unpaid (purpose #15, replaces the £141.66 estimate). NEW 20 Oct — named purpose #37: pipe lagging for the outside tap/pipework, £177.58 (Buy Insulation Online, paid by Ryan's card; scope Shared / site-wide). NEW 22 Oct — named purpose #38: V4 QUO-0040 £1,268 (materials to complete the decking substructure, delivered Mon 19 Oct, paid by card 22 Oct). The soft wash (#34) was completed and paid in cash (£1,200) on Mon 19 Oct. Also to be drawn from Contingency, no estimates yet: Revolutional Electrical (cables under the decking for the new shed area and the extended-deck lighting; call-out charge 22 Oct), the new shed (still to be ordered) and three new grates by the side of the house (extra work).
A8: Chimney repair | B8: LG Building and Roofing Ltd | C8: 4700 | D8: =SUMIF('Invoice Register'!$B:$B,$A8,'Invoice Register'!$F:$F) -> 4700.01 | E8: =SUMIFS('Invoice Register'!$F:$F,'Invoice Register'!$B:$B,$A8,'Invoice Register'!$G:$G,"<>") -> 4700.01 | F8: =C8-D8 -> -0.01 | G8: Quoted 2 Jun: £3,200 labour (invoiced full price, INV-0286) + £1,500 scaffold share. Cowl upgrade (£62.90) and TP account materials reclassified out 17 Aug — see Contingency and Materials (pooled) rows. This is now a clean quote-vs-actual labour figure.
A9: Coping stones repair | B9: LG Building and Roofing Ltd | C9: 5310 | D9: =SUMIF('Invoice Register'!$B:$B,$A9,'Invoice Register'!$F:$F) -> 5310 | E9: =SUMIFS('Invoice Register'!$F:$F,'Invoice Register'!$B:$B,$A9,'Invoice Register'!$G:$G,"<>") -> 5310 | F9: =C9-D9 -> 0 | G9: Quoted 3 Jun: £3,800 labour, confirmed 7 Aug as £3,610 blended (50% cash @10% disc. + 50% invoiced) + £1,700 scaffold share. Condensation-prep (£276.42) and TP account materials share (£277.29) reclassified out — see Contingency and Materials (pooled) rows. RISK: coping-stone damage on removal could substantially increase cost.
A10: Materials (pooled) | B10: Merchant trade accounts | C10: 1130 | D10: =SUMIF('Invoice Register'!$B:$B,$A10,'Invoice Register'!$F:$F) -> 1120.69 | E10: =SUMIFS('Invoice Register'!$F:$F,'Invoice Register'!$B:$B,$A10,'Invoice Register'!$G:$G,"<>") -> 1120.69 | F10: =C10-D10 -> 9.31 | G10: Pooled chimney (£480) + coping (£650) materials budget — decision 20 Jul. Purchased via merchant trade accounts (Dry Lining Supplies, Travis Perkins etc.), cleared on receipts. Detail on Materials Receipts sheet.
A11: Rubbish removal (pooled skips) | B11: Skip Hire Comparison Ltd / future providers | C11: 1360 | D11: =SUMIF('Invoice Register'!$B:$B,$A11,'Invoice Register'!$F:$F) -> 1460 | E11: =SUMIFS('Invoice Register'!$F:$F,'Invoice Register'!$B:$B,$A11,'Invoice Register'!$G:$G,"<>") -> 1460 | F11: =C11-D11 -> -100 | G11: Transferred 10 Aug from chimney/coping/decking rubbish-removal quotes (£80+£80+£1,200). Original skip (Skip Hire Comparison Ltd) cancelled 11 Aug, refunded — replaced same-day by Elmbridge Mini Skips (2 skips, £780 total, settled 12 Aug). Provisional — more skips expected, especially during decking. Detail on Skip Hire Log sheet. £40 Roofline works rubbish removal is expected but not yet incurred — not counted above; if incurred the pool would be £140 over.
A12: Roofline works | B12: LG Building and Roofing Ltd | C12: 2100 | D12: =SUMIF('Invoice Register'!$B:$B,$A12,'Invoice Register'!$F:$F) -> 1984.93 | E12: =SUMIFS('Invoice Register'!$F:$F,'Invoice Register'!$B:$B,$A12,'Invoice Register'!$G:$G,"<>") -> 1984.93 | F12: =C12-D12 -> 115.07 | G12: Own scope, own budget (estimate 4 Sep, £2,140 — unchanged; started 29 Sep, all roofline works complete Fri 16 Oct, including the lead flashing) — gutter replacement, fascia/soffit extension, slate replacement, barge board trim. Replaces the earlier 'gutters included in Luke's price' arrangement (back-gutter realignment and front gutters/tile repairs): on 4 Oct Gantt tasks 1.5, 1.7 and 3.2 were merged into one 'Roofline works' task (1.5). The estimate has no front-of-house gutters, and front tile repairs are covered by 'replace various broken slates'. Budget £2,100 = £1,600 labour (no VAT) + £150 scaffold tower + £350 materials; the £40 rubbish removal in the quote sits in the pooled Rubbish removal fund (not yet incurred). The tower was not needed (Luke used his own ladder) and that £150 benefit offsets the £40.40 of additional materials: net £109.60 under budget. LABOUR: INV-0291 £1,600 (2 Oct) confirmed correct and PAID 3 Oct by bank transfer, full price. MATERIALS: Graham SI19670857 £256.78 (£260 cash, paid 29 Sep); Graham SI19687572 £9.74 + TFP 0001458493 £78.01 (£90 cash) and TFP 0001458792 £40.40 (all paid in cash 2 Oct). This row shows £1,984.93 (invoices only); Cost Lines and Budget vs Actual use £1,990.40 actual, which includes £5.47 of coin top-ups. Additional lead work (~£200, Gantt task 1.5a, part of Gate 2) is outside this budget — see Contingency.
A13: Core project (Luke's ~£56,800 outline) | C13: =C5+C6+C7 -> 54828.99 | D13: =D5+D6+D7 -> 57288.96 | E13: =E5+E6+E7 -> 57288.96 | F13: =F5+F6+F7 -> -2459.97
A14: Chimney + coping incl. pooled materials | C14: =C8+C9+C10 -> 11140 | D14: =D8+D9+D10 -> 11130.7 | E14: =E8+E9+E10 -> 11130.7 | F14: =F8+F9+F10 -> 9.3
A15: PROJECT TOTAL | C15: =C11+C12+C13+C14 -> 69428.99 | D15: =D11+D12+D13 -> 60733.89 | E15: =E11+E12+E13 -> 60733.89 | F15: =F11+F12+F13 -> -2444.9
A16: Contingency remaining: | B16: ='Contingency Drawdown'!$D$4 -> -11659.97
A18: Cost centre = which budget pays · Scope = what it was for (see Scope View tab) · 'Decking materials (V4)' = V4 orders only; Travis Perkins and other decking-related materials sit in Contingency.
A20: Decking labour — quoted-value position (10% cash discount applied)
A21: Quoted labour, stages 1–4 | C21: =C6 -> 17600 | G21: Luke's quote for the main decking labour.
A22: Quoted value covered to date | C22: =SUMIFS('Invoice Register'!$F:$F,'Invoice Register'!$B:$B,"Decking labour",'Invoice Register'!$H:$H,"Bank transfer")+SUMIFS('Invoice Register'!$F:$F,'Invoice Register'!$B:$B,"Decking labour",'Invoice Register'!$H:$H,"Cash*")/0.9 -> 8844.4444 | G22: Bank payments at face value; cash payments ÷ 0.9 because of the 10% cash discount (e.g. £2,000 cash covers £2,222.22 of quoted value).
A23: Quoted value REMAINING | C23: =C21-C22 -> 8755.5556 | G23: This is the figure to use. It matches Luke's own workings (£8,756). The 'Remaining' column above (£9,200) is a plain cash subtraction, and the older tracker view that showed £11,200 pre-dated the 18 Sep instalment.

Sheet Budget vs Actual
A1: Spinney External Works — Budget vs Actual
A2: Snapshot as of 22 Oct 2026 (Week 13) — refresh narrative each batched update session; table figures pull from Summary sheet.
A4: Snapshot
A5: Week 13 — Contingency is well over cap: £16,659.97 drawn and paid against the £5,000 pot (£11,659.97 over). The main driver is the £5,322.74 V4 materials order for the expanded shed-area/fence-move decking scope (named purpose #24, paid by card 29 Sep). Since the last update, the whole-house soft wash by Gorgeous Cleaning Services (£1,200 cash) was completed and paid on Mon 19 Oct, pipe lagging for the outside tap/pipework (£177.58, Buy Insulation Online, paid by Ryan's card 20 Oct) was drawn from Contingency, and LG INV-0294 (£1,350, paid by bank transfer 17 Oct) added £350 for the driveway channel (half a day, Luke and Max) and £1,000 of extra decking labour. Nothing is invoiced but unpaid in the Register. Still to come from Contingency: the ~£200 additional lead work (done 16 Oct, awaiting invoice) and the V4 screw top-up #3, now invoiced at £47.22 and unpaid. The further V4 delivery to complete the decking substructure (QUO-0040, £1,268) arrived Mon 19 Oct and was paid by card on 22 Oct. Also to come from Contingency, with no estimates yet: Revolutional Electrical's cabling and extended-deck lighting (call-out charge 22 Oct), the new shed (still to be ordered) and three new grates by the side of the house (extra work). The total as spent/committed is now £2,251.06 over the overall budget. Chimney and coping are complete and settled. All roofline works were completed Fri 16 Oct, including the lead flashing.
A7: • Chimney | B7: COMPLETE (Gate 1, 18 Aug) — £0 variance, labour invoiced at the full quoted £3,200, no discount applied (non-cash terms).
A8: • Coping | B8: COMPLETE (Gate 1, 18 Aug) — £190 UNDER quote, half the labour was settled in cash at the agreed 10% discount, the other half invoiced at full price.
A9: • Decking (labour + V4 materials) | B9: Materials fully paid to the V4 proforma exactly (£32,228.99 — unchanged; the new £5,322.74 V4 order sits under Contingency, see below, not here). Labour: Stage 1 (£4,400) invoiced full price, plus two £2,000 cash instalments (4 Sep, 18 Sep, 10% discount each) — £8,844.44 quoted-value equivalent paid so far, £8,755.56 remaining across future stages.
A10: • Scaffold (pooled, chimney + coping combined) | B10: £0 variance — this was never split-quoted per workstream, just one £3,200 job (£2,000 paid on erection, £1,200 due on strike). Treating it as its own pooled line avoids implying a false per-workstream comparison.
A11: • Materials (pooled, chimney + coping) | B11: Back under the £1,130 cap — a £72.23 refund from Dry Lining Supplies (unused monocouche + other returned items) landed 19 Aug, more than offsetting the earlier £62.90 overage from pooling Luke's Travis Perkins account purchases.
A12: • Rubbish removal (pooled, all 3 workstreams) | B12: £1,460 spent against the £1,360 pool — £100 over. That is £780 for the two Elmbridge skips plus £680 for the old decking substructure wood collection, which was charged per trip and came in well above the £350 estimate. The skips and wood removal served chimney, coping and the soakaway/decking-prep groundworks, so the spend can't be attributed cleanly to one workstream. A further £40 for the Roofline works rubbish removal is expected but not yet incurred; if it is, the pool would be £140 over. Flagged, not hidden.
A13: • Roofline works (new) | B13: £1,600 labour + £150 scaffold tower + £350 materials = £2,100 budget (quote £2,140 unchanged; the £40 rubbish removal sits in the pooled fund). Started 29 Sep, all roofline works completed Fri 16 Oct, including the lead flashing. Labour INV-0291 (£1,600) paid 3 Oct by bank transfer. The tower was not needed — Luke used his ladder — and that £150 benefit offsets £40.40 of additional materials (four invoices, £390.40 cash, all reimbursed to Luke): net £109.60 under budget, actual £1,990.40. Additional lead work (~£200) will come from Contingency.
A14: • Contingency | B14: £16,659.97 drawn and PAID against the £5,000 pot — £11,659.97 OVER CAP. Main driver: £5,322.74 V4 materials order (purpose #24, paid 29 Sep). Travis Perkins invoices were settled 5 Oct, LG INV-0293 (£1,850) was paid 9 Oct, whole-house soft wash (£1,200 cash, purpose #34, 19 Oct), Toolstation tools (£84.97, purpose #33) were repaid 13 Oct and LG INV-0294 (£1,350: driveway channel £350 + extra decking labour £1,000) was paid 17 Oct and pipe lagging (£177.58, purpose #37) on 20 Oct, and V4 QUO-0040 (£1,268, purpose #38) on 22 Oct. Flagged, not hidden. Pending, not yet drawn: ~£200 additional lead work (purpose #31) and V4 screw top-up #3 (£47.22 invoiced, unpaid).
A16: Budget vs Actual — detail
A17: Cost centre | B17: Quote / Budget £ | C17: Actual £ | D17: Variance £ | E17: Note
A18: Chimney (labour) | B18: 3200 | C18: 3200 | D18: 0 | E18: Invoiced full price (INV-0286) — non-cash, no discount
A19: Coping (labour) | B19: 3800 | C19: 3610 | D19: -190 | E19: 50% cash @10% disc. + 50% invoiced — favourable
A20: Decking (labour) | B20: 17600 | C20: 8400 | D20: -9200 | E20: Stage 1 (£4,400 invoiced) + two £2,000 cash instalments (4 Sep, 18 Sep, 10% discount each) — £8,844.44 quoted value retired, £8,755.56 remaining, mix of future cash/invoice TBC.
A21: Decking materials (V4) | B21: 32228.99 | C21: 32228.99 | D21: 0 | E21: Proforma matched exactly, paid in full 9 Jul
A22: Scaffold (pooled, chimney+coping) | B22: 3200 | C22: 3200 | D22: 0 | E22: Never split-quoted — one combined job. £2,000 paid, £1,200 due on strike
A23: Materials (pooled, chimney+coping) | B23: 1130 | C23: 1120.69 | D23: -9.31 | E23: Back under the £1,130 cap after a £72.23 refund from Dry Lining Supplies (unused monocouche + other returned items) landed 19 Aug — was £62.92 over before the refund.
A24: Rubbish removal (pooled, all 3 workstreams) | B24: 1360 | C24: 1460 | D24: 100 | E24: £100 OVER the £1,360 cap — the wood removal correction (£350 est. → £680 actual, charged per trip) pushed it over. Flagged, not hidden; cap left as-is per the same approach used for Materials pooled. Plus £40 expected (Roofline works rubbish removal, not yet incurred) — not counted above; if incurred the pool would be £140 over.
A25: Roofline works (new, 4 Sep estimate) | B25: 2100 | C25: 1990.4 | D25: -109.6 | E25: Quote £2,140 (4 Sep) unchanged = £2,100 here + £40 rubbish removal in the pooled fund (not yet incurred). Started 29 Sep, all roofline works completed Fri 16 Oct, including the lead flashing. The £150 scaffold tower was not needed (Luke used his ladder) — that benefit offsets the £40.40 of additional materials (£390.40 cash vs £350 allowance), net £109.60 under. ACTUAL £1,990.40 = £1,600 labour (INV-0291, paid 3 Oct by bank transfer) + £390.40 materials (paid in cash). Additional lead work (~£200) sits in Contingency.
A26: Contingency | B26: 5000 | C26: 16659.97 | D26: 11659.97 | E26: £16,659.97 drawn and PAID against the £5,000 pot, which is £11,659.97 over. Main driver: the £5,322.74 V4 materials order for the extended deck / shed area (named purpose #24, paid by phone 29 Sep), larger than the whole pot on its own. Travis Perkins settled 5 Oct; LG INV-0293 paid 9 Oct; Toolstation tools repaid 13 Oct; LG INV-0294 (£1,350 — driveway channel £350, extra decking labour £1,000) paid 17 Oct; pipe lagging (£177.58) paid 20 Oct; V4 QUO-0040 (£1,268) paid 22 Oct. The £1,200 whole-house soft wash was paid in cash on 19 Oct. Still to come: electrics, the new shed and three new grates, with no estimates yet. See the Contingency explained tab. Flagged, not hidden — same treatment as the Rubbish removal overage.
A27: TOTAL (as spent/committed to date) | B27: 69618.99 | C27: 71870.05 | D27: 2251.06
A29: Reconciliation check
A30: Summary's PROJECT TOTAL uses each cost centre's committed/ceiling figure — for Chimney, Coping, and Decking that's the real actual; for Materials, Rubbish, and Contingency (all pooled/reserve buckets) it's the provisional cap, not what's been spent so far. Recomputed on that same basis below to confirm nothing here is missing or double-counted against Summary.
A32: Chimney (actual) | C32: 4700
A33: Coping (actual) | C33: 5310
A34: Decking labour (actual) | C34: 17600
A35: Decking materials (actual) | C35: 32228.99
A36: Materials pooled (at £1,130 cap, per Summary) | C36: 1130
A37: Rubbish removal pooled (at £1,360 cap, per Summary) | C37: 1360
A38: Contingency (at £5,000 cap, per Summary) | C38: 5000
A39: Roofline works (actual, per estimate) | C39: 2100
A40: Recomputed total (Summary basis) | C40: =SUM(C32:C39) -> 69428.99
A41: Summary PROJECT TOTAL (committed) | C41: =Summary!C15 -> 69428.99
A42: Difference — should be £0.00 | C42: =C40-C41 -> 0

Sheet Contingency Explained
A1: Contingency explained — why the £5,000 pot has been exceeded
A2: As at 22 Oct 2026. Amounts inc VAT. Pulls live from the Contingency Drawdown, Summary and Cost Lines tabs. Scope tags on Travis Perkins invoices are inferred from invoice dates (confirm with Luke).
A3: ="Short answer: Contingency has £"&TEXT(B7,"#,##0.00")&" drawn against a £"&TEXT(B6,"#,##0")&" pot — £"&TEXT(B10,"#,##0.00")&" over. About "&TEXT(C14,"0%")&" of it is a new area of decking (the extended deck and shed base) that was not in the pot's original purposes." -> Short answer: Contingency has £16,659.97 drawn against a £5,000 pot — £11,659.97 over. About 62% of it is a new area of decking (the extended deck and shed base) that was not in the pot's original purposes.
A5: 1. The headline
A6: Pot agreed 1 Jul | B6: =Summary!C7 -> 5000 | E6: Agreed for: fence move/repair labour, soakaway fix before decking (cancelled 1 Sep, nothing drawn), drainage by the garage (nothing drawn), additional curved-decking labour, cement and bricks.
A7: Drawn (invoiced) | B7: =Summary!D7 -> 16659.97 | E7: Every Contingency invoice in the Invoice Register, paid or not.
A8: of which paid | B8: =Summary!E7 -> 16659.97
A9: of which invoiced, not yet paid | B9: =B7-B8 -> 0 | E9: Nothing outstanding in the Register: the Travis Perkins invoices were settled on 5 Oct, LG INV-0293 was paid on 9 Oct and LG INV-0294 was paid on 17 Oct and the pipe lagging on 20 Oct V4 QUO-0040 on 22 Oct and the soft wash (cash) on 19 Oct.
A10: OVER THE POT BY | B10: =B7-B6 -> 11659.97
A12: 2. Where the money went
A13: Driver | B13: £ | C13: Share | D13: On the 1 Jul list? | E13: What is in it
A14: Extended deck & shed base | B14: =SUMIFS('Contingency Drawdown'!$E$8:$E$60,'Contingency Drawdown'!$J$8:$J$60,"Extended deck & shed base") -> 10371.8 | C14: =B14/B$21 -> 0.62255814 | D14: No — arose later | E14: The new decking area the fence move opened up, plus the shed base: V4 materials order, extra digging, extra frame and the first Travis Perkins blocks and cement for it. Also the £1,050 additional deck labour on LG INV-0293. Includes the £1,000 extra decking labour on LG INV-0294 (17 Oct). Includes the £1,268 V4 QUO-0040 order (22 Oct).
A15: Main deck materials | B15: =SUMIFS('Contingency Drawdown'!$E$8:$E$60,'Contingency Drawdown'!$J$8:$J$60,"Main deck") -> 2760.44 | C15: =B15/B$21 -> 0.16569298 | D15: Partly — 'cement and bricks' | E15: Travis Perkins bulk materials for the original decking (cement, ballast, sand, blocks, ply, small tools) plus V4 subframe screw top-ups. Luke's quote has materials paid directly, so they had to land somewhere. Also the £800 curved-deck labour on LG INV-0293.
A16: Groundworks hire | B16: =SUMIFS('Contingency Drawdown'!$E$8:$E$60,'Contingency Drawdown'!$J$8:$J$60,"Groundworks (digger & dumper)") -> 836.37 | C16: =B16/B$21 -> 0.050202371 | D16: No | E16: Digger, dumper and clean-up. Used for both the main deck widening and the new shed area, so not split between them.
A17: Fence relocation | B17: =SUMIFS('Contingency Drawdown'!$E$8:$E$60,'Contingency Drawdown'!$J$8:$J$60,"Fence relocation") -> 606.17 | C17: =B17/B$21 -> 0.036384819 | D17: Yes — fence move | E17: Fence move labour (chimney side, boundary reclaim) and the fence materials.
A18: Chimney & coping extras, shared items | B18: =SUMIFS('Contingency Drawdown'!$E$8:$E$60,'Contingency Drawdown'!$J$8:$J$60,"Chimney & coping")+SUMIFS('Contingency Drawdown'!$E$8:$E$60,'Contingency Drawdown'!$J$8:$J$60,"Shared / site-wide") -> 1735.19 | C18: =B18/B$21 -> 0.10415325 | D18: No | E18: Coping condensation-prep, chimney cowl upgrade, and one shared small-consumables invoice. Also the pipe lagging for the outside tap/pipework (£177.58, 20 Oct). Also the whole-house soft wash (£1,200 cash, 19 Oct).
A19: Driveway channel | B19: =SUMIFS('Contingency Drawdown'!$E$8:$E$60,'Contingency Drawdown'!$J$8:$J$60,"Driveway channel") -> 350 | C19: =B19/B$21 -> 0.021008441 | D19: No — arose later | E19: Water-softener waste channel (rainy-day task, Gantt 3.1), done in half a day on 14 Oct by Luke and Max, £350 on LG INV-0294.
A20: New shed & electrics | B20: =SUMIFS('Contingency Drawdown'!$E$8:$E$60,'Contingency Drawdown'!$J$8:$J$60,"New shed & electrics") -> 0 | C20: =B20/B$21 -> 0 | D20: No — arose later | E20: Workstream 8: the new shed, its installation and the electrics (first fix done 22 Oct; call-out charge not yet invoiced). Nothing drawn yet; costs to come, no estimates.
A21: TOTAL DRAWN | B21: =SUM(B14:B20) -> 16659.97 | C21: =SUM(C14:C20) -> 1
A22: Check: total less Summary 'Invoiced' (must be 0.00) | B22: =ROUND(B21-Summary!D7,2) -> 0
A24: 3. Inside the drivers
A25: Line | B25: £ | D25: Purpose # | E25: Source
A26: V4 order — shed area / extended deck materials | B26: =SUMIFS('Contingency Drawdown'!$E$8:$E$60,'Contingency Drawdown'!$A$8:$A$60,24) -> 5322.74 | D26: #24 | E26: Placed and paid by phone 29 Sep (quote QUO-0031).
A27: Extra digging — wider gate area + shed/additional deck | B27: =SUMIFS('Contingency Drawdown'!$E$8:$E$60,'Contingency Drawdown'!$A$8:$A$60,11) -> 1260 | D27: #11 | E27: Invoiced and paid 11 Sep.
A28: Extra frame — wider deck gate area | B28: =SUMIFS('Contingency Drawdown'!$E$8:$E$60,'Contingency Drawdown'!$A$8:$A$60,14) -> 360 | D28: #14 | E28: Invoiced and paid 11 Sep.
A29: Travis Perkins blocks and cement dated 21 Sep | B29: =SUMIFS('Contingency Drawdown'!$E$8:$E$60,'Contingency Drawdown'!$A$8:$A$60,29)+SUMIFS('Contingency Drawdown'!$E$8:$E$60,'Contingency Drawdown'!$A$8:$A$60,30) -> 111.06 | D29: #29, #30 | E29: Two invoices, paid 5 Oct.
A30: Extra deck labour — additional deck (LG INV-0293) | B30: =SUMIFS('Contingency Drawdown'!$E$8:$E$60,'Contingency Drawdown'!$A$8:$A$60,32) -> 1050 | D30: #32 | E30: Invoiced and paid 9 Oct (£1,050, bank transfer).
A31: Extra decking labour (LG INV-0294) | B31: =SUMIFS('Contingency Drawdown'!$E$8:$E$60,'Contingency Drawdown'!$A$8:$A$60,36) -> 1000 | D31: #36 | E31: Invoiced and paid 17 Oct (£1,000, bank transfer).
A32: V4 order — materials to complete the substructure (QUO-0040) | B32: =SUMIFS('Contingency Drawdown'!$E$8:$E$60,'Contingency Drawdown'!$A$8:$A$60,38) -> 1268 | D32: #38 | E32: Delivered Mon 19 Oct; paid by card 22 Oct (£1,268). Some Plas-Pro may be used on the main decking.
A33: Extended deck & shed base — subtotal | B33: =SUM(B26:B32) -> 10371.8
A34: Check against section 2 (must be 0.00) | B34: =ROUND(B33-B14,2) -> 0
A35: Travis Perkins bulk materials, main deck | B35: =B15-B36-B37-B38 -> 1592.15 | D35: #16–#22, #25–#27 | E35: Invoices dated before 21 Sep.
A36: V4 subframe screw top-ups | B36: =SUMIFS('Contingency Drawdown'!$E$8:$E$60,'Contingency Drawdown'!$A$8:$A$60,8)+SUMIFS('Contingency Drawdown'!$E$8:$E$60,'Contingency Drawdown'!$A$8:$A$60,9) -> 283.32 | D36: #8, #9 | E36: Two top-ups of 15 boxes.
A37: Curved-decking labour (LG INV-0293) | B37: =SUMIFS('Contingency Drawdown'!$E$8:$E$60,'Contingency Drawdown'!$A$8:$A$60,4) -> 800 | D37: #4 | E37: Invoiced and paid 9 Oct (£800 of the £1,000 agreed 24 Sep).
A38: Saw blades and drill bits (Toolstation) | B38: =SUMIFS('Contingency Drawdown'!$E$8:$E$60,'Contingency Drawdown'!$A$8:$A$60,33) -> 84.97 | D38: #33 | E38: Bought by Luke on his card 6 Oct; repaid in cash 13 Oct. Tagged Main deck, used throughout.
A39: Digger hire | B39: =SUMIFS('Contingency Drawdown'!$E$8:$E$60,'Contingency Drawdown'!$A$8:$A$60,10) -> 378.58 | D39: #10 | E39: 3–8 Sep, on Luke's TP account.
A40: Dumper hire | B40: =SUMIFS('Contingency Drawdown'!$E$8:$E$60,'Contingency Drawdown'!$A$8:$A$60,28) -> 277.79 | D40: #28 | E40: 2–8 Sep, on Luke's TP account.
A41: Clean-up + small tree dig | B41: =SUMIFS('Contingency Drawdown'!$E$8:$E$60,'Contingency Drawdown'!$A$8:$A$60,12) -> 180 | D41: #12 | E41: Invoiced and paid 11 Sep.
A42: Fence move labour | B42: =SUMIFS('Contingency Drawdown'!$E$8:$E$60,'Contingency Drawdown'!$A$8:$A$60,13) -> 315 | D42: #13 | E42: Chimney side / side (a) boundary. Paid 11 Sep.
A43: Fence materials | B43: =SUMIFS('Contingency Drawdown'!$E$8:$E$60,'Contingency Drawdown'!$A$8:$A$60,23) -> 291.17 | D43: #23 | E43: Travis Perkins invoice 1051142985.
A44: Check against section 2 (must be 0.00) | B44: =ROUND((B39+B40+B41-B16)+(B42+B43-B17),2) -> 0
A46: 4. Would the pot have held for what it was set up for?
A47: Item | B47: £ | E47: Notes
A48: Drawn on the 1 Jul purposes so far (fence + TP main-deck materials) | B48: =B17+B35 -> 2198.32 | E48: Fence relocation plus 'cement and bricks'.
A49: Plus: curved-decking labour (#4) — invoiced 9 Oct | B49: =SUMIFS('Contingency Drawdown'!$E$8:$E$60,'Contingency Drawdown'!$A$8:$A$60,4)+SUMIFS('Contingency Drawdown'!$H$8:$H$60,'Contingency Drawdown'!$A$8:$A$60,4) -> 800 | E49: Agreed 24 Sep at £1,000 full price / £900 cash; Luke invoiced £800 on INV-0293.
A50: Total for the originally intended purposes | B50: =B48+B49 -> 2998.32
A51: Pot | B51: =B6 -> 5000
A52: Headroom if only the original purposes had been drawn | B52: =B51-B50 -> 2001.68 | E52: The pot would have held, with room to spare.
A53: Everything else drawn (not on the 1 Jul list) | B53: =B7-B48-B49 -> 13661.65 | E53: New scope, hire, screw top-ups, chimney/coping extras and the additional deck labour (£1,050). Also Luke's saw blades and drill bits (£84.97). Also the 17 Oct LG INV-0294 (£1,350: driveway channel £350 and extra decking labour £1,000). Also the pipe lagging (£177.58, 20 Oct). Also V4 QUO-0040 (£1,268, 22 Oct). Also the £1,200 soft wash (19 Oct).
A55: 5. How the pot was used up
A56: Point in time | B56: £ drawn | C56: vs pot | E56: Notes
A57: Tracker view on 24 Sep (before the V4 order and the TP paper copies) | B57: =B7-B26-SUMIFS('Contingency Drawdown'!$E$8:$E$60,'Contingency Drawdown'!$A$8:$A$60,">=25",'Contingency Drawdown'!$A$8:$A$60,"<=30")-B30-B37-B38-B19-B31-SUMIFS('Contingency Drawdown'!$E$8:$E$60,'Contingency Drawdown'!$A$8:$A$60,37)-SUMIFS('Contingency Drawdown'!$E$8:$E$60,'Contingency Drawdown'!$A$8:$A$60,38)-SUMIFS('Contingency Drawdown'!$E$8:$E$60,'Contingency Drawdown'!$A$8:$A$60,34) -> 4313.11 | C57: =IF(B57>B$6,"Over","Within") -> Within | E57: 86% of the pot — it looked on track.
A58: On invoice dates, by 11 Sep | B58: =SUMIFS('Contingency Drawdown'!$E$8:$E$60,'Contingency Drawdown'!$B$8:$B$60,"<="&DATE(2026,9,11)) -> 5017.83 | C58: =IF(B58>B$6,"Over","Within") -> Over | E58: The pot was already used up by the extra digging, fence move and fence materials — before the V4 order, but not yet visible because Travis Perkins invoices were still being gathered.
A59: After the V4 order, 29 Sep | B59: =B57+B26 -> 9635.85 | C59: =IF(B59>B$6,"Over","Within") -> Over | E59: The single biggest step.
A60: After the TP paper copies were added, 3 Oct | B60: =B7-B30-B37-B38-B19-B31-SUMIFS('Contingency Drawdown'!$E$8:$E$60,'Contingency Drawdown'!$A$8:$A$60,37)-SUMIFS('Contingency Drawdown'!$E$8:$E$60,'Contingency Drawdown'!$A$8:$A$60,38)-SUMIFS('Contingency Drawdown'!$E$8:$E$60,'Contingency Drawdown'!$A$8:$A$60,34) -> 10729.42 | C60: =IF(B60>B$6,"Over","Within") -> Over | E60: Six more TP invoices (£1,093.57) added once Luke supplied the paper copies.
A61: After INV-0293 (curves and additional deck), 9 Oct | B61: =B7-B38-B19-B31-SUMIFS('Contingency Drawdown'!$E$8:$E$60,'Contingency Drawdown'!$A$8:$A$60,37)-SUMIFS('Contingency Drawdown'!$E$8:$E$60,'Contingency Drawdown'!$A$8:$A$60,38)-SUMIFS('Contingency Drawdown'!$E$8:$E$60,'Contingency Drawdown'!$A$8:$A$60,34) -> 12579.42 | C61: =IF(B61>B$6,"Over","Within") -> Over | E61: The invoice for the extra curved and additional decking work (£1,850), paid 9 Oct. Travis Perkins was settled 5 Oct without changing the drawn figure.
A62: After the Toolstation saw blades, 13 Oct | B62: =B7-B19-B31-SUMIFS('Contingency Drawdown'!$E$8:$E$60,'Contingency Drawdown'!$A$8:$A$60,37)-SUMIFS('Contingency Drawdown'!$E$8:$E$60,'Contingency Drawdown'!$A$8:$A$60,38)-SUMIFS('Contingency Drawdown'!$E$8:$E$60,'Contingency Drawdown'!$A$8:$A$60,34) -> 12664.39 | C62: =IF(B62>B$6,"Over","Within") -> Over | E62: Luke's saw blades and drill bits (£84.97), repaid in cash 13 Oct.
A63: After LG INV-0294 (driveway channel and extra decking), 17 Oct | B63: =B7-SUMIFS('Contingency Drawdown'!$E$8:$E$60,'Contingency Drawdown'!$A$8:$A$60,37)-SUMIFS('Contingency Drawdown'!$E$8:$E$60,'Contingency Drawdown'!$A$8:$A$60,38)-SUMIFS('Contingency Drawdown'!$E$8:$E$60,'Contingency Drawdown'!$A$8:$A$60,34) -> 14014.39 | C63: =IF(B63>B$6,"Over","Within") -> Over | E63: £350 driveway channel plus £1,000 extra decking labour, paid 17 Oct by bank transfer.
A64: After the soft wash was paid, 19 Oct | B64: =B7-SUMIFS('Contingency Drawdown'!$E$8:$E$60,'Contingency Drawdown'!$A$8:$A$60,37)-SUMIFS('Contingency Drawdown'!$E$8:$E$60,'Contingency Drawdown'!$A$8:$A$60,38) -> 15214.39 | C64: =IF(B64>B$6,"Over","Within") -> Over | E64: Whole-house soft wash (£1,200), paid in cash on the day.
A65: After the pipe lagging order, 20 Oct | B65: =B7-SUMIFS('Contingency Drawdown'!$E$8:$E$60,'Contingency Drawdown'!$A$8:$A$60,38) -> 15391.97 | C65: =IF(B65>B$6,"Over","Within") -> Over | E65: Pipe lagging for the outside tap/pipework (£177.58), paid by Ryan's card 20 Oct.
A66: After V4 QUO-0040, 22 Oct | B66: =B7 -> 16659.97 | C66: =IF(B66>B$6,"Over","Within") -> Over | E66: V4 materials to complete the decking substructure (£1,268), paid by card 22 Oct.
A68: 6. Not yet in the figure
A69: Item | B69: £ | D69: Status | E69: Notes
A70: Curved decking labour (#4) — resolved | B70: =SUMIFS('Contingency Drawdown'!$H$8:$H$60,'Contingency Drawdown'!$A$8:$A$60,4) -> 0 | D70: Invoiced 9 Oct | E70: Agreed £1,000; INV-0293 billed £800, so nothing pending. The other £200 is not expected unless Luke bills it later.
A71: Additional lead work (#31, Gantt task 1.5a) | B71: =SUMIFS('Contingency Drawdown'!$H$8:$H$60,'Contingency Drawdown'!$A$8:$A$60,31) -> 200 | D71: Work complete 16 Oct, awaiting invoice | E71: Part of Gate 2 — lead flashing finished Fri 16 Oct. Luke has not yet invoiced the ~£200 estimate.
A72: V4 subframe screw top-up #3 (#15) | B72: =SUMIFS('Contingency Drawdown'!$H$8:$H$60,'Contingency Drawdown'!$A$8:$A$60,15) -> 47.22 | D72: Invoiced, unpaid (due 12 Oct) | E72: V4 invoice #336484, £47.22 for additional screws. Replaces the earlier £141.66 estimate. Logged in Cost Lines only until paid.
A73: Whole-house soft wash (#34, Gorgeous Cleaning Services) | B73: =SUMIFS('Contingency Drawdown'!$H$8:$H$60,'Contingency Drawdown'!$A$8:$A$60,34) -> 0 | D73: Paid 19 Oct (cash) | E73: £1,200 cash, from Contingency; completed and paid Mon 19 Oct. Now in the drawn figure, so nothing pending.
A74: Known pending | B74: =SUM(B70:B73) -> 247.22
A75: Luke's extended-deck labour still to come — low (3.5 days x £700, less £1,000 invoiced 17 Oct) | B75: =3.5*700-B31 -> 1450 | D75: Not agreed or logged | E75: From Luke's 2 Oct figures (2 people x 1 day = £700) and his 5–6 day estimate, less the 1.5 days invoiced as the £1,050 additional deck on INV-0293 and the £1,000 extra decking labour on INV-0294 (my arithmetic: £1,000 counted against the same estimate; Luke has not confirmed this).
A76: Luke's extended-deck labour still to come — high (4.5 days x £700, less £1,000 invoiced 17 Oct) | B76: =4.5*700-B31 -> 2150 | D76: Not agreed or logged | E76: Same basis as above, at the top of his 5–6 day range.
A77: Illustrative drawn if all of the above land in Contingency — low | B77: =B7+B74+B75 -> 18357.19 | E77: Depends on how Luke invoices the extended deck.
A78: Illustrative drawn if all of the above land in Contingency — high | B78: =B7+B74+B76 -> 19057.19
A80: 7. Scope added after the project began — and where each piece sits
A81: Item | B81: £ | D81: Where it sits | E81: Notes
A82: Extended deck & shed base, and the fence relocation | B82: =B14+B17 -> 10977.97 | D82: Contingency | E82: Not on the 1 Jul list.
A83: Roofline works — budget | B83: =Summary!C12 -> 2100 | D83: Own budget line (not Contingency) | E83: The £2,140 quote (4 Sep) is £2,100 here plus £40 rubbish removal, which sits in the pooled skips fund.
A84: Roofline works — invoiced and paid to date | B84: =Summary!D12 -> 1984.93 | D84: Own budget line | E84: Labour INV-0291 plus four materials invoices.
A85: Roofline works: the roofline works quote was also unseen at the start of the project. Although it now has its own budget line, it was not part of the original scope. It is kept out of Contingency, so it is not in the drawn figure above — but, like the extended deck, it is a later addition to the project.

Sheet Contingency Drawdown
A1: Contingency Drawdown — £5,000 pot (agreed Lara/Luke, 1 Jul 2026)
A2: One row per named purpose (#1–#38), sorted by purpose number. Drawn and Paid come from the Invoice Register (matched on its 'Named purpose #' column); Pending comes from Cost Lines. Sort or filter freely: 'pot remaining' is worked out from the invoice dates, so it stays correct in any order. Travis Perkins invoices were settled on 5 Oct (net £2,169.04 after Luke's 6 Oct repayment — see TP Account).
A4: Opening pot: | B4: 5000 | C4: Remaining: | D4: =B4-SUM($E$8:$E$60) -> -11659.97
A5: Drawn: | B5: =SUM($E$8:$E$60) -> 16659.97 | C5: Paid: | D5: =SUM($F$8:$F$60) -> 16659.97 | E5: Pending: | F5: =SUM($H$8:$H$60) -> 247.22
C6: Check vs Register (must be 0.00): | D6: =ROUND(SUM($E$8:$E$60)-SUMIF('Invoice Register'!$B:$B,"Contingency",'Invoice Register'!$F:$F),2) -> 0
A7: Named purpose # | B7: Invoice date | C7: Purpose | D7: Supplier / detail | E7: Drawn £ | F7: Paid £ | G7: Unpaid £ | H7: Pending (not yet drawn) £ | I7: Status | J7: Scope | K7: Pot remaining at this invoice date £ | L7: Notes
A8: 1 | C8: Fence move / repair labour | D8: Luke (LG Building and Roofing) | E8: =IF($A8="","",SUMIFS('Invoice Register'!$F:$F,'Invoice Register'!$B:$B,"Contingency",'Invoice Register'!$L:$L,$A8)) -> 0 | F8: =IF($A8="","",SUMIFS('Invoice Register'!$F:$F,'Invoice Register'!$B:$B,"Contingency",'Invoice Register'!$L:$L,$A8,'Invoice Register'!$G:$G,"<>")) -> 0 | G8: =IF($A8="","",E8-F8) -> 0 | H8: =IF($A8="","",IF(E8>0,0,SUMIF('Cost Lines'!$C:$C,"*purpose #"&$A8&" *",'Cost Lines'!$F:$F))) -> 0 | I8: Superseded by #13 | J8: Fence relocation | K8: =IF(OR($A8="",$B8=""),"",$B$4-SUMIFS($E$8:$E$60,$B$8:$B$60,"<="&$B8)) | L8: On the 1 Jul list. Superseded by #13 (fence move, chimney side).
A9: 2 | C9: Soakaway fix before decking | D9: — | E9: =IF($A9="","",SUMIFS('Invoice Register'!$F:$F,'Invoice Register'!$B:$B,"Contingency",'Invoice Register'!$L:$L,$A9)) -> 0 | F9: =IF($A9="","",SUMIFS('Invoice Register'!$F:$F,'Invoice Register'!$B:$B,"Contingency",'Invoice Register'!$L:$L,$A9,'Invoice Register'!$G:$G,"<>")) -> 0 | G9: =IF($A9="","",E9-F9) -> 0 | H9: =IF($A9="","",IF(E9>0,0,SUMIF('Cost Lines'!$C:$C,"*purpose #"&$A9&" *",'Cost Lines'!$F:$F))) -> 0 | I9: Cancelled 1 Sep | K9: =IF(OR($A9="",$B9=""),"",$B$4-SUMIFS($E$8:$E$60,$B$8:$B$60,"<="&$B9)) | L9: On the 1 Jul list. CANCELLED 1 Sep — cost-benefit not worth it. Nothing drawn.
A10: 3 | C10: Drainage by the garage | D10: — | E10: =IF($A10="","",SUMIFS('Invoice Register'!$F:$F,'Invoice Register'!$B:$B,"Contingency",'Invoice Register'!$L:$L,$A10)) -> 0 | F10: =IF($A10="","",SUMIFS('Invoice Register'!$F:$F,'Invoice Register'!$B:$B,"Contingency",'Invoice Register'!$L:$L,$A10,'Invoice Register'!$G:$G,"<>")) -> 0 | G10: =IF($A10="","",E10-F10) -> 0 | H10: =IF($A10="","",IF(E10>0,0,SUMIF('Cost Lines'!$C:$C,"*purpose #"&$A10&" *",'Cost Lines'!$F:$F))) -> 0 | I10: Nothing drawn | K10: =IF(OR($A10="",$B10=""),"",$B$4-SUMIFS($E$8:$E$60,$B$8:$B$60,"<="&$B10)) | L10: On the 1 Jul list. Nothing drawn.
A11: 4 | B11: 46304 | C11: Additional curved-decking labour | D11: Luke (LG Building and Roofing) | E11: =IF($A11="","",SUMIFS('Invoice Register'!$F:$F,'Invoice Register'!$B:$B,"Contingency",'Invoice Register'!$L:$L,$A11)) -> 800 | F11: =IF($A11="","",SUMIFS('Invoice Register'!$F:$F,'Invoice Register'!$B:$B,"Contingency",'Invoice Register'!$L:$L,$A11,'Invoice Register'!$G:$G,"<>")) -> 800 | G11: =IF($A11="","",E11-F11) -> 0 | H11: =IF($A11="","",IF(E11>0,0,SUMIF('Cost Lines'!$C:$C,"*purpose #"&$A11&" *",'Cost Lines'!$F:$F))) -> 0 | I11: =IF(E11>0,IF(F11>=E11-0.005,"Paid",IF(F11>0,"Part paid","Invoiced, unpaid")),IF(H11>0,"Not yet invoiced","")) -> Paid | J11: Main deck | K11: =IF(OR($A11="",$B11=""),"",$B$4-SUMIFS($E$8:$E$60,$B$8:$B$60,"<="&$B11)) -> -7664.39 | L11: On the 1 Jul list. AGREED 24 Sep at £1,000 full price / £900 cash. INVOICED 9 Oct: £800 on INV-0293 (the curves), paid the same day by bank transfer — Luke billed £800, not the £1,000 agreed. The other £200 is not expected unless Luke bills it.
A12: 5 | C12: Cement & bricks | D12: — | E12: =IF($A12="","",SUMIFS('Invoice Register'!$F:$F,'Invoice Register'!$B:$B,"Contingency",'Invoice Register'!$L:$L,$A12)) -> 0 | F12: =IF($A12="","",SUMIFS('Invoice Register'!$F:$F,'Invoice Register'!$B:$B,"Contingency",'Invoice Register'!$L:$L,$A12,'Invoice Register'!$G:$G,"<>")) -> 0 | G12: =IF($A12="","",E12-F12) -> 0 | H12: =IF($A12="","",IF(E12>0,0,SUMIF('Cost Lines'!$C:$C,"*purpose #"&$A12&" *",'Cost Lines'!$F:$F))) -> 0 | I12: Covered by #16–#30 | K12: =IF(OR($A12="",$B12=""),"",$B$4-SUMIFS($E$8:$E$60,$B$8:$B$60,"<="&$B12)) | L12: On the 1 Jul list. Actual draws are recorded under the specific Travis Perkins purposes #16–#30.
A13: 6 | B13: 46247 | C13: Coping condensation-prep (labour + DPC roll) | D13: LG Building and Roofing Ltd — INV-0288; LG Building and Roofing Ltd (Travis Perkins account) — TP invoice 1048887075 | E13: =IF($A13="","",SUMIFS('Invoice Register'!$F:$F,'Invoice Register'!$B:$B,"Contingency",'Invoice Register'!$L:$L,$A13)) -> 276.42 | F13: =IF($A13="","",SUMIFS('Invoice Register'!$F:$F,'Invoice Register'!$B:$B,"Contingency",'Invoice Register'!$L:$L,$A13,'Invoice Register'!$G:$G,"<>")) -> 276.42 | G13: =IF($A13="","",E13-F13) -> 0 | H13: =IF($A13="","",IF(E13>0,0,SUMIF('Cost Lines'!$C:$C,"*purpose #"&$A13&" *",'Cost Lines'!$F:$F))) -> 0 | I13: =IF(E13>0,IF(F13>=E13-0.005,"Paid",IF(F13>0,"Part paid","Invoiced, unpaid")),IF(H13>0,"Not yet invoiced","")) -> Paid | J13: Chimney & coping | K13: =IF(OR($A13="",$B13=""),"",$B$4-SUMIFS($E$8:$E$60,$B$8:$B$60,"<="&$B13)) -> 4552.54 | L13: Labour £250 (INV-0288, 14 Aug) + Damplas DPC roll £26.42 (17 Aug).
A14: 7 | B14: 46244 | C14: Chimney cowl upgrade — stainless steel | D14: StoveWorldUK — Order #147399 | E14: =IF($A14="","",SUMIFS('Invoice Register'!$F:$F,'Invoice Register'!$B:$B,"Contingency",'Invoice Register'!$L:$L,$A14)) -> 62.9 | F14: =IF($A14="","",SUMIFS('Invoice Register'!$F:$F,'Invoice Register'!$B:$B,"Contingency",'Invoice Register'!$L:$L,$A14,'Invoice Register'!$G:$G,"<>")) -> 62.9 | G14: =IF($A14="","",E14-F14) -> 0 | H14: =IF($A14="","",IF(E14>0,0,SUMIF('Cost Lines'!$C:$C,"*purpose #"&$A14&" *",'Cost Lines'!$F:$F))) -> 0 | I14: =IF(E14>0,IF(F14>=E14-0.005,"Paid",IF(F14>0,"Part paid","Invoiced, unpaid")),IF(H14>0,"Not yet invoiced","")) -> Paid | J14: Chimney & coping | K14: =IF(OR($A14="",$B14=""),"",$B$4-SUMIFS($E$8:$E$60,$B$8:$B$60,"<="&$B14)) -> 4937.1
A15: 8 | B15: 46258 | C15: V4 subframe screw top-up | D15: V4 Wood Flooring Ltd — V4FQ-17702 | E15: =IF($A15="","",SUMIFS('Invoice Register'!$F:$F,'Invoice Register'!$B:$B,"Contingency",'Invoice Register'!$L:$L,$A15)) -> 141.66 | F15: =IF($A15="","",SUMIFS('Invoice Register'!$F:$F,'Invoice Register'!$B:$B,"Contingency",'Invoice Register'!$L:$L,$A15,'Invoice Register'!$G:$G,"<>")) -> 141.66 | G15: =IF($A15="","",E15-F15) -> 0 | H15: =IF($A15="","",IF(E15>0,0,SUMIF('Cost Lines'!$C:$C,"*purpose #"&$A15&" *",'Cost Lines'!$F:$F))) -> 0 | I15: =IF(E15>0,IF(F15>=E15-0.005,"Paid",IF(F15>0,"Part paid","Invoiced, unpaid")),IF(H15>0,"Not yet invoiced","")) -> Paid | J15: Main deck | K15: =IF(OR($A15="",$B15=""),"",$B$4-SUMIFS($E$8:$E$60,$B$8:$B$60,"<="&$B15)) -> 3359.68 | L15: 15 boxes of structural subframe screws.
A16: 9 | B16: 46275 | C16: V4 subframe screw top-up #2 | D16: V4 Wood Flooring Ltd — TBC | E16: =IF($A16="","",SUMIFS('Invoice Register'!$F:$F,'Invoice Register'!$B:$B,"Contingency",'Invoice Register'!$L:$L,$A16)) -> 141.66 | F16: =IF($A16="","",SUMIFS('Invoice Register'!$F:$F,'Invoice Register'!$B:$B,"Contingency",'Invoice Register'!$L:$L,$A16,'Invoice Register'!$G:$G,"<>")) -> 141.66 | G16: =IF($A16="","",E16-F16) -> 0 | H16: =IF($A16="","",IF(E16>0,0,SUMIF('Cost Lines'!$C:$C,"*purpose #"&$A16&" *",'Cost Lines'!$F:$F))) -> 0 | I16: =IF(E16>0,IF(F16>=E16-0.005,"Paid",IF(F16>0,"Part paid","Invoiced, unpaid")),IF(H16>0,"Not yet invoiced","")) -> Paid | J16: Main deck | K16: =IF(OR($A16="",$B16=""),"",$B$4-SUMIFS($E$8:$E$60,$B$8:$B$60,"<="&$B16)) -> 2406.63 | L16: 15 boxes of structural subframe screws. Paid 10 Sep.
A17: 10 | B17: 46274 | C17: Digger hire | D17: Travis Perkins Hire (Luke's account) — 1051011143 | E17: =IF($A17="","",SUMIFS('Invoice Register'!$F:$F,'Invoice Register'!$B:$B,"Contingency",'Invoice Register'!$L:$L,$A17)) -> 378.58 | F17: =IF($A17="","",SUMIFS('Invoice Register'!$F:$F,'Invoice Register'!$B:$B,"Contingency",'Invoice Register'!$L:$L,$A17,'Invoice Register'!$G:$G,"<>")) -> 378.58 | G17: =IF($A17="","",E17-F17) -> 0 | H17: =IF($A17="","",IF(E17>0,0,SUMIF('Cost Lines'!$C:$C,"*purpose #"&$A17&" *",'Cost Lines'!$F:$F))) -> 0 | I17: =IF(E17>0,IF(F17>=E17-0.005,"Paid",IF(F17>0,"Part paid","Invoiced, unpaid")),IF(H17>0,"Not yet invoiced","")) -> Paid | J17: Groundworks (digger & dumper) | K17: =IF(OR($A17="",$B17=""),"",$B$4-SUMIFS($E$8:$E$60,$B$8:$B$60,"<="&$B17)) -> 2673.02 | L17: 3–8 Sep, Travis Perkins Hire. Actual invoice £378.58 replaced the £530 estimate; no barrow loader charge appears on the invoice (flagged, not assumed).
A18: 11 | B18: 46276 | C18: Extra digging — wider gate area + shed/additional deck | D18: LG Building and Roofing Ltd (cash) | E18: =IF($A18="","",SUMIFS('Invoice Register'!$F:$F,'Invoice Register'!$B:$B,"Contingency",'Invoice Register'!$L:$L,$A18)) -> 1260 | F18: =IF($A18="","",SUMIFS('Invoice Register'!$F:$F,'Invoice Register'!$B:$B,"Contingency",'Invoice Register'!$L:$L,$A18,'Invoice Register'!$G:$G,"<>")) -> 1260 | G18: =IF($A18="","",E18-F18) -> 0 | H18: =IF($A18="","",IF(E18>0,0,SUMIF('Cost Lines'!$C:$C,"*purpose #"&$A18&" *",'Cost Lines'!$F:$F))) -> 0 | I18: =IF(E18>0,IF(F18>=E18-0.005,"Paid",IF(F18>0,"Part paid","Invoiced, unpaid")),IF(H18>0,"Not yet invoiced","")) -> Paid | J18: Extended deck & shed base | K18: =IF(OR($A18="",$B18=""),"",$B$4-SUMIFS($E$8:$E$60,$B$8:$B$60,"<="&$B18)) -> -17.83 | L18: Part of Luke's 11 Sep extras invoice (£2,350 quoted, £2,115 paid after the 10% cash discount).
A19: 12 | B19: 46276 | C19: Clean-up + small tree dig | D19: LG Building and Roofing Ltd (cash) | E19: =IF($A19="","",SUMIFS('Invoice Register'!$F:$F,'Invoice Register'!$B:$B,"Contingency",'Invoice Register'!$L:$L,$A19)) -> 180 | F19: =IF($A19="","",SUMIFS('Invoice Register'!$F:$F,'Invoice Register'!$B:$B,"Contingency",'Invoice Register'!$L:$L,$A19,'Invoice Register'!$G:$G,"<>")) -> 180 | G19: =IF($A19="","",E19-F19) -> 0 | H19: =IF($A19="","",IF(E19>0,0,SUMIF('Cost Lines'!$C:$C,"*purpose #"&$A19&" *",'Cost Lines'!$F:$F))) -> 0 | I19: =IF(E19>0,IF(F19>=E19-0.005,"Paid",IF(F19>0,"Part paid","Invoiced, unpaid")),IF(H19>0,"Not yet invoiced","")) -> Paid | J19: Groundworks (digger & dumper) | K19: =IF(OR($A19="",$B19=""),"",$B$4-SUMIFS($E$8:$E$60,$B$8:$B$60,"<="&$B19)) -> -17.83 | L19: Part of Luke's 11 Sep extras invoice.
A20: 13 | B20: 46276 | C20: Fence move — chimney side / side (a) boundary reclaim | D20: LG Building and Roofing Ltd (cash) | E20: =IF($A20="","",SUMIFS('Invoice Register'!$F:$F,'Invoice Register'!$B:$B,"Contingency",'Invoice Register'!$L:$L,$A20)) -> 315 | F20: =IF($A20="","",SUMIFS('Invoice Register'!$F:$F,'Invoice Register'!$B:$B,"Contingency",'Invoice Register'!$L:$L,$A20,'Invoice Register'!$G:$G,"<>")) -> 315 | G20: =IF($A20="","",E20-F20) -> 0 | H20: =IF($A20="","",IF(E20>0,0,SUMIF('Cost Lines'!$C:$C,"*purpose #"&$A20&" *",'Cost Lines'!$F:$F))) -> 0 | I20: =IF(E20>0,IF(F20>=E20-0.005,"Paid",IF(F20>0,"Part paid","Invoiced, unpaid")),IF(H20>0,"Not yet invoiced","")) -> Paid | J20: Fence relocation | K20: =IF(OR($A20="",$B20=""),"",$B$4-SUMIFS($E$8:$E$60,$B$8:$B$60,"<="&$B20)) -> -17.83 | L20: Part of Luke's 11 Sep extras invoice. Supersedes #1.
A21: 14 | B21: 46276 | C21: Extra frame — wider deck gate area | D21: LG Building and Roofing Ltd (cash) | E21: =IF($A21="","",SUMIFS('Invoice Register'!$F:$F,'Invoice Register'!$B:$B,"Contingency",'Invoice Register'!$L:$L,$A21)) -> 360 | F21: =IF($A21="","",SUMIFS('Invoice Register'!$F:$F,'Invoice Register'!$B:$B,"Contingency",'Invoice Register'!$L:$L,$A21,'Invoice Register'!$G:$G,"<>")) -> 360 | G21: =IF($A21="","",E21-F21) -> 0 | H21: =IF($A21="","",IF(E21>0,0,SUMIF('Cost Lines'!$C:$C,"*purpose #"&$A21&" *",'Cost Lines'!$F:$F))) -> 0 | I21: =IF(E21>0,IF(F21>=E21-0.005,"Paid",IF(F21>0,"Part paid","Invoiced, unpaid")),IF(H21>0,"Not yet invoiced","")) -> Paid | J21: Extended deck & shed base | K21: =IF(OR($A21="",$B21=""),"",$B$4-SUMIFS($E$8:$E$60,$B$8:$B$60,"<="&$B21)) -> -17.83 | L21: Part of Luke's 11 Sep extras invoice.
A22: 15 | C22: V4 subframe screw top-up #3 | D22: V4 Wood Flooring Ltd | E22: =IF($A22="","",SUMIFS('Invoice Register'!$F:$F,'Invoice Register'!$B:$B,"Contingency",'Invoice Register'!$L:$L,$A22)) -> 0 | F22: =IF($A22="","",SUMIFS('Invoice Register'!$F:$F,'Invoice Register'!$B:$B,"Contingency",'Invoice Register'!$L:$L,$A22,'Invoice Register'!$G:$G,"<>")) -> 0 | G22: =IF($A22="","",E22-F22) -> 0 | H22: =IF($A22="","",IF(E22>0,0,SUMIF('Cost Lines'!$C:$C,"*purpose #"&$A22&" *",'Cost Lines'!$F:$F))) -> 47.22 | I22: Invoiced, unpaid (£47.22) | J22: Main deck | K22: =IF(OR($A22="",$B22=""),"",$B$4-SUMIFS($E$8:$E$60,$B$8:$B$60,"<="&$B22)) | L22: V4 invoice #336484, £47.22, due 12 Oct, 'additional screws' — received but STILL UNPAID (17 Oct). Replaces the earlier £141.66 / 15-box estimate. Logged in Cost Lines only until paid.
A23: 16 | B23: 46252 | C23: TP materials — cement, blade | D23: Travis Perkins (Luke's account) — 1049651867 | E23: =IF($A23="","",SUMIFS('Invoice Register'!$F:$F,'Invoice Register'!$B:$B,"Contingency",'Invoice Register'!$L:$L,$A23)) -> 144.58 | F23: =IF($A23="","",SUMIFS('Invoice Register'!$F:$F,'Invoice Register'!$B:$B,"Contingency",'Invoice Register'!$L:$L,$A23,'Invoice Register'!$G:$G,"<>")) -> 144.58 | G23: =IF($A23="","",E23-F23) -> 0 | H23: =IF($A23="","",IF(E23>0,0,SUMIF('Cost Lines'!$C:$C,"*purpose #"&$A23&" *",'Cost Lines'!$F:$F))) -> 0 | I23: =IF(E23>0,IF(F23>=E23-0.005,"Paid",IF(F23>0,"Part paid","Invoiced, unpaid")),IF(H23>0,"Not yet invoiced","")) -> Paid | J23: Main deck | K23: =IF(OR($A23="",$B23=""),"",$B$4-SUMIFS($E$8:$E$60,$B$8:$B$60,"<="&$B23)) -> 4060.84 | L23: Travis Perkins invoice 1049651867.
A24: 17 | B24: 46253 | C24: TP materials — plywood, drill bit, screws, gloves | D24: Travis Perkins (Luke's account) — 1049757851 | E24: =IF($A24="","",SUMIFS('Invoice Register'!$F:$F,'Invoice Register'!$B:$B,"Contingency",'Invoice Register'!$L:$L,$A24)) -> 74.34 | F24: =IF($A24="","",SUMIFS('Invoice Register'!$F:$F,'Invoice Register'!$B:$B,"Contingency",'Invoice Register'!$L:$L,$A24,'Invoice Register'!$G:$G,"<>")) -> 74.34 | G24: =IF($A24="","",E24-F24) -> 0 | H24: =IF($A24="","",IF(E24>0,0,SUMIF('Cost Lines'!$C:$C,"*purpose #"&$A24&" *",'Cost Lines'!$F:$F))) -> 0 | I24: =IF(E24>0,IF(F24>=E24-0.005,"Paid",IF(F24>0,"Part paid","Invoiced, unpaid")),IF(H24>0,"Not yet invoiced","")) -> Paid | J24: Main deck | K24: =IF(OR($A24="",$B24=""),"",$B$4-SUMIFS($E$8:$E$60,$B$8:$B$60,"<="&$B24)) -> 3986.5 | L24: Travis Perkins invoice 1049757851.
A25: 18 | B25: 46254 | C25: TP materials — ballast, cement, blocks, pallet deposit | D25: Travis Perkins (Luke's account) — 1049844268 | E25: =IF($A25="","",SUMIFS('Invoice Register'!$F:$F,'Invoice Register'!$B:$B,"Contingency",'Invoice Register'!$L:$L,$A25)) -> 462.5 | F25: =IF($A25="","",SUMIFS('Invoice Register'!$F:$F,'Invoice Register'!$B:$B,"Contingency",'Invoice Register'!$L:$L,$A25,'Invoice Register'!$G:$G,"<>")) -> 462.5 | G25: =IF($A25="","",E25-F25) -> 0 | H25: =IF($A25="","",IF(E25>0,0,SUMIF('Cost Lines'!$C:$C,"*purpose #"&$A25&" *",'Cost Lines'!$F:$F))) -> 0 | I25: =IF(E25>0,IF(F25>=E25-0.005,"Paid",IF(F25>0,"Part paid","Invoiced, unpaid")),IF(H25>0,"Not yet invoiced","")) -> Paid | J25: Main deck | K25: =IF(OR($A25="",$B25=""),"",$B$4-SUMIFS($E$8:$E$60,$B$8:$B$60,"<="&$B25)) -> 3501.34 | L25: Travis Perkins invoice 1049844268. Includes a £30.30 REFUNDABLE pallet deposit (not a final cost).
A26: 19 | B26: 46254 | C26: TP materials — flat packers | D26: Travis Perkins (Luke's account) — 1049844267 | E26: =IF($A26="","",SUMIFS('Invoice Register'!$F:$F,'Invoice Register'!$B:$B,"Contingency",'Invoice Register'!$L:$L,$A26)) -> 22.66 | F26: =IF($A26="","",SUMIFS('Invoice Register'!$F:$F,'Invoice Register'!$B:$B,"Contingency",'Invoice Register'!$L:$L,$A26,'Invoice Register'!$G:$G,"<>")) -> 22.66 | G26: =IF($A26="","",E26-F26) -> 0 | H26: =IF($A26="","",IF(E26>0,0,SUMIF('Cost Lines'!$C:$C,"*purpose #"&$A26&" *",'Cost Lines'!$F:$F))) -> 0 | I26: =IF(E26>0,IF(F26>=E26-0.005,"Paid",IF(F26>0,"Part paid","Invoiced, unpaid")),IF(H26>0,"Not yet invoiced","")) -> Paid | J26: Main deck | K26: =IF(OR($A26="",$B26=""),"",$B$4-SUMIFS($E$8:$E$60,$B$8:$B$60,"<="&$B26)) -> 3501.34 | L26: Travis Perkins invoice 1049844267.
A27: 20 | B27: 46273 | C27: TP materials — plywood, line marker | D27: Travis Perkins (Luke's account) — 1050903283 | E27: =IF($A27="","",SUMIFS('Invoice Register'!$F:$F,'Invoice Register'!$B:$B,"Contingency",'Invoice Register'!$L:$L,$A27)) -> 58.62 | F27: =IF($A27="","",SUMIFS('Invoice Register'!$F:$F,'Invoice Register'!$B:$B,"Contingency",'Invoice Register'!$L:$L,$A27,'Invoice Register'!$G:$G,"<>")) -> 58.62 | G27: =IF($A27="","",E27-F27) -> 0 | H27: =IF($A27="","",IF(E27>0,0,SUMIF('Cost Lines'!$C:$C,"*purpose #"&$A27&" *",'Cost Lines'!$F:$F))) -> 0 | I27: =IF(E27>0,IF(F27>=E27-0.005,"Paid",IF(F27>0,"Part paid","Invoiced, unpaid")),IF(H27>0,"Not yet invoiced","")) -> Paid | J27: Main deck | K27: =IF(OR($A27="",$B27=""),"",$B$4-SUMIFS($E$8:$E$60,$B$8:$B$60,"<="&$B27)) -> 3051.6 | L27: Travis Perkins invoice 1050903283.
A28: 21 | B28: 46275 | C28: TP materials — ballast, cement | D28: Travis Perkins (Luke's account) — 1051072869 | E28: =IF($A28="","",SUMIFS('Invoice Register'!$F:$F,'Invoice Register'!$B:$B,"Contingency",'Invoice Register'!$L:$L,$A28)) -> 124.73 | F28: =IF($A28="","",SUMIFS('Invoice Register'!$F:$F,'Invoice Register'!$B:$B,"Contingency",'Invoice Register'!$L:$L,$A28,'Invoice Register'!$G:$G,"<>")) -> 124.73 | G28: =IF($A28="","",E28-F28) -> 0 | H28: =IF($A28="","",IF(E28>0,0,SUMIF('Cost Lines'!$C:$C,"*purpose #"&$A28&" *",'Cost Lines'!$F:$F))) -> 0 | I28: =IF(E28>0,IF(F28>=E28-0.005,"Paid",IF(F28>0,"Part paid","Invoiced, unpaid")),IF(H28>0,"Not yet invoiced","")) -> Paid | J28: Main deck | K28: =IF(OR($A28="",$B28=""),"",$B$4-SUMIFS($E$8:$E$60,$B$8:$B$60,"<="&$B28)) -> 2406.63 | L28: Travis Perkins invoice 1051072869.
A29: 22 | B29: 46276 | C29: TP materials — gloves, woodscrews | D29: Travis Perkins (Luke's account) — 1051162218 | E29: =IF($A29="","",SUMIFS('Invoice Register'!$F:$F,'Invoice Register'!$B:$B,"Contingency",'Invoice Register'!$L:$L,$A29)) -> 18.29 | F29: =IF($A29="","",SUMIFS('Invoice Register'!$F:$F,'Invoice Register'!$B:$B,"Contingency",'Invoice Register'!$L:$L,$A29,'Invoice Register'!$G:$G,"<>")) -> 18.29 | G29: =IF($A29="","",E29-F29) -> 0 | H29: =IF($A29="","",IF(E29>0,0,SUMIF('Cost Lines'!$C:$C,"*purpose #"&$A29&" *",'Cost Lines'!$F:$F))) -> 0 | I29: =IF(E29>0,IF(F29>=E29-0.005,"Paid",IF(F29>0,"Part paid","Invoiced, unpaid")),IF(H29>0,"Not yet invoiced","")) -> Paid | J29: Shared / site-wide | K29: =IF(OR($A29="",$B29=""),"",$B$4-SUMIFS($E$8:$E$60,$B$8:$B$60,"<="&$B29)) -> -17.83 | L29: Travis Perkins invoice 1051162218.
A30: 23 | B30: 46276 | C30: TP fence materials — posts, Postcrete, rail brackets, pegs, timber | D30: Travis Perkins (Luke's account) — 1051142985 | E30: =IF($A30="","",SUMIFS('Invoice Register'!$F:$F,'Invoice Register'!$B:$B,"Contingency",'Invoice Register'!$L:$L,$A30)) -> 291.17 | F30: =IF($A30="","",SUMIFS('Invoice Register'!$F:$F,'Invoice Register'!$B:$B,"Contingency",'Invoice Register'!$L:$L,$A30,'Invoice Register'!$G:$G,"<>")) -> 291.17 | G30: =IF($A30="","",E30-F30) -> 0 | H30: =IF($A30="","",IF(E30>0,0,SUMIF('Cost Lines'!$C:$C,"*purpose #"&$A30&" *",'Cost Lines'!$F:$F))) -> 0 | I30: =IF(E30>0,IF(F30>=E30-0.005,"Paid",IF(F30>0,"Part paid","Invoiced, unpaid")),IF(H30>0,"Not yet invoiced","")) -> Paid | J30: Fence relocation | K30: =IF(OR($A30="",$B30=""),"",$B$4-SUMIFS($E$8:$E$60,$B$8:$B$60,"<="&$B30)) -> -17.83 | L30: Travis Perkins invoice 1051142985.
A31: 24 | B31: 46294 | C31: V4 materials — shed area / extended deck | D31: V4 Wood Flooring Ltd — QUO-0031 | E31: =IF($A31="","",SUMIFS('Invoice Register'!$F:$F,'Invoice Register'!$B:$B,"Contingency",'Invoice Register'!$L:$L,$A31)) -> 5322.74 | F31: =IF($A31="","",SUMIFS('Invoice Register'!$F:$F,'Invoice Register'!$B:$B,"Contingency",'Invoice Register'!$L:$L,$A31,'Invoice Register'!$G:$G,"<>")) -> 5322.74 | G31: =IF($A31="","",E31-F31) -> 0 | H31: =IF($A31="","",IF(E31>0,0,SUMIF('Cost Lines'!$C:$C,"*purpose #"&$A31&" *",'Cost Lines'!$F:$F))) -> 0 | I31: =IF(E31>0,IF(F31>=E31-0.005,"Paid",IF(F31>0,"Part paid","Invoiced, unpaid")),IF(H31>0,"Not yet invoiced","")) -> Paid | J31: Extended deck & shed base | K31: =IF(OR($A31="",$B31=""),"",$B$4-SUMIFS($E$8:$E$60,$B$8:$B$60,"<="&$B31)) -> -5729.42 | L31: Quote QUO-0031, placed and paid by phone 29 Sep. On its own larger than the whole pot.
A32: 25 | B32: 46245 | C32: TP materials — sand, white cement, Bosch blade | D32: Travis Perkins (Luke's account) — 1049231418 | E32: =IF($A32="","",SUMIFS('Invoice Register'!$F:$F,'Invoice Register'!$B:$B,"Contingency",'Invoice Register'!$L:$L,$A32)) -> 108.14 | F32: =IF($A32="","",SUMIFS('Invoice Register'!$F:$F,'Invoice Register'!$B:$B,"Contingency",'Invoice Register'!$L:$L,$A32,'Invoice Register'!$G:$G,"<>")) -> 108.14 | G32: =IF($A32="","",E32-F32) -> 0 | H32: =IF($A32="","",IF(E32>0,0,SUMIF('Cost Lines'!$C:$C,"*purpose #"&$A32&" *",'Cost Lines'!$F:$F))) -> 0 | I32: =IF(E32>0,IF(F32>=E32-0.005,"Paid",IF(F32>0,"Part paid","Invoiced, unpaid")),IF(H32>0,"Not yet invoiced","")) -> Paid | J32: Main deck | K32: =IF(OR($A32="",$B32=""),"",$B$4-SUMIFS($E$8:$E$60,$B$8:$B$60,"<="&$B32)) -> 4828.96 | L32: Travis Perkins invoice 1049231418. Paid from the £500 TP receipt of 11 Sep.
A33: 26 | B33: 46251 | C33: TP materials — ballast, building sand, 72 blocks | D33: Travis Perkins (Luke's account) — 1049595624 | E33: =IF($A33="","",SUMIFS('Invoice Register'!$F:$F,'Invoice Register'!$B:$B,"Contingency",'Invoice Register'!$L:$L,$A33)) -> 347.12 | F33: =IF($A33="","",SUMIFS('Invoice Register'!$F:$F,'Invoice Register'!$B:$B,"Contingency",'Invoice Register'!$L:$L,$A33,'Invoice Register'!$G:$G,"<>")) -> 347.12 | G33: =IF($A33="","",E33-F33) -> 0 | H33: =IF($A33="","",IF(E33>0,0,SUMIF('Cost Lines'!$C:$C,"*purpose #"&$A33&" *",'Cost Lines'!$F:$F))) -> 0 | I33: =IF(E33>0,IF(F33>=E33-0.005,"Paid",IF(F33>0,"Part paid","Invoiced, unpaid")),IF(H33>0,"Not yet invoiced","")) -> Paid | J33: Main deck | K33: =IF(OR($A33="",$B33=""),"",$B$4-SUMIFS($E$8:$E$60,$B$8:$B$60,"<="&$B33)) -> 4205.42 | L33: Travis Perkins invoice 1049595624. £247.01 paid from the £500 receipt; £100.11 balance paid by card 5 Oct.
A34: 27 | B34: 46268 | C34: TP materials — ballast x2, Mastercrete x10 | D34: Travis Perkins (Luke's account) — 1050655200 | E34: =IF($A34="","",SUMIFS('Invoice Register'!$F:$F,'Invoice Register'!$B:$B,"Contingency",'Invoice Register'!$L:$L,$A34)) -> 249.46 | F34: =IF($A34="","",SUMIFS('Invoice Register'!$F:$F,'Invoice Register'!$B:$B,"Contingency",'Invoice Register'!$L:$L,$A34,'Invoice Register'!$G:$G,"<>")) -> 249.46 | G34: =IF($A34="","",E34-F34) -> 0 | H34: =IF($A34="","",IF(E34>0,0,SUMIF('Cost Lines'!$C:$C,"*purpose #"&$A34&" *",'Cost Lines'!$F:$F))) -> 0 | I34: =IF(E34>0,IF(F34>=E34-0.005,"Paid",IF(F34>0,"Part paid","Invoiced, unpaid")),IF(H34>0,"Not yet invoiced","")) -> Paid | J34: Main deck | K34: =IF(OR($A34="",$B34=""),"",$B$4-SUMIFS($E$8:$E$60,$B$8:$B$60,"<="&$B34)) -> 3110.22 | L34: Travis Perkins invoice 1050655200.
... A37: 30 | B37: 46286 | C37: TP materials — 20 blocks | D37: Travis Perkins (Luke's account) — 1051708772 | E37: =IF($A37="","",SUMIFS('Invoice Register'!$F:$F,'Invoice Register'!$B:$B,"Contingency",'Invoice Register'!$L:$L,$A37)) -> 50.76 | F37: =IF($A37="","",SUMIFS('Invoice Register'!$F:$F,'Invoice Register'!$B:$B,"Contingency",'Invoice Register'!$L:$L,$A37,'Invoice Register'!$G:$G,"<>")) -> 50.76 | G37: =IF($A37="","",E37-F37) -> 0 | H37: =IF($A37="","",IF(E37>0,0,SUMIF('Cost Lines'!$C:$C,"*purpose #"&$A37&" *",'Cost Lines'!$F:$F))) -> 0 | I37: =IF(E37>0,IF(F37>=E37-0.005,"Paid",IF(F37>0,"Part paid","Invoiced, unpaid")),IF(H37>0,"Not yet invoiced","")) -> Paid | J37: Extended deck & shed base | K37: =IF(OR($A37="",$B37=""),"",$B$4-SUMIFS($E$8:$E$60,$B$8:$B$60,"<="&$B37)) -> -406.68 | L37: Travis Perkins invoice 1051708772.
A38: 31 | C38: Additional lead work — back-of-house gutters | D38: Luke (LG Building and Roofing) | E38: =IF($A38="","",SUMIFS('Invoice Register'!$F:$F,'Invoice Register'!$B:$B,"Contingency",'Invoice Register'!$L:$L,$A38)) -> 0 | F38: =IF($A38="","",SUMIFS('Invoice Register'!$F:$F,'Invoice Register'!$B:$B,"Contingency",'Invoice Register'!$L:$L,$A38,'Invoice Register'!$G:$G,"<>")) -> 0 | G38: =IF($A38="","",E38-F38) -> 0 | H38: =IF($A38="","",IF(E38>0,0,SUMIF('Cost Lines'!$C:$C,"*purpose #"&$A38&" *",'Cost Lines'!$F:$F))) -> 200 | I38: =IF(E38>0,IF(F38>=E38-0.005,"Paid",IF(F38>0,"Part paid","Invoiced, unpaid")),IF(H38>0,"Not yet invoiced","")) -> Not yet invoiced | J38: Roofline | K38: =IF(OR($A38="",$B38=""),"",$B$4-SUMIFS($E$8:$E$60,$B$8:$B$60,"<="&$B38)) | L38: Gantt task 1.5a, part of Gate 2. Chase lead into the walls so the gutters work properly. Luke's estimate about £200 (2 Oct), work completed Fri 16 Oct (lead flashing confirmed included); awaiting Luke's invoice.
A39: 32 | B39: 46304 | C39: Additional deck labour — extended deck & shed base | D39: Luke (LG Building and Roofing) — INV-0293 | E39: =IF($A39="","",SUMIFS('Invoice Register'!$F:$F,'Invoice Register'!$B:$B,"Contingency",'Invoice Register'!$L:$L,$A39)) -> 1050 | F39: =IF($A39="","",SUMIFS('Invoice Register'!$F:$F,'Invoice Register'!$B:$B,"Contingency",'Invoice Register'!$L:$L,$A39,'Invoice Register'!$G:$G,"<>")) -> 1050 | G39: =IF($A39="","",E39-F39) -> 0 | H39: =IF($A39="","",IF(E39>0,0,SUMIF('Cost Lines'!$C:$C,"*purpose #"&$A39&" *",'Cost Lines'!$F:$F))) -> 0 | I39: =IF($A39="","",IF(E39>0,IF(F39>=E39-0.005,"Paid",IF(F39>0,"Part paid","Invoiced, unpaid")),IF(H39>0,"Not yet invoiced",""))) -> Paid | J39: Extended deck & shed base | K39: =IF(OR($A39="",$B39=""),"",$B$4-SUMIFS($E$8:$E$60,$B$8:$B$60,"<="&$B39)) -> -7664.39 | L39: Part of LG INV-0293 (£1,850, 9 Oct): the £1,050 for the additional deck. The other £800 is the curves (#4). Paid 9 Oct by bank transfer. Separate from the £17,600 main decking labour draws.
A40: 33 | B40: 46301 | C40: Saw blades and drill bits — Toolstation | D40: Toolstation Ltd — YAC545477716 (bought by Luke) | E40: =IF($A40="","",SUMIFS('Invoice Register'!$F:$F,'Invoice Register'!$B:$B,"Contingency",'Invoice Register'!$L:$L,$A40)) -> 84.97 | F40: =IF($A40="","",SUMIFS('Invoice Register'!$F:$F,'Invoice Register'!$B:$B,"Contingency",'Invoice Register'!$L:$L,$A40,'Invoice Register'!$G:$G,"<>")) -> 84.97 | G40: =IF($A40="","",E40-F40) -> 0 | H40: =IF($A40="","",IF(E40>0,0,SUMIF('Cost Lines'!$C:$C,"*purpose #"&$A40&" *",'Cost Lines'!$F:$F))) -> 0 | I40: =IF($A40="","",IF(E40>0,IF(F40>=E40-0.005,"Paid",IF(F40>0,"Part paid","Invoiced, unpaid")),IF(H40>0,"Not yet invoiced",""))) -> Paid | J40: Main deck | K40: =IF(OR($A40="",$B40=""),"",$B$4-SUMIFS($E$8:$E$60,$B$8:$B$60,"<="&$B40)) -> -5814.39 | L40: Freud mitre saw blade, ROKTOR drill bits, DeWalt circular saw blade (£84.97). Luke paid by card 6 Oct; repaid in cash 13 Oct. Scope Main deck, although the tools will be used throughout the project.
A41: 34 | B41: 46314 | C41: Whole-house soft wash — Gorgeous Cleaning Services | D41: Gorgeous Cleaning Services | E41: =IF($A41="","",SUMIFS('Invoice Register'!$F:$F,'Invoice Register'!$B:$B,"Contingency",'Invoice Register'!$L:$L,$A41)) -> 1200 | F41: =IF($A41="","",SUMIFS('Invoice Register'!$F:$F,'Invoice Register'!$B:$B,"Contingency",'Invoice Register'!$L:$L,$A41,'Invoice Register'!$G:$G,"<>")) -> 1200 | G41: =IF($A41="","",E41-F41) -> 0 | H41: =IF($A41="","",IF(E41>0,0,SUMIF('Cost Lines'!$C:$C,"*purpose #"&$A41&" *",'Cost Lines'!$F:$F))) -> 0 | I41: =IF($A41="","",IF(E41>0,IF(F41>=E41-0.005,"Paid",IF(F41>0,"Part paid","Invoiced, unpaid")),IF(H41>0,"Not yet invoiced",""))) -> Paid | J41: Shared / site-wide | K41: =IF(OR($A41="",$B41=""),"",$B$4-SUMIFS($E$8:$E$60,$B$8:$B$60,"<="&$B41)) -> -10214.39 | L41: £1,200 cash, from Contingency, paid Mon 19 Oct. Gutters, soffits, roof tiles, roof solar panels, render, windows etc. Started and finished that day. Replaces the chimney + coping-only soft wash.
A42: 35 | B42: 46312 | C42: Driveway channel — water-softener waste | D42: Luke (LG Building and Roofing) — INV-0294 | E42: =IF($A42="","",SUMIFS('Invoice Register'!$F:$F,'Invoice Register'!$B:$B,"Contingency",'Invoice Register'!$L:$L,$A42)) -> 350 | F42: =IF($A42="","",SUMIFS('Invoice Register'!$F:$F,'Invoice Register'!$B:$B,"Contingency",'Invoice Register'!$L:$L,$A42,'Invoice Register'!$G:$G,"<>")) -> 350 | G42: =IF($A42="","",E42-F42) -> 0 | H42: =IF($A42="","",IF(E42>0,0,SUMIF('Cost Lines'!$C:$C,"*purpose #"&$A42&" *",'Cost Lines'!$F:$F))) -> 0 | I42: =IF($A42="","",IF(E42>0,IF(F42>=E42-0.005,"Paid",IF(F42>0,"Part paid","Invoiced, unpaid")),IF(H42>0,"Not yet invoiced",""))) -> Paid | J42: Driveway channel | K42: =IF(OR($A42="",$B42=""),"",$B$4-SUMIFS($E$8:$E$60,$B$8:$B$60,"<="&$B42)) -> -9014.39 | L42: Half a day, Luke and Max, 14 Oct (Gantt 3.1). Water-softener discharge connected to natural drainage; cobbles reinstated; discharge confirmed working. £350 of LG INV-0294 (£1,350), paid 17 Oct by bank transfer.
A43: 36 | B43: 46312 | C43: Extra decking labour — extended deck & shed base | D43: Luke (LG Building and Roofing) — INV-0294 | E43: =IF($A43="","",SUMIFS('Invoice Register'!$F:$F,'Invoice Register'!$B:$B,"Contingency",'Invoice Register'!$L:$L,$A43)) -> 1000 | F43: =IF($A43="","",SUMIFS('Invoice Register'!$F:$F,'Invoice Register'!$B:$B,"Contingency",'Invoice Register'!$L:$L,$A43,'Invoice Register'!$G:$G,"<>")) -> 1000 | G43: =IF($A43="","",E43-F43) -> 0 | H43: =IF($A43="","",IF(E43>0,0,SUMIF('Cost Lines'!$C:$C,"*purpose #"&$A43&" *",'Cost Lines'!$F:$F))) -> 0 | I43: =IF($A43="","",IF(E43>0,IF(F43>=E43-0.005,"Paid",IF(F43>0,"Part paid","Invoiced, unpaid")),IF(H43>0,"Not yet invoiced",""))) -> Paid | J43: Extended deck & shed base | K43: =IF(OR($A43="",$B43=""),"",$B$4-SUMIFS($E$8:$E$60,$B$8:$B$60,"<="&$B43)) -> -9014.39 | L43: £1,000 of LG INV-0294 (£1,350), paid 17 Oct by bank transfer. Extra decking labour as discussed. No further extended-deck labour agreed yet.
A44: 37 | B44: 46315 | C44: Pipe lagging — outside tap/pipework | D44: Buy Insulation Online — INV842429677 | E44: =IF($A44="","",SUMIFS('Invoice Register'!$F:$F,'Invoice Register'!$B:$B,"Contingency",'Invoice Register'!$L:$L,$A44)) -> 177.58 | F44: =IF($A44="","",SUMIFS('Invoice Register'!$F:$F,'Invoice Register'!$B:$B,"Contingency",'Invoice Register'!$L:$L,$A44,'Invoice Register'!$G:$G,"<>")) -> 177.58 | G44: =IF($A44="","",E44-F44) -> 0 | H44: =IF($A44="","",IF(E44>0,0,SUMIF('Cost Lines'!$C:$C,"*purpose #"&$A44&" *",'Cost Lines'!$F:$F))) -> 0 | I44: =IF($A44="","",IF(E44>0,IF(F44>=E44-0.005,"Paid",IF(F44>0,"Part paid","Invoiced, unpaid")),IF(H44>0,"Not yet invoiced",""))) -> Paid | J44: Shared / site-wide | K44: =IF(OR($A44="",$B44=""),"",$B$4-SUMIFS($E$8:$E$60,$B$8:$B$60,"<="&$B44)) -> -10391.97 | L44: 7 x Stornch outdoor pipe insulation (£177.58 inc VAT), paid by Ryan's card 20 Oct. For the outside tap/pipework (Gantt 2.4, Gate 3). Scope site-wide (main deck).
A45: 38 | B45: 46317 | C45: V4 materials to complete the decking substructure | D45: V4 Wood Flooring Ltd — QUO-0040 | E45: =IF($A45="","",SUMIFS('Invoice Register'!$F:$F,'Invoice Register'!$B:$B,"Contingency",'Invoice Register'!$L:$L,$A45)) -> 1268 | F45: =IF($A45="","",SUMIFS('Invoice Register'!$F:$F,'Invoice Register'!$B:$B,"Contingency",'Invoice Register'!$L:$L,$A45,'Invoice Register'!$G:$G,"<>")) -> 1268 | G45: =IF($A45="","",E45-F45) -> 0 | H45: =IF($A45="","",IF(E45>0,0,SUMIF('Cost Lines'!$C:$C,"*purpose #"&$A45&" *",'Cost Lines'!$F:$F))) -> 0 | I45: =IF($A45="","",IF(E45>0,IF(F45>=E45-0.005,"Paid",IF(F45>0,"Part paid","Invoiced, unpaid")),IF(H45>0,"Not yet invoiced",""))) -> Paid | J45: Extended deck & shed base | K45: =IF(OR($A45="",$B45=""),"",$B$4-SUMIFS($E$8:$E$60,$B$8:$B$60,"<="&$B45)) -> -11659.97 | L45: Delivered Mon 19 Oct; paid by card 22 Oct (£1,268). Some of the Plas-Pro will likely be used on the main decking.

Sheet Scope View
A1: Scope View — what the money was for
A2: Cost centre = which budget pays; Scope = what it was for. Source: the Scope column on the Invoice Register. Amounts invoiced, inc VAT. Scope tags on Travis Perkins invoices are INFERRED: Luke's 2 Oct update says only 1 day (2 people) has been spent on the extended deck so far, so only TP invoices from 21 Sep are treated as extended; earlier ones are main deck. Digger/dumper hire served both and is not split. Confirm with Luke. LG INV-0293 (9 Oct) is split: £800 curves (Main deck) and £1,050 additional deck (Extended deck & shed base). Toolstation saw blades (13 Oct, £84.97) are tagged Main deck although used throughout. LG INV-0294 (17 Oct) is split: £350 driveway channel (new scope, Driveway channel) and £1,000 extra decking labour (Extended deck & shed base). Pipe lagging (20 Oct, £177.58) is tagged Shared / site-wide (main deck). V4 QUO-0040 (22 Oct, £1,268) is tagged Extended deck & shed base, though some Plas-Pro will likely be used on the main decking. New scope "New shed & electrics" (workstream 8) covers the shed, its installation and the electrics; nothing invoiced against it yet.
A4: A. Invoiced by scope and cost centre
A5: Scope | B5: Decking materials (V4) | C5: Decking labour | D5: Contingency | E5: Roofline works | F5: Chimney repair | G5: Coping stones repair | H5: Materials (pooled) | I5: Rubbish removal (pooled skips) | J5: Total invoiced £ | K5: Total paid £ | L5: Unpaid £
A6: Main deck | B6: =SUMIFS('Invoice Register'!$F:$F,'Invoice Register'!$B:$B,B$5,'Invoice Register'!$J:$J,$A6) -> 32228.99 | C6: =SUMIFS('Invoice Register'!$F:$F,'Invoice Register'!$B:$B,C$5,'Invoice Register'!$J:$J,$A6) -> 8400 | D6: =SUMIFS('Invoice Register'!$F:$F,'Invoice Register'!$B:$B,D$5,'Invoice Register'!$J:$J,$A6) -> 2760.44 | E6: =SUMIFS('Invoice Register'!$F:$F,'Invoice Register'!$B:$B,E$5,'Invoice Register'!$J:$J,$A6) -> 0 | F6: =SUMIFS('Invoice Register'!$F:$F,'Invoice Register'!$B:$B,F$5,'Invoice Register'!$J:$J,$A6) -> 0 | G6: =SUMIFS('Invoice Register'!$F:$F,'Invoice Register'!$B:$B,G$5,'Invoice Register'!$J:$J,$A6) -> 0 | H6: =SUMIFS('Invoice Register'!$F:$F,'Invoice Register'!$B:$B,H$5,'Invoice Register'!$J:$J,$A6) -> 0 | I6: =SUMIFS('Invoice Register'!$F:$F,'Invoice Register'!$B:$B,I$5,'Invoice Register'!$J:$J,$A6) -> 680 | J6: =SUM(B6:I6) -> 44069.43 | K6: =SUMIFS('Invoice Register'!$F:$F,'Invoice Register'!$J:$J,$A6,'Invoice Register'!$G:$G,"<>") -> 44069.43 | L6: =J6-K6 -> 0
A7: Extended deck & shed base | B7: =SUMIFS('Invoice Register'!$F:$F,'Invoice Register'!$B:$B,B$5,'Invoice Register'!$J:$J,$A7) -> 0 | C7: =SUMIFS('Invoice Register'!$F:$F,'Invoice Register'!$B:$B,C$5,'Invoice Register'!$J:$J,$A7) -> 0 | D7: =SUMIFS('Invoice Register'!$F:$F,'Invoice Register'!$B:$B,D$5,'Invoice Register'!$J:$J,$A7) -> 10371.8 | E7: =SUMIFS('Invoice Register'!$F:$F,'Invoice Register'!$B:$B,E$5,'Invoice Register'!$J:$J,$A7) -> 0 | F7: =SUMIFS('Invoice Register'!$F:$F,'Invoice Register'!$B:$B,F$5,'Invoice Register'!$J:$J,$A7) -> 0 | G7: =SUMIFS('Invoice Register'!$F:$F,'Invoice Register'!$B:$B,G$5,'Invoice Register'!$J:$J,$A7) -> 0 | H7: =SUMIFS('Invoice Register'!$F:$F,'Invoice Register'!$B:$B,H$5,'Invoice Register'!$J:$J,$A7) -> 0 | I7: =SUMIFS('Invoice Register'!$F:$F,'Invoice Register'!$B:$B,I$5,'Invoice Register'!$J:$J,$A7) -> 0 | J7: =SUM(B7:I7) -> 10371.8 | K7: =SUMIFS('Invoice Register'!$F:$F,'Invoice Register'!$J:$J,$A7,'Invoice Register'!$G:$G,"<>") -> 10371.8 | L7: =J7-K7 -> 0
A8: Fence relocation | B8: =SUMIFS('Invoice Register'!$F:$F,'Invoice Register'!$B:$B,B$5,'Invoice Register'!$J:$J,$A8) -> 0 | C8: =SUMIFS('Invoice Register'!$F:$F,'Invoice Register'!$B:$B,C$5,'Invoice Register'!$J:$J,$A8) -> 0 | D8: =SUMIFS('Invoice Register'!$F:$F,'Invoice Register'!$B:$B,D$5,'Invoice Register'!$J:$J,$A8) -> 606.17 | E8: =SUMIFS('Invoice Register'!$F:$F,'Invoice Register'!$B:$B,E$5,'Invoice Register'!$J:$J,$A8) -> 0 | F8: =SUMIFS('Invoice Register'!$F:$F,'Invoice Register'!$B:$B,F$5,'Invoice Register'!$J:$J,$A8) -> 0 | G8: =SUMIFS('Invoice Register'!$F:$F,'Invoice Register'!$B:$B,G$5,'Invoice Register'!$J:$J,$A8) -> 0 | H8: =SUMIFS('Invoice Register'!$F:$F,'Invoice Register'!$B:$B,H$5,'Invoice Register'!$J:$J,$A8) -> 0 | I8: =SUMIFS('Invoice Register'!$F:$F,'Invoice Register'!$B:$B,I$5,'Invoice Register'!$J:$J,$A8) -> 0 | J8: =SUM(B8:I8) -> 606.17 | K8: =SUMIFS('Invoice Register'!$F:$F,'Invoice Register'!$J:$J,$A8,'Invoice Register'!$G:$G,"<>") -> 606.17 | L8: =J8-K8 -> 0
A9: Groundworks (digger & dumper) | B9: =SUMIFS('Invoice Register'!$F:$F,'Invoice Register'!$B:$B,B$5,'Invoice Register'!$J:$J,$A9) -> 0 | C9: =SUMIFS('Invoice Register'!$F:$F,'Invoice Register'!$B:$B,C$5,'Invoice Register'!$J:$J,$A9) -> 0 | D9: =SUMIFS('Invoice Register'!$F:$F,'Invoice Register'!$B:$B,D$5,'Invoice Register'!$J:$J,$A9) -> 836.37 | E9: =SUMIFS('Invoice Register'!$F:$F,'Invoice Register'!$B:$B,E$5,'Invoice Register'!$J:$J,$A9) -> 0 | F9: =SUMIFS('Invoice Register'!$F:$F,'Invoice Register'!$B:$B,F$5,'Invoice Register'!$J:$J,$A9) -> 0 | G9: =SUMIFS('Invoice Register'!$F:$F,'Invoice Register'!$B:$B,G$5,'Invoice Register'!$J:$J,$A9) -> 0 | H9: =SUMIFS('Invoice Register'!$F:$F,'Invoice Register'!$B:$B,H$5,'Invoice Register'!$J:$J,$A9) -> 0 | I9: =SUMIFS('Invoice Register'!$F:$F,'Invoice Register'!$B:$B,I$5,'Invoice Register'!$J:$J,$A9) -> 0 | J9: =SUM(B9:I9) -> 836.37 | K9: =SUMIFS('Invoice Register'!$F:$F,'Invoice Register'!$J:$J,$A9,'Invoice Register'!$G:$G,"<>") -> 836.37 | L9: =J9-K9 -> 0
A10: Roofline | B10: =SUMIFS('Invoice Register'!$F:$F,'Invoice Register'!$B:$B,B$5,'Invoice Register'!$J:$J,$A10) -> 0 | C10: =SUMIFS('Invoice Register'!$F:$F,'Invoice Register'!$B:$B,C$5,'Invoice Register'!$J:$J,$A10) -> 0 | D10: =SUMIFS('Invoice Register'!$F:$F,'Invoice Register'!$B:$B,D$5,'Invoice Register'!$J:$J,$A10) -> 0 | E10: =SUMIFS('Invoice Register'!$F:$F,'Invoice Register'!$B:$B,E$5,'Invoice Register'!$J:$J,$A10) -> 1984.93 | F10: =SUMIFS('Invoice Register'!$F:$F,'Invoice Register'!$B:$B,F$5,'Invoice Register'!$J:$J,$A10) -> 0 | G10: =SUMIFS('Invoice Register'!$F:$F,'Invoice Register'!$B:$B,G$5,'Invoice Register'!$J:$J,$A10) -> 0 | H10: =SUMIFS('Invoice Register'!$F:$F,'Invoice Register'!$B:$B,H$5,'Invoice Register'!$J:$J,$A10) -> 0 | I10: =SUMIFS('Invoice Register'!$F:$F,'Invoice Register'!$B:$B,I$5,'Invoice Register'!$J:$J,$A10) -> 0 | J10: =SUM(B10:I10) -> 1984.93 | K10: =SUMIFS('Invoice Register'!$F:$F,'Invoice Register'!$J:$J,$A10,'Invoice Register'!$G:$G,"<>") -> 1984.93 | L10: =J10-K10 -> 0
A11: Chimney & coping | B11: =SUMIFS('Invoice Register'!$F:$F,'Invoice Register'!$B:$B,B$5,'Invoice Register'!$J:$J,$A11) -> 0 | C11: =SUMIFS('Invoice Register'!$F:$F,'Invoice Register'!$B:$B,C$5,'Invoice Register'!$J:$J,$A11) -> 0 | D11: =SUMIFS('Invoice Register'!$F:$F,'Invoice Register'!$B:$B,D$5,'Invoice Register'!$J:$J,$A11) -> 339.32 | E11: =SUMIFS('Invoice Register'!$F:$F,'Invoice Register'!$B:$B,E$5,'Invoice Register'!$J:$J,$A11) -> 0 | F11: =SUMIFS('Invoice Register'!$F:$F,'Invoice Register'!$B:$B,F$5,'Invoice Register'!$J:$J,$A11) -> 4700.01 | G11: =SUMIFS('Invoice Register'!$F:$F,'Invoice Register'!$B:$B,G$5,'Invoice Register'!$J:$J,$A11) -> 5310 | H11: =SUMIFS('Invoice Register'!$F:$F,'Invoice Register'!$B:$B,H$5,'Invoice Register'!$J:$J,$A11) -> 1120.69 | I11: =SUMIFS('Invoice Register'!$F:$F,'Invoice Register'!$B:$B,I$5,'Invoice Register'!$J:$J,$A11) -> 0 | J11: =SUM(B11:I11) -> 11470.02 | K11: =SUMIFS('Invoice Register'!$F:$F,'Invoice Register'!$J:$J,$A11,'Invoice Register'!$G:$G,"<>") -> 11470.02 | L11: =J11-K11 -> 0
A12: Driveway channel | B12: =SUMIFS('Invoice Register'!$F:$F,'Invoice Register'!$B:$B,B$5,'Invoice Register'!$J:$J,$A12) -> 0 | C12: =SUMIFS('Invoice Register'!$F:$F,'Invoice Register'!$B:$B,C$5,'Invoice Register'!$J:$J,$A12) -> 0 | D12: =SUMIFS('Invoice Register'!$F:$F,'Invoice Register'!$B:$B,D$5,'Invoice Register'!$J:$J,$A12) -> 350 | E12: =SUMIFS('Invoice Register'!$F:$F,'Invoice Register'!$B:$B,E$5,'Invoice Register'!$J:$J,$A12) -> 0 | F12: =SUMIFS('Invoice Register'!$F:$F,'Invoice Register'!$B:$B,F$5,'Invoice Register'!$J:$J,$A12) -> 0 | G12: =SUMIFS('Invoice Register'!$F:$F,'Invoice Register'!$B:$B,G$5,'Invoice Register'!$J:$J,$A12) -> 0 | H12: =SUMIFS('Invoice Register'!$F:$F,'Invoice Register'!$B:$B,H$5,'Invoice Register'!$J:$J,$A12) -> 0 | I12: =SUMIFS('Invoice Register'!$F:$F,'Invoice Register'!$B:$B,I$5,'Invoice Register'!$J:$J,$A12) -> 0 | J12: =SUM(B12:I12) -> 350 | K12: =SUMIFS('Invoice Register'!$F:$F,'Invoice Register'!$J:$J,$A12,'Invoice Register'!$G:$G,"<>") -> 350 | L12: =J14-K14 -> 0
A13: New shed & electrics | B13: =SUMIFS('Invoice Register'!$F:$F,'Invoice Register'!$B:$B,B$5,'Invoice Register'!$J:$J,$A13) -> 0 | C13: =SUMIFS('Invoice Register'!$F:$F,'Invoice Register'!$B:$B,C$5,'Invoice Register'!$J:$J,$A13) -> 0 | D13: =SUMIFS('Invoice Register'!$F:$F,'Invoice Register'!$B:$B,D$5,'Invoice Register'!$J:$J,$A13) -> 0 | E13: =SUMIFS('Invoice Register'!$F:$F,'Invoice Register'!$B:$B,E$5,'Invoice Register'!$J:$J,$A13) -> 0 | F13: =SUMIFS('Invoice Register'!$F:$F,'Invoice Register'!$B:$B,F$5,'Invoice Register'!$J:$J,$A13) -> 0 | G13: =SUMIFS('Invoice Register'!$F:$F,'Invoice Register'!$B:$B,G$5,'Invoice Register'!$J:$J,$A13) -> 0 | H13: =SUMIFS('Invoice Register'!$F:$F,'Invoice Register'!$B:$B,H$5,'Invoice Register'!$J:$J,$A13) -> 0 | I13: =SUMIFS('Invoice Register'!$F:$F,'Invoice Register'!$B:$B,I$5,'Invoice Register'!$J:$J,$A13) -> 0 | J13: =SUM(B13:I13) -> 0 | K13: =SUMIFS('Invoice Register'!$F:$F,'Invoice Register'!$J:$J,$A13,'Invoice Register'!$G:$G,"<>") -> 0 | L13: =J14-K14 -> 0
A14: Shared / site-wide | B14: =SUMIFS('Invoice Register'!$F:$F,'Invoice Register'!$B:$B,B$5,'Invoice Register'!$J:$J,$A14) -> 0 | C14: =SUMIFS('Invoice Register'!$F:$F,'Invoice Register'!$B:$B,C$5,'Invoice Register'!$J:$J,$A14) -> 0 | D14: =SUMIFS('Invoice Register'!$F:$F,'Invoice Register'!$B:$B,D$5,'Invoice Register'!$J:$J,$A14) -> 1395.87 | E14: =SUMIFS('Invoice Register'!$F:$F,'Invoice Register'!$B:$B,E$5,'Invoice Register'!$J:$J,$A14) -> 0 | F14: =SUMIFS('Invoice Register'!$F:$F,'Invoice Register'!$B:$B,F$5,'Invoice Register'!$J:$J,$A14) -> 0 | G14: =SUMIFS('Invoice Register'!$F:$F,'Invoice Register'!$B:$B,G$5,'Invoice Register'!$J:$J,$A14) -> 0 | H14: =SUMIFS('Invoice Register'!$F:$F,'Invoice Register'!$B:$B,H$5,'Invoice Register'!$J:$J,$A14) -> 0 | I14: =SUMIFS('Invoice Register'!$F:$F,'Invoice Register'!$B:$B,I$5,'Invoice Register'!$J:$J,$A14) -> 780 | J14: =SUM(B14:I14) -> 2175.87 | K14: =SUMIFS('Invoice Register'!$F:$F,'Invoice Register'!$J:$J,$A14,'Invoice Register'!$G:$G,"<>") -> 2175.87 | L14: =J14-K14 -> 0
A15: TOTAL | B15: =SUM(B6:B14) -> 32228.99 | C15: =SUM(C6:C14) -> 8400 | D15: =SUM(D6:D14) -> 16659.97 | E15: =SUM(E6:E14) -> 1984.93 | F15: =SUM(F6:F14) -> 4700.01 | G15: =SUM(G6:G14) -> 5310 | H15: =SUM(H6:H14) -> 1120.69 | I15: =SUM(I6:I14) -> 1460 | ... L15: =SUM(L6:L14) -> 0
A16: Summary 'Invoiced £' (same cost centre) | B16: =SUMIF(Summary!$A$5:$A$13,B$5,Summary!$D$5:$D$13) -> 32228.99 | C16: =SUMIF(Summary!$A$5:$A$13,C$5,Summary!$D$5:$D$13) -> 8400 | D16: =SUMIF(Summary!$A$5:$A$13,D$5,Summary!$D$5:$D$13) -> 16659.97 | E16: =SUMIF(Summary!$A$5:$A$13,E$5,Summary!$D$5:$D$13) -> 1984.93 | F16: =SUMIF(Summary!$A$5:$A$13,F$5,Summary!$D$5:$D$13) -> 4700.01 | G16: =SUMIF(Summary!$A$5:$A$13,G$5,Summary!$D$5:$D$13) -> 5310 | H16: =SUMIF(Summary!$A$5:$A$13,H$5,Summary!$D$5:$D$13) -> 1120.69 | I16: =SUMIF(Summary!$A$5:$A$13,I$5,Summary!$D$5:$D$13) -> 1460 | J16: =SUM(B16:I16) -> 71864.59
A17: Check: difference (must be 0.00) | B17: =ROUND(B15-B16,2) -> 0 | C17: =ROUND(C15-C16,2) -> 0 | D17: =ROUND(D15-D16,2) -> 0 | E17: =ROUND(E15-E16,2) -> 0 | F17: =ROUND(F15-F16,2) -> 0 | G17: =ROUND(G15-G16,2) -> 0 | H17: =ROUND(H15-H16,2) -> 0 | I17: =ROUND(I15-I16,2) -> 0 | J17: =ROUND(J15-J16,2) -> 0
A19: B. Headlines
A20: Main deck — invoiced to date | B20: =J6 -> 44069.43 | C20: Original V4 order, decking labour, V4 screw top-ups, TP materials invoiced before 21 Sep, old-deck waste removal.
A21: Extended deck & shed base + Fence relocation — invoiced | B21: =J7+J8 -> 10977.97 | C21: New area enabled by the fence move: V4 order #24, extra digging/frame labour, TP materials from 21 Sep, fence materials and labour.
A22: Groundworks — shared by both projects | B22: =J9 -> 836.37 | C22: Digger and dumper hire, clean-up and small tree dig — used for the main deck widening and the new shed area, not split.
A23: Shared / site-wide (skips, small consumables) | B23: =J14 -> 2175.87 | C23: Pooled skip hire and consumables that cannot be split between projects.
A24: Driveway channel — invoiced | B24: =J12 -> 350 | C24: Water-softener waste channel (Gantt 3.1), a rainy-day task done on 14 Oct: half a day, Luke and Max, £350 on LG INV-0294. Drawn from Contingency.
A25: New shed & electrics — invoiced | B25: =J13 -> 0 | C25: Workstream 8: the new shed, its installation and the electrics (first fix done 22 Oct; final fix to follow). Nothing invoiced yet; drawn from Contingency. Earlier substructure spend stays under Extended deck & shed base.
A26: C. Contingency by scope — Register vs Contingency Drawdown
A27: Scope | B27: Invoice Register £ | C27: Drawdown sheet £ | D27: Difference £
A28: Main deck | B28: =SUMIFS('Invoice Register'!$F:$F,'Invoice Register'!$B:$B,"Contingency",'Invoice Register'!$J:$J,$A28) -> 2760.44 | C28: =SUMIFS('Contingency Drawdown'!$E$8:$E$60,'Contingency Drawdown'!$J$8:$J$60,$A28) -> 2760.44 | D28: =ROUND(B28-C28,2) -> 0
A29: Extended deck & shed base | B29: =SUMIFS('Invoice Register'!$F:$F,'Invoice Register'!$B:$B,"Contingency",'Invoice Register'!$J:$J,$A29) -> 10371.8 | C29: =SUMIFS('Contingency Drawdown'!$E$8:$E$60,'Contingency Drawdown'!$J$8:$J$60,$A29) -> 10371.8 | D29: =ROUND(B29-C29,2) -> 0
A30: Fence relocation | B30: =SUMIFS('Invoice Register'!$F:$F,'Invoice Register'!$B:$B,"Contingency",'Invoice Register'!$J:$J,$A30) -> 606.17 | C30: =SUMIFS('Contingency Drawdown'!$E$8:$E$60,'Contingency Drawdown'!$J$8:$J$60,$A30) -> 606.17 | D30: =ROUND(B30-C30,2) -> 0
A31: Groundworks (digger & dumper) | B31: =SUMIFS('Invoice Register'!$F:$F,'Invoice Register'!$B:$B,"Contingency",'Invoice Register'!$J:$J,$A31) -> 836.37 | C31: =SUMIFS('Contingency Drawdown'!$E$8:$E$60,'Contingency Drawdown'!$J$8:$J$60,$A31) -> 836.37 | D31: =ROUND(B31-C31,2) -> 0
A32: Roofline | B32: =SUMIFS('Invoice Register'!$F:$F,'Invoice Register'!$B:$B,"Contingency",'Invoice Register'!$J:$J,$A32) -> 0 | C32: =SUMIFS('Contingency Drawdown'!$E$8:$E$60,'Contingency Drawdown'!$J$8:$J$60,$A32) -> 0 | D32: =ROUND(B32-C32,2) -> 0
A33: Chimney & coping | B33: =SUMIFS('Invoice Register'!$F:$F,'Invoice Register'!$B:$B,"Contingency",'Invoice Register'!$J:$J,$A33) -> 339.32 | C33: =SUMIFS('Contingency Drawdown'!$E$8:$E$60,'Contingency Drawdown'!$J$8:$J$60,$A33) -> 339.32 | D33: =ROUND(B33-C33,2) -> 0
A34: Driveway channel | B34: =SUMIFS('Invoice Register'!$F:$F,'Invoice Register'!$B:$B,"Contingency",'Invoice Register'!$J:$J,$A34) -> 350 | C34: =SUMIFS('Contingency Drawdown'!$E$8:$E$60,'Contingency Drawdown'!$J$8:$J$60,$A34) -> 350 | D34: =ROUND(B34-C34,2) -> 0
A35: New shed & electrics | B35: =SUMIFS('Invoice Register'!$F:$F,'Invoice Register'!$B:$B,"Contingency",'Invoice Register'!$J:$J,$A35) -> 0 | C35: =SUMIFS('Contingency Drawdown'!$E$8:$E$60,'Contingency Drawdown'!$J$8:$J$60,$A35) -> 0 | D35: =ROUND(B35-C35,2) -> 0
A36: Shared / site-wide | B36: =SUMIFS('Invoice Register'!$F:$F,'Invoice Register'!$B:$B,"Contingency",'Invoice Register'!$J:$J,$A36) -> 1395.87 | C36: =SUMIFS('Contingency Drawdown'!$E$8:$E$60,'Contingency Drawdown'!$J$8:$J$60,$A36) -> 1395.87 | D36: =ROUND(B36-C36,2) -> 0
A37: TOTAL | B37: =SUM(B28:B36) -> 16659.97 | C37: =SUM(C28:C36) -> 16659.97 | D37: =ROUND(B37-C37,2) -> 0
A38: Check: Register total vs Summary Contingency 'Invoiced £' (must be 0.00) | B38: =ROUND(B37-Summary!$D$7,2) -> 0
A41: D. Travis Perkins spend by scope (from TP Line Items)
A42: Scope | B42: TP spend £ | C42: Share of TP spend
A43: Main deck | B43: =SUMIFS('TP Line Items'!$F:$F,'TP Line Items'!$G:$G,$A43) -> 1592.15 | C43: =IF($B$52=0,0,B43/$B$52) -> 0.49492993
A44: Extended deck & shed base | B44: =SUMIFS('TP Line Items'!$F:$F,'TP Line Items'!$G:$G,$A44) -> 111.06 | C44: =IF($B$52=0,0,B44/$B$52) -> 0.034523706
A45: Fence relocation | B45: =SUMIFS('TP Line Items'!$F:$F,'TP Line Items'!$G:$G,$A45) -> 291.17 | C45: =IF($B$52=0,0,B45/$B$52) -> 0.090512043
A46: Groundworks (digger & dumper) | B46: =SUMIFS('TP Line Items'!$F:$F,'TP Line Items'!$G:$G,$A46) -> 656.37 | C46: =IF($B$52=0,0,B46/$B$52) -> 0.20403678
A47: Roofline | B47: =SUMIFS('TP Line Items'!$F:$F,'TP Line Items'!$G:$G,$A47) -> 0 | C47: =IF($B$52=0,0,B47/$B$52) -> 0
A48: Chimney & coping | B48: =SUMIFS('TP Line Items'!$F:$F,'TP Line Items'!$G:$G,$A48) -> 547.88 | C48: =IF($B$52=0,0,B48/$B$52) -> 0.17031198
A49: Driveway channel | B49: =SUMIFS('TP Line Items'!$F:$F,'TP Line Items'!$G:$G,$A49) -> 0 | C49: =IF($B$52=0,0,B49/$B$52) -> 0
A50: New shed & electrics | B50: =SUMIFS('TP Line Items'!$F:$F,'TP Line Items'!$G:$G,$A50) -> 0 | C50: =IF($B$52=0,0,B50/$B$52) -> 0
A51: Shared / site-wide | B51: =SUMIFS('TP Line Items'!$F:$F,'TP Line Items'!$G:$G,$A51) -> 18.29 | C51: =IF($B$52=0,0,B51/$B$52) -> 0.0056855626
A52: TOTAL | B52: =SUM(B43:B51) -> 3216.92 | C52: =SUM(C43:C51) -> 1
A53: Check: TP Account total invoiced less this total (must be 0.00) | B53: =ROUND('TP Account'!$E$22-B52,2) -> 0
A56: E. Pending — not yet invoiced (logged in Cost Lines only)
A57: Item | B57: Scope | C57: Cost centre | D57: Amount £ | E57: Status
A58: Additional curved-decking labour (purpose #4) | B58: Main deck | C58: Contingency | D58: =SUMIFS('Contingency Drawdown'!$H$8:$H$60,'Contingency Drawdown'!$A$8:$A$60,4) -> 0 | E58: Invoiced 9 Oct (INV-0293, £800) and paid — no longer pending. £1,000 was agreed on 24 Sep; the other £200 is not expected unless Luke bills it.
A59: Additional lead work (purpose #31) | B59: Roofline | C59: Contingency | D59: =SUMIFS('Contingency Drawdown'!$H$8:$H$60,'Contingency Drawdown'!$A$8:$A$60,31) -> 200 | E59: Luke's estimate 2 Oct; work completed Fri 16 Oct (lead flashing included); awaiting his invoice.
A60: Whole-house soft wash (purpose #34) | B60: Shared / site-wide | C60: Contingency | D60: =SUMIFS('Contingency Drawdown'!$H$8:$H$60,'Contingency Drawdown'!$A$8:$A$60,34) -> 0 | E60: Paid in cash Mon 19 Oct — no longer pending.
A61: TOTAL pending | D61: =SUM(D58:D60) -> 200 | E61: Luke's remaining extended-deck labour (about 2.1–3.1 days still to come, roughly £1,450–£2,150 on my arithmetic after the £1,000 on INV-0294) is NOT logged until agreed.

Sheet Invoicing Schedule
A1: Invoicing Schedule — expected invoice events
A2: Terms: 10% labour discount on all Luke phases except decking labour and scaffolding. Chimney & coping settle as SINGLE CASH PAYMENTS on phase completion (agreed Lara/Ryan 20 Jul; TBC with Luke 21 Jul). Log every payment on the Invoice Register — this sheet is expectations, the Register is the record.
A4: # | B4: Cost centre | C4: Trigger event | D4: Payee | E4: Basis | F4: Est. £ | G4: Status | H4: Notes
A5: 1 | B5: Decking materials (V4) | C5: Order placed — PAID IN FULL 9 Jul | D5: V4 Wood Flooring Ltd | E5: Invoice V4FQ-15584 | F5: 32228.99 | G5: Paid
A6: 2 | B6: Chimney + Coping (scaffold) | C6: Erection complete (17–18 Jul) — PAID | D6: Scaffolder (via Trevor) | E6: £2,000 cash (of £3,200 combined) | F6: 2000 | G6: Paid | H6: Logged in Register: £937.50 chimney + £1,062.50 coping
A7: 3 | B7: Chimney + Coping (scaffold) | C7: Strike, after Gate 1 sign-off | D7: Scaffolder (via Trevor) | E7: £1,200 cash balance on strike | F7: 1200 | G7: Agreed | H7: Log in Register: £562.50 chimney + £637.50 coping
A8: 4 | B8: Chimney repair | C8: INVOICED & PAID 24 Jul (non-cash) | D8: LG Building and Roofing Ltd | E8: £3,200 labour less £111.70 prepaid = £3,088.30. Full price — no discount. | F8: 3200 | G8: Paid | H8: £3,200 labour invoiced & paid 24 Jul (£3,088.30 after £111.70 prepayment deduction). Rubbish removal (£80) transferred 10 Aug to pooled skip fund — no longer owed to Luke.
A9: 5 | B9: Coping stones repair | C9: 50% CASH — PAID 7 Aug | D9: LG Building and Roofing Ltd | E9: 50% of base labour (£1,710.00), 10% cash discount. Based on original £3,800 quote only. | F9: 1710 | G9: Paid | H9: Excludes condensation-prep addition — price not yet finalised (see separate row).
A10: 6 | B10: Coping stones repair | C10: 50% INVOICED — due next week | D10: LG Building and Roofing Ltd | E10: 50% of base labour (£1,900.00) full price. Rubbish removal transferred to pooled skip fund 10 Aug. | F10: 1900 | G10: Paid 14 Aug | H10: INVOICED 13 Aug as part of Luke's INV-0288 (£2,150 total, due 14 Aug) — that invoice also includes the £250 condensation-prep item, now tracked separately under Contingency. No longer includes rubbish removal — see Rubbish removal (pooled skips) row.
A11: 7 | B11: Contingency | C11: Additional scope — condensation-escape prep (price TBC) | D11: LG Building and Roofing Ltd | E11: Combined labour + materials, Luke's estimate — price NOT yet finalised | F11: 0 | G11: Paid 14 Aug | H11: RECLASSIFIED: priced at £250, invoiced as part of Luke's INV-0288 (£2,150 total, 13 Aug), paid 14 Aug via bank transfer. Tracked as Contingency named purpose #6 — Est.£ shown as £0 here since it's a draw FROM the £5,000 pot (row 14), not additional money on top of it.
A12: 8 | B12: Decking labour | C12: Stage 1 (25%, INV-0289) PAID 20 Aug — 4 stages confirmed, flat 25% each | D12: LG Building and Roofing Ltd | E12: £17,600 labour total across stages, at quoted rates. CORRECTED 4 Sep: cash payments DO get the 10% discount (same as chimney/coping) — only invoiced stages are full price. Rubbish removal transferred to pooled skip fund. | F12: 17600 | G12: Stage 1 paid, 25% down | H12: Stage 1 (£4,400) invoiced/paid 20 Aug, full price. Two cash instalments since (£2,000 each, 4 Sep + 18 Sep), 10% discount applies to both. £8,400 paid to date, £8,844.44 quoted value retired, £8,755.56 remaining. Exact milestone triggers for further stages still TBC.
A13: 9 | B13: Materials (pooled) | C13: Periodic — on receipts | D13: Merchant trade accounts (Dry Lining Supplies, TP etc.) | E13: Pooled £1,130 budget (chimney £480 + coping £650) | F13: 1130 | G13: Agreed in principle | H13: Log each receipt in Register + Materials Receipts sheet
A14: 10 | B14: Contingency | C14: Rainy-day tasks 100% on completion; named extras as incurred | D14: LG Building / merchants | E14: £5,000 pot — fence labour, soakaway fix, garage drainage, curved-deck extras, cement & bricks. Labour at 10% discount | F14: 5000 | G14: Approved 20 Jul — first draw 14 Aug | H14: Curved-decking extra labour discount TBC. First draw: coping condensation-prep (£250, named purpose #6), paid 14 Aug via bank transfer, INV-0288. The £5,000 pot has since been exceeded — see the Contingency Drawdown sheet. Each drawdown also on Contingency Drawdown sheet.
A15: 11 | B15: Contingency | C15: Additional material — stainless steel cowl | D15: StoveWorldUK (paid direct, project account) | E15: Order #147399, 10 Aug 2026 | F15: 0 | G15: Paid | H15: 5" stainless steel chimney pot hanger cowl — replaces original spec (decision logged 7 Aug), prevents rusting. Contingency named purpose #7 — Est.£ shown as £0 here since it's a draw FROM the £5,000 pot (row 14), not additional money on top of it. Actually paid: £62.90 (see Invoice Register).
A16: 11 | B16: Rubbish removal (pooled skips) | C16: Periodic — as skips are needed | D16: Skip Hire Comparison Ltd / future providers | E16: Provisional £1,360 (transferred from chimney/coping/decking rubbish quotes) | F16: 1360 | G16: Approved 10 Aug | H16: First skip £344.16 paid 10 Aug, delivery 11 Aug. More skips expected during decking — budget is provisional, watch like the materials pool. Log each skip in Register + Skip Hire Log sheet.
A17: 9 | B17: Roofline works | C17: New scope, own budget — estimate 4 Sep; started 29 Sep; complete Fri 16 Oct | D17: LG Building and Roofing Ltd | E17: £1,600 labour (no VAT) + £150 scaffold tower + £350 materials = £2,100 (the £2,140 quote less £40 rubbish removal, reclassified to the pooled Rubbish removal fund and not yet incurred). Tower not needed (Luke used his ladder) — the £150 benefit offsets £40.40 of additional materials. | F17: 2100 | G17: Complete — finished Fri 16 Oct (incl. lead flashing) | H17: Supersedes the earlier 'gutters included in Luke's price' understanding (old Gantt tasks 1.5 and 3.2, merged into task 1.5 on 4 Oct). The estimate has no front-of-house gutters; front tile repairs are covered by 'replace various broken slates'.
... A32: 26 | B32: Contingency | C32: Named purpose #38 — V4 materials to complete the decking substructure (QUO-0040) | D32: V4 Wood Flooring Ltd | E32: QUO-0040, delivered 19 Oct | F32: 0 | G32: Paid | H32: £1,268 actual — a draw FROM the £5,000 pot (row 14), not additional money on top of it. Paid by card 22 Oct.
E33: Schedule Total: | F33: =SUM(F5:F32) -> 69428.99
E34: Summary tab committed total: | F34: =Summary!$C$15 -> 69428.99
E35: Difference (must be £0.00): | F35: =F33-F34 -> 0

Sheet Invoice Register
A1: Invoice & Payment Register — add a row per invoice received
A2: Yellow cells are inputs. Cost centre must match the Summary sheet names exactly (dropdown-free by design — copy from row 5). Paid date empty = outstanding.
A4: Invoice date | B4: Cost centre | C4: Supplier | D4: Reference | E4: Description | F4: Amount £ (gross) | G4: Paid date | H4: Method | I4: Notes | J4: Scope | K4: Scope basis | L4: Named purpose #
A5: 46212 | B5: Decking materials (V4) | C5: V4 Wood Flooring Ltd | D5: V4FQ-15584 | E5: Millboard Ashwood decking + Plas-Pro subframe, fixings (144.9 m²) | F5: 32228.99 | G5: 46212 | H5: Amex | I5: Paid in full at order | J5: Main deck | K5: Quote: original V4 order.
A6: 46223 | B6: Materials (pooled) | C6: Dry Lining Supplies Ltd | D6: RECB000NNIVB49XWEXOG | E6: Render materials (shared chimney+coping): mesh, Weberend Aid ×6, beads, SBR, rubble sacks | F6: 311.98 | G6: 46223 | H6: Pay By Link | I6: Project-materials share of £423.69 receipt | J6: Chimney & coping | K6: Cost centre (chimney/coping pools).
A7: 46223 | B7: Chimney repair | C7: Dry Lining Supplies Ltd | D7: RECB000NNIVB49XWEXOG | E7: Folding work platform 600mm — Luke's equipment, non-project | F7: 111.71 | G7: 46223 | H7: Pay By Link | I7: PREPAYMENT vs chimney phase-start invoice: pay £1,528.29 of the £1,640 when it lands | J7: Chimney & coping | K7: Cost centre (chimney/coping pools).
A8: 46223 | B8: Chimney repair | C8: Scaffolder (via Trevor) | D8: Cash | E8: Scaffold erection payment — chimney share (pro-rata of £2,000 cash) | F8: 937.5 | G8: 46223 | H8: Cash | I8: £2,000 paid following erection 17–18 Jul; amend date cell if payment day differed | J8: Chimney & coping | K8: Cost centre (chimney/coping pools).
A9: 46227 | B9: Chimney repair | C9: LG Building and Roofing Ltd | D9: INV-0286 | E9: Chimney labour, invoiced (£3,200 less £111.70 work-platform prepayment). Rubbish removal £80 NOT included — outstanding. | F9: 3088.3 | G9: 46227 | H9: Bank transfer | I9: Invoiced (non-cash) — full price, no 10% discount. £80 rubbish removal still outstanding. | J9: Chimney & coping | K9: Cost centre (chimney/coping pools).
A10: 46225 | B10: Materials (pooled) | C10: Dry Lining Supplies | D10: 914751798 | E10: Weber Pral M Silver Pearl x10, Plastic 15mm Stop Bead 3m x3 (shared render finish) | F10: 162.96 | G10: 46225 | H10: Pay By Link | I10: Second pooled-materials trip | J10: Chimney & coping | K10: Cost centre (chimney/coping pools).
A11: 46238 | B11: Materials (pooled) | C11: Dry Lining Supplies Ltd | D11: RECB000NNIVB6DIPDFCW | E11: Weberend Ocr x3, Weber Pral M Silver Pearl x4, Stop Bead x6, Drip Bead x2, Sikabond SBR x1 (coping render) | F11: 148.53 | G11: 46238 | H11: Pay By Link | I11: Coping stones render materials. Receipt received 4 Aug (till David, 07:31). | J11: Chimney & coping | K11: Cost centre (chimney/coping pools).
A12: 46241 | B12: Coping stones repair | C12: LG Building and Roofing Ltd | D12: Cash | E12: Coping 50% cash labour payment (base labour only, 10% discount). Condensation-prep addition NOT included — price not yet finalised. | F12: 1710 | G12: 46241 | H12: Cash | I12: Confirmed 7 Aug: 50% cash / 50% invoice split on original £3,800 quote. Remainder £1,980.00 (incl. rubbish) to be invoiced next week. £250 addition separate, price TBC. | J12: Chimney & coping | K12: Cost centre (chimney/coping pools).
A13: 46244 | B13: Contingency | C13: StoveWorldUK | D13: Order #147399 | E13: 5" Stainless Steel Chimney Pot Hanger Cowl — replaces original spec | F13: 62.9 | G13: 46244 | H13: Card (Ryan, project account) | I13: Named purpose #7 (chimney cowl upgrade). RECLASSIFIED 17 Aug from Chimney repair — genuine scope addition beyond original quote. | J13: Chimney & coping | K13: Item: chimney cowl (purpose #7). | L13: 7
A14: 46244 | B14: Rubbish removal (pooled skips) | C14: Skip Hire Comparison Ltd | D14: D81F29CE-0002 | E14: 8 cubic yard skip, delivery 11 Aug | F14: 344.16 | G14: 46244 | H14: Card (Ryan, project account) | I14: First skip. Replaces chimney/coping/decking rubbish-removal quotes — transferred to this pooled fund 10 Aug. CANCELLED 11 Aug — original supplier delayed delivery; refunded in full (receipt 3362-9782), see row below. | J14: Shared / site-wide | K14: Pooled skip hire serves all work.
A15: 46245 | B15: Rubbish removal (pooled skips) | C15: Skip Hire Comparison Ltd | D15: Refund 3362-9782 (orig. inv. D81F29CE-0002) | E15: Refund — original skip cancelled after supplier delivery delay | F15: -344.16 | G15: 46247 | H15: — | I15: Refund confirmed received 13 Aug 2026 — cleared in 2 working days, faster than the 5-10 day estimate. | J15: Shared / site-wide | K15: Pooled skip hire serves all work.
A16: 46245 | B16: Rubbish removal (pooled skips) | C16: Elmbridge Mini Skips | D16: INV-11373 / ref 25996 | E16: 8 cubic yard skip — delivery, replaces cancelled Skip Hire Comparison booking | F16: 390 | G16: 46246 | H16: TBC | I16: Settled 12 Aug 2026. Skip delivered filled 11 Aug; collected and swapped for empty 12 Aug. | J16: Shared / site-wide | K16: Pooled skip hire serves all work.
A17: 46246 | B17: Rubbish removal (pooled skips) | C17: Elmbridge Mini Skips | D17: INV-11375 / ref 26030 | E17: 8 cubic yard skip — exchange (collects filled skip, delivers empty) | F17: 390 | G17: 46246 | H17: TBC | I17: Settled 12 Aug 2026. | J17: Shared / site-wide | K17: Pooled skip hire serves all work.
A18: 46247 | B18: Coping stones repair | C18: LG Building and Roofing Ltd | D18: INV-0288 | E18: 50% invoiced balance — coping base labour | F18: 1900 | G18: 46248 | H18: Bank transfer | I18: Paid as part of INV-0288 (£2,150 total, also includes the £250 condensation-prep item — see Contingency row below). | J18: Chimney & coping | K18: Cost centre (chimney/coping pools).
A19: 46247 | B19: Contingency | C19: LG Building and Roofing Ltd | D19: INV-0288 | E19: Named purpose #6 — coping condensation-escape prep (re-bed 3 bricks, fibreglass mesh, 4 weep holes) | F19: 250 | G19: 46248 | H19: Bank transfer | I19: Reclassified from Coping 13 Aug. Terms were originally agreed as 100% cash — confirmed 14 Aug this is instead paid via bank transfer as part of INV-0288, bundled with the £1,900 coping balance. | J19: Chimney & coping | K19: Item: coping condensation-prep (purpose #6). | L19: 6
A20: 46250 | B20: Materials (pooled) | C20: SoftWash UK | D20: Order F4UJ62VLQ | E20: Render Cleaner Gel X Pro, 5 Litres | F20: 47.99 | G20: 46250 | H20: Card (Mastercard ...4597) | I20: Paid at checkout, order confirmed 16 Aug. Also logged on Materials Receipts sheet — pool detail. | J20: Chimney & coping | K20: Cost centre (chimney/coping pools).
A21: 46251 | B21: Materials (pooled) | C21: LG Building and Roofing Ltd (Travis Perkins account) | D21: TP invoices 1047678330 / 1047972816 / 1048887075 | E21: Render/masonry consumables + lead flashing — pooled, not split by workstream | F21: 481.28 | G21: 46252 | H21: Bank transfer | I21: PAID 18 Aug, confirmed as part of the full £547.88 TP account settlement (all 4 invoices). £0.02 rounding absorbed here so the three allocations reconcile exactly to the confirmed total. | J21: Chimney & coping | K21: Cost centre (chimney/coping pools).
A22: 46253 | B22: Materials (pooled) | C22: Dry Lining Supplies Ltd | D22: Refund against 4 Aug order | E22: Refund — 5 bags unused monocouche + other returned items, against original £148.53 order | F22: -72.23 | G22: 46253 | H22: Bank transfer | I22: Refund confirmed received 19 Aug — £72.23, slightly more than the £63.10 estimate (5 bags x £12.62), likely covered a few additional returned items beyond the monocouche. Actual figure used, not the estimate. | J22: Chimney & coping | K22: Cost centre (chimney/coping pools).
A23: 46251 | B23: Contingency | C23: LG Building and Roofing Ltd (Travis Perkins account) | D23: TP invoice 1048887075 | E23: Damplas DPC roll — coping condensation-prep material (named purpose #6) | F23: 26.42 | G23: 46252 | H23: Bank transfer | I23: PAID 18 Aug, part of the full £547.88 TP account settlement. Adds to the existing purpose #6 draw (£250 labour) — total now £276.42. | J23: Chimney & coping | K23: Item: coping DPC roll (purpose #6). | L23: 6
A24: 46244 | B24: Materials (pooled) | C24: LG Building and Roofing Ltd (Travis Perkins account) | D24: TP invoice 1049120278 | E24: Cleaning/finishing consumables — pooled, not split by workstream | F24: 40.18 | G24: 46252 | H24: Bank transfer | I24: PAID 18 Aug, part of the full £547.88 TP account settlement. | J24: Chimney & coping | K24: Cost centre (chimney/coping pools).
A25: 46252 | B25: Decking labour | C25: LG Building and Roofing Ltd | D25: INV-0289 | E25: Decking labour — stage 1 (25% of £17,600 quoted labour) | F25: 4400 | G25: 46254 | H25: Bank transfer | I25: First stage payment — resolves the earlier open question about 4-5 stage triggers: appears to be a flat 25% per stage. 3 stages remaining (£13,200). | J25: Main deck | K25: Cost centre: decking labour.
A26: 46223 | B26: Coping stones repair | C26: Scaffolder (via Trevor) | D26: Cash | E26: Scaffold erection payment — coping share (pro-rata of £2,000 cash). CAUGHT 18 Aug: paid at the time, only now logged in the Register. | F26: 1062.5 | G26: 46223 | H26: Cash | I26: Matches chimney's already-logged share (row 8) — total £2,000 split £1,500/£1,700 chimney/coping ratio. | J26: Chimney & coping | K26: Cost centre (chimney/coping pools).
A27: 46252 | B27: Chimney repair | C27: Scaffolder (via Trevor) | D27: — | E27: Scaffold final balance — chimney share (pro-rata of £1,200) | F27: 562.5 | G27: 46252 | H27: TBC | I27: Scaffold strike complete 18 Aug, final balance paid. Full £3,200 now settled: £1,500 chimney + £1,700 coping. | J27: Chimney & coping | K27: Cost centre (chimney/coping pools).
A28: 46252 | B28: Coping stones repair | C28: Scaffolder (via Trevor) | D28: — | E28: Scaffold final balance — coping share (pro-rata of £1,200) | F28: 637.5 | G28: 46252 | H28: TBC | I28: Scaffold strike complete 18 Aug, final balance paid. | J28: Chimney & coping | K28: Cost centre (chimney/coping pools).
A29: 46258 | B29: Contingency | C29: V4 Wood Flooring Ltd | D29: V4FQ-17702 | E29: V4 screw top-up — 15 boxes structural subframe screws (named purpose #8) | F29: 141.66 | G29: 46258 | H29: Bank transfer | I29: Requested by Luke 20 Aug, ordered and paid 24 Aug. | J29: Main deck | K29: Item: structural subframe screws (V4 top-up #1). | L29: 8
A30: 46269 | B30: Decking labour | C30: LG Building and Roofing Ltd | D30: Cash | E30: Decking labour — cash instalment (10% discount applies) | F30: 2000 | G30: 46269 | H30: Cash | I30: Retires £2,222.22 of quoted value at the 10% cash discount (£2,000 paid = 90%). Not a full 25% stage — partial/interim payment. Total paid to date: £6,400 (Stage 1 £4,400 invoiced + this £2,000 cash). Quoted value remaining: £10,977.78. | J30: Main deck | K30: Cost centre: decking labour.
A31: 46275 | B31: Contingency | C31: V4 Wood Flooring Ltd | D31: TBC (no invoice number given) | E31: V4 screw top-up #2 — 15 boxes structural subframe screws (named purpose #9) | F31: 141.66 | G31: 46275 | H31: TBC | I31: Invoice received and paid 10 Sep, delivery scheduled 11 Sep. Amount inferred from purpose #8's confirmed rate — no invoice number/exact figure given; flag if actual differs. | J31: Main deck | K31: Item: structural subframe screws (V4 top-up #2). | L31: 9
A32: 46276 | B32: Rubbish removal (pooled skips) | C32: TBC | D32: N/A (cash) | E32: Old decking substructure wood collection — corrected to £680 (was £350 est.), charged per trip, 2 trips | F32: 680 | G32: 46276 | H32: Cash | I32: Same job as the earlier £350 estimate — supplier charges per trip, not a flat rate. Not a separate/additional charge. | J32: Main deck | K32: Item: old decking substructure wood collection.
A33: 46276 | B33: Contingency | C33: LG Building and Roofing Ltd | D33: Cash | E33: Extra digging — wider gate area + shed/additional deck (named purpose #11) | F33: 1260 | G33: 46276 | H33: Cash | I33: Quoted £1,400, 10% cash discount applied. Part of Luke's 11 Sep extras, £2,115 total across 4 items. | J33: Extended deck & shed base | K33: Item: extra digging for the wider gate area + shed/additional deck (mixed, both extended scope). | L33: 11
A34: 46276 | B34: Contingency | C34: LG Building and Roofing Ltd | D34: Cash | E34: Cleanup after machines + dig up small tree (named purpose #12) | F34: 180 | G34: 46276 | H34: Cash | I34: Quoted £200, 10% cash discount applied. | J34: Groundworks (digger & dumper) | K34: Item: clean-up after the machines + small tree dig. | L34: 12
A35: 46276 | B35: Contingency | C35: LG Building and Roofing Ltd | D35: Cash | E35: Fence move, chimney side/side a boundary reclaim (named purpose #13) | F35: 315 | G35: 46276 | H35: Cash | I35: Quoted £700 for move+spurs, but spurs (3.3, side b) didn't happen — only £350 charged, 10% cash discount applied. | J35: Fence relocation | K35: Item: fence move, chimney side / side (a) boundary reclaim. | L35: 13
A36: 46276 | B36: Contingency | C36: LG Building and Roofing Ltd | D36: Cash | E36: Extra frame, wider deck gate area (named purpose #14) | F36: 360 | G36: 46276 | H36: Cash | I36: Quoted £400, 10% cash discount applied. | J36: Extended deck & shed base | K36: Item: extra frame for the wider deck gate area. | L36: 14
A37: 46283 | B37: Decking labour | C37: LG Building and Roofing Ltd | D37: Cash | E37: Decking labour — second cash instalment (10% discount applies) | F37: 2000 | G37: 46283 | H37: Cash | I37: Retires £2,222.22 of quoted value at the 10% cash discount. Total paid to date: £8,400 (Stage 1 £4,400 invoiced + £2,000 cash 4 Sep + £2,000 cash 18 Sep). Quoted value retired: £8,844.44. Remaining: £8,755.56. | J37: Main deck | K37: Cost centre: decking labour.
A38: 46252 | B38: Contingency | C38: Travis Perkins (Luke's account) | D38: 1049651867 | E38: TP materials — cement, blade (named purpose #16) | F38: 144.58 | G38: 46300 | H38: Card (TP settlement, 5 Oct) | I38: On Luke's TP trade account (NH4276). PAID 5 Oct 2026 by card — part of the £2,313.89 TP settlement (see TP Account). | J38: Main deck | K38: Date rule: invoiced before 21 Sep → main deck. Luke (2 Oct): only 1 day (2 people) spent on the extended deck so far — half last week, half this week. INFERRED — confirm with Luke. | L38: 16
A39: 46253 | B39: Contingency | C39: Travis Perkins (Luke's account) | D39: 1049757851 | E39: TP materials — plywood, drill bit, screws, gloves (named purpose #17) | F39: 74.34 | G39: 46300 | H39: Card (TP settlement, 5 Oct) | I39: On Luke's TP trade account (NH4276). PAID 5 Oct 2026 by card — part of the £2,313.89 TP settlement (see TP Account). | J39: Main deck | K39: Date rule: invoiced before 21 Sep → main deck. Luke (2 Oct): only 1 day (2 people) spent on the extended deck so far — half last week, half this week. INFERRED — confirm with Luke. | L39: 17
A40: 46254 | B40: Contingency | C40: Travis Perkins (Luke's account) | D40: 1049844268 | E40: TP materials — ballast x2, cement, blocks, pallet deposit (named purpose #18) | F40: 462.5 | G40: 46300 | H40: Card (TP settlement, 5 Oct) | I40: On Luke's TP trade account (NH4276). Includes £30.30 REFUNDABLE pallet deposit — not a final cost. PAID 5 Oct 2026 by card — part of the £2,313.89 TP settlement (see TP Account). | J40: Main deck | K40: Date rule: invoiced before 21 Sep → main deck. Luke (2 Oct): only 1 day (2 people) spent on the extended deck so far — half last week, half this week. INFERRED — confirm with Luke. | L40: 18
A41: 46254 | B41: Contingency | C41: Travis Perkins (Luke's account) | D41: 1049844267 | E41: TP materials — Broadfix flat packers (named purpose #19) | F41: 22.66 | G41: 46300 | H41: Card (TP settlement, 5 Oct) | I41: On Luke's TP trade account (NH4276). PAID 5 Oct 2026 by card — part of the £2,313.89 TP settlement (see TP Account). | J41: Main deck | K41: Date rule: invoiced before 21 Sep → main deck. Luke (2 Oct): only 1 day (2 people) spent on the extended deck so far — half last week, half this week. INFERRED — confirm with Luke. | L41: 19
A42: 46273 | B42: Contingency | C42: Travis Perkins (Luke's account) | D42: 1050903283 | E42: TP materials — plywood, line marker (named purpose #20) | F42: 58.62 | G42: 46300 | H42: Card (TP settlement, 5 Oct) | I42: On Luke's TP trade account (NH4276). PAID 5 Oct 2026 by card — part of the £2,313.89 TP settlement (see TP Account). | J42: Main deck | K42: Date rule: invoiced before 21 Sep → main deck. Luke (2 Oct): only 1 day (2 people) spent on the extended deck so far — half last week, half this week. INFERRED — confirm with Luke. | L42: 20
A43: 46274 | B43: Contingency | C43: Travis Perkins Hire (Luke's account) | D43: 1051011143 | E43: Digger hire — excavator, waiver, diesel, transport (named purpose #10, corrects £530 est.) | F43: 378.58 | G43: 46300 | H43: Card (TP settlement, 5 Oct) | I43: On Luke's TP trade account (NH4276). No barrow loader charge on this invoice — flagged, not confirmed either way. PAID 5 Oct 2026 by card — part of the £2,313.89 TP settlement (see TP Account). | J43: Groundworks (digger & dumper) | K43: Hire used for both the main deck widening and the new shed area (Luke, 8 Sep) — mixed, not split. | L43: 10
A44: 46275 | B44: Contingency | C44: Travis Perkins (Luke's account) | D44: 1051072869 | E44: TP materials — ballast, cement (named purpose #21) | F44: 124.73 | G44: 46300 | H44: Card (TP settlement, 5 Oct) | I44: On Luke's TP trade account (NH4276). PAID 5 Oct 2026 by card — part of the £2,313.89 TP settlement (see TP Account). | J44: Main deck | K44: Date rule: invoiced before 21 Sep → main deck. Luke (2 Oct): only 1 day (2 people) spent on the extended deck so far — half last week, half this week. INFERRED — confirm with Luke. | L44: 21
A45: 46276 | B45: Contingency | C45: Travis Perkins (Luke's account) | D45: 1051162218 | E45: TP materials — gloves, woodscrews (named purpose #22) | F45: 18.29 | G45: 46300 | H45: Card (TP settlement, 5 Oct) | I45: On Luke's TP trade account (NH4276). PAID 5 Oct 2026 by card — part of the £2,313.89 TP settlement (see TP Account). | J45: Shared / site-wide | K45: Small consumables (gloves + woodscrews) — cannot be split between projects. INFERRED. | L45: 22
A46: 46276 | B46: Contingency | C46: Travis Perkins (Luke's account) | D46: 1051142985 | E46: TP fence materials — posts, postcrete, rail brackets, pegs, treated timber, gloves (named purpose #23) | F46: 291.17 | G46: 46300 | H46: Card (TP settlement, 5 Oct) | I46: On Luke's TP trade account (NH4276). Two-page invoice, both pages verified (£242.64 goods + £48.53 VAT = £291.17). PAID 5 Oct 2026 by card — part of the £2,313.89 TP settlement (see TP Account). | J46: Fence relocation | K46: Item: fence materials (posts, rails, brackets, Postcrete, pegs). | L46: 23
A47: 46294 | B47: Contingency | C47: V4 Wood Flooring Ltd | D47: QUO-0031 (quote number used as invoice ref — no formal invoice/order confirmation received) | E47: V4 materials — expanded shed-area/fence-move decking scope (named purpose #24), actioned + paid by phone 29 Sep | F47: 5322.74 | G47: 46294 | H47: Card (paid over the phone) | I47: Delivery expected 30 Sep or 1 Oct. Routed to Contingency per Ryan's steer 29 Sep — covers expanded scope beyond the original V4 order, not the base decking quote. | J47: Extended deck & shed base | K47: Quote: V4 order for the expanded shed-area / fence-move decking scope. | L47: 24
A48: 46294 | B48: Roofline works | C48: Graham (The Plumbers' Merchant), via Luke's cash trade account | D48: SI19670857 | E48: Guttering/fascia materials — rear-of-house gutters (FloPlast Hi-Cap black system): gutter pipe, fascia brackets, running outlet, external stopend, downpipe | F48: 256.78 | G48: 46294 | H48: Cash (via Luke) — £260 handed over, £3.22 of which was Luke's own coin top-up to round the figure | I48: Replaces the £350 generic materials placeholder in Cost Lines for Roofline works. Further materials invoices may follow as the job extends to other elevations. | J48: Roofline | K48: Cost centre: Roofline works.
A49: 46295 | B49: Roofline works | C49: Graham (The Plumbers' Merchant), via Luke's cash trade account | D49: SI19687572 | E49: Union bracket (RUH1BL) — additional guttering fitting | F49: 9.74 | G49: 46297 | H49: Cash (via Luke) — £90 combined with TFP 0001458493, paid 2 Oct | I49: Part of a combined £90 cash payment (with TFP 0001458493): £87.75 of invoices + £2.25 Luke's coin top-up. Reimbursed to Luke in cash 2 Oct. | J49: Roofline | K49: Cost centre: Roofline works.
A50: 46295 | B50: Roofline works | C50: The Fascia Place (TFP), Guildford | D50: 0001458493 | E50: Fascia board, soffit board, fascia joints, soffit trim (white) | F50: 78.01 | G50: 46297 | H50: Cash (via Luke) — £90 combined with Graham SI19687572, paid 2 Oct | I50: Part of a combined £90 cash payment (with Graham SI19687572): £87.75 of invoices + £2.25 Luke's coin top-up. Reimbursed to Luke in cash 2 Oct. Invoice marked 'Payment has been received with thanks'. | J50: Roofline | K50: Cost centre: Roofline works.
A51: 46296 | B51: Roofline works | C51: The Fascia Place (TFP), Guildford | D51: 0001458792 | E51: Soffit board — 250mm x 9mm pre-vented, white (SM250WV) | F51: 40.4 | G51: 46297 | H51: Cash (via Luke) — £40.40, paid 2 Oct | I51: Invoice marked 'payment has been received' (Luke paid at the TP counter). Reimbursed to Luke in cash 2 Oct. | J51: Roofline | K51: Cost centre: Roofline works.
A52: 46245 | B52: Contingency | C52: Travis Perkins (Luke's account) | D52: 1049231418 | E52: Sand, white Snowcrete cement, Bosch blade (named purpose #25) | F52: 108.14 | G52: 46276 | H52: Bank transfer (part of £500 TP receipt) | I52: On Luke's TP trade account (NH4276), Net Monthly terms. Cleared by the £500 receipt of 11 Sep (taken from bank 12 Sep) per TP transaction history CSV. | J52: Main deck | K52: Date rule: invoiced before 21 Sep → main deck. Luke (2 Oct): only 1 day (2 people) spent on the extended deck so far — half last week, half this week. INFERRED — confirm with Luke. NB white Snowcrete cement + sand may relate to the coping work (13 Aug). | L52: 25
A53: 46251 | B53: Contingency | C53: Travis Perkins (Luke's account) | D53: 1049595624 (part paid) | E53: Ballast, building sand, 72 blocks (named purpose #26) — paid portion | F53: 247.01 | G53: 46276 | H53: Bank transfer (part of £500 TP receipt) | I53: On Luke's TP trade account (NH4276), Net Monthly terms. Part 1 of 2: £247.01 is the remainder of the £500 receipt after the five invoices listed in TP's CSV (inferred by elimination). | J53: Main deck | K53: Date rule: invoiced before 21 Sep → main deck. Luke (2 Oct): only 1 day (2 people) spent on the extended deck so far — half last week, half this week. INFERRED — confirm with Luke. | L53: 26
A54: 46251 | B54: Contingency | C54: Travis Perkins (Luke's account) | D54: 1049595624 (balance) | E54: Ballast, building sand, 72 blocks (named purpose #26) — balance | F54: 100.11 | G54: 46300 | H54: Card (TP settlement, 5 Oct) | I54: On Luke's TP trade account (NH4276), Net Monthly terms. Part 2 of 2: the £100.11 balance, confirmed outstanding by Luke, paid by card 5 Oct as part of the £2,313.89 TP settlement. Part 1 (£247.01) was paid 11 Sep. | J54: Main deck | K54: Date rule: invoiced before 21 Sep → main deck. Luke (2 Oct): only 1 day (2 people) spent on the extended deck so far — half last week, half this week. INFERRED — confirm with Luke. | L54: 26
A55: 46268 | B55: Contingency | C55: Travis Perkins (Luke's account) | D55: 1050655200 | E55: Ballast x2, Mastercrete cement x10 (named purpose #27) | F55: 249.46 | G55: 46300 | H55: Card (TP settlement, 5 Oct) | I55: On Luke's TP trade account (NH4276). PAID 5 Oct 2026 by card — part of the £2,313.89 TP settlement (see TP Account). | J55: Main deck | K55: Date rule: invoiced before 21 Sep → main deck. Luke (2 Oct): only 1 day (2 people) spent on the extended deck so far — half last week, half this week. INFERRED — confirm with Luke. | L55: 27
A56: 46279 | B56: Contingency | C56: Travis Perkins Hire (Luke's account) | D56: 1051287675 | E56: Tracked dumper hire 2–8 Sep (named purpose #28) | F56: 277.79 | G56: 46300 | H56: Card (TP settlement, 5 Oct) | I56: On Luke's TP trade account (NH4276). PAID 5 Oct 2026 by card — part of the £2,313.89 TP settlement (see TP Account). | J56: Groundworks (digger & dumper) | K56: Hire used for both the main deck widening and the new shed area (Luke, 8 Sep) — mixed, not split. | L56: 28
A57: 46286 | B57: Contingency | C57: Travis Perkins (Luke's account) | D57: 1051688095 | E57: Blocks x6, cement x4, rubber mallet, line marker (named purpose #29) | F57: 60.3 | G57: 46300 | H57: Card (TP settlement, 5 Oct) | I57: On Luke's TP trade account (NH4276). PAID 5 Oct 2026 by card — part of the £2,313.89 TP settlement (see TP Account). | J57: Extended deck & shed base | K57: Concrete/blocks dated 21 Sep — fits the first extended-deck work (Luke, 2 Oct: 1 day x2 people so far, half last week, half this week). INFERRED — confirm with Luke. | L57: 29
A58: 46286 | B58: Contingency | C58: Travis Perkins (Luke's account) | D58: 1051708772 | E58: Blocks x20 (named purpose #30) | F58: 50.76 | G58: 46300 | H58: Card (TP settlement, 5 Oct) | I58: On Luke's TP trade account (NH4276). PAID 5 Oct 2026 by card — part of the £2,313.89 TP settlement (see TP Account). | J58: Extended deck & shed base | K58: Concrete/blocks dated 21 Sep — fits the first extended-deck work (Luke, 2 Oct: 1 day x2 people so far, half last week, half this week). INFERRED — confirm with Luke. | L58: 30
A59: 46297 | B59: Roofline works | C59: LG Building and Roofing Ltd | D59: INV-0291 | E59: Roofline works labour — gutter replacement, fascia/soffit extension, slate replacement, barge board trim (per 4 Sep estimate; labour only, no VAT) | F59: 1600 | G59: 46298 | H59: Bank transfer | I59: Issued 2 Oct, due 2 Oct. Confirmed correct by Ryan 3 Oct and paid by bank transfer 3 Oct — full price, so no cash discount applies. Matches the labour line of the 4 Sep estimate exactly. | J59: Roofline | K59: Cost centre: Roofline works.
A60: 46304 | B60: Contingency | C60: LG Building and Roofing Ltd | D60: INV-0293 (curves) | E60: Extra decking labour — curves (named purpose #4); part of LG INV-0293 (curve and additional decking) | F60: 800 | G60: 46304 | H60: Bank transfer | I60: LG invoice INV-0293, £1,850 in total (no VAT), issued and due 9 Oct 2026 for the extra work carried out (curve and additional decking); paid in full 9 Oct by bank transfer. Full price, no cash discount. Separate from the £17,600 decking labour draws. | J60: Main deck | K60: Curves = named purpose #4 (Main deck scope). Ryan split INV-0293 into £800 curves + £1,050 additional deck on 9 Oct. | L60: 4
A61: 46304 | B61: Contingency | C61: LG Building and Roofing Ltd | D61: INV-0293 (additional deck) | E61: Extra decking labour — additional deck, extended deck & shed base (named purpose #32); part of LG INV-0293 | F61: 1050 | G61: 46304 | H61: Bank transfer | I61: LG invoice INV-0293, £1,850 in total (no VAT), issued and due 9 Oct 2026 for the extra work carried out (curve and additional decking); paid in full 9 Oct by bank transfer. Full price, no cash discount. Separate from the £17,600 decking labour draws. | J61: Extended deck & shed base | K61: Additional deck = extended deck & shed base scope. Ryan split INV-0293 into £800 curves + £1,050 additional deck on 9 Oct. | L61: 32
A62: 46301 | B62: Contingency | C62: Toolstation Ltd (bought by Luke, on his card) | D62: YAC545477716 | E62: Toolstation — Freud mitre saw blade (£71.99), ROKTOR HSS drill bits (£2.99), DeWalt circular saw blade (£9.99) (named purpose #33) | F62: 84.97 | G62: 46308 | H62: Cash (reimbursed to Luke) | I62: Ordered 6 Oct and paid by Luke by card (£70.80 + £14.17 VAT); Luke repaid in cash by Ryan on 13 Oct. Tools will be used throughout the project. | J62: Main deck | K62: Saw blades and drill bits — scope set as Main deck by Ryan 13 Oct, although they will be used throughout the project. | L62: 33
A63: 46312 | B63: Contingency | C63: LG Building and Roofing Ltd | D63: INV-0294 (driveway channel) | E63: Driveway channel — lift cobbles, dig waste channel for the water-softener discharge, reinstate cobbles; half a day, Luke and Max, 14 Oct (named purpose #35); part of LG INV-0294 | F63: 350 | G63: 46312 | H63: Bank transfer | I63: LG invoice INV-0294, £1,350 in total (no VAT), issued, due and paid 17 Oct 2026 for the extra work as discussed; paid in full by bank transfer. Full price, no cash discount. | J63: Driveway channel | K63: Ryan split INV-0294 on 17 Oct: £350 driveway channel (half day, Luke and Max, Gantt task 3.1) + £1,000 extra decking labour. Drawn from Contingency. | L63: 35
A64: 46312 | B64: Contingency | C64: LG Building and Roofing Ltd | D64: INV-0294 (extra decking) | E64: Extra decking labour — extended deck & shed base (named purpose #36); part of LG INV-0294 | F64: 1000 | G64: 46312 | H64: Bank transfer | I64: LG invoice INV-0294, £1,350 in total (no VAT), issued, due and paid 17 Oct 2026 for the extra work as discussed; paid in full by bank transfer. Full price, no cash discount. | J64: Extended deck & shed base | K64: Ryan split INV-0294 on 17 Oct: £350 driveway channel + £1,000 extra decking labour (extended deck & shed base scope). | L64: 36
A65: 46315 | B65: Contingency | C65: Buy Insulation Online | D65: INV842429677 | E65: Stornch outdoor pipe insulation, 2m x 22mm bore x 19mm thick, 7 pieces at £21.14 (£147.98 + £29.60 VAT; free delivery) — pipe lagging for the outside tap/pipework (named purpose #37) | F65: 177.58 | G65: 46315 | H65: Card (Ryan) | I65: Online order placed and paid by Ryan's card on Tue 20 Oct 2026; order confirmation #INV842429677. Delivery date to follow by email. Drawn from Contingency. | J65: Shared / site-wide | K65: Pipe lagging for the outside tap/pipework (Gantt 2.4, Gate 3). Scope set as site-wide (main deck) by Ryan 20 Oct. | L65: 37
A66: 46317 | B66: Contingency | C66: V4 Wood Flooring Ltd | D66: QUO-0040 | E66: V4 — materials to complete the decking substructure, delivered Mon 19 Oct (quote/invoice QUO-0040) (named purpose #38) | F66: 1268 | G66: 46317 | H66: Card | I66: V4 delivery arrived Mon 19 Oct to complete the decking substructure; QUO-0040 paid by card to V4 on Thu 22 Oct 2026. Drawn from Contingency. | J66: Extended deck & shed base | K66: Scope set as Extended deck & shed base by Ryan 22 Oct; some of the Plas-Pro will likely be used on the main decking. | L66: 38
A67: 46314 | B67: Contingency | C67: Gorgeous Cleaning Services | D67: Cash payment (no invoice number) | E67: Whole-house soft wash — gutters, soffits, roof tiles, roof solar panels, render, windows etc. (named purpose #34) | F67: 1200 | G67: 46314 | H67: Cash | I67: Whole-house soft wash started and finished Mon 19 Oct (very successful); £1,200 paid in cash on the day. Drawn from Contingency. Replaces the earlier chimney + coping-only soft wash (Gantt 1.6). | J67: Shared / site-wide | K67: Whole house, so not split between projects. | L67: 34

Sheet Cost Lines
A1: Cost Lines — every line item from LG estimates and the V4 invoice
A2: Source documents: LG chimney estimate 2 Jun 2026 · LG coping estimate 3 Jun 2026 · LG decking estimate 3 Jun 2026 · V4 invoice V4FQ-15584, 9 Jul 2026. · V4 quote #QUO-0031, actioned 29 Sep (Contingency named purpose #24). · TP invoices #5/#6/#11/#17/#18/#19 and TFP 0001458792 added 3 Oct.
A4: Cost centre | B4: Supplier | C4: Line item | D4: Qty | E4: Unit £ | F4: Line total £ | G4: VAT | H4: Payment route | I4: Notes
A5: Chimney repair | B5: LG Building | C5: Labour — remove render, k-rend sealer, base + top coat, render crown, storm-dry cream | F5: 3200 | G5: No VAT | H5: LG invoice | I5: INVOICED 24 Jul (INV-0286), full price £3,200 less £111.70 prepaid = £3,088.30. Non-cash, so 10% discount does not apply. Rubbish removal £80 outstanding.
A6: Chimney repair | B6: Scaffolder (direct) | C6: Tubular scaffolding — all four sides of chimney and crown | F6: 1500 | G6: Inc VAT | H6: Paid directly | I6: Combined £3,200, cash terms (20 Jul): £2,000 paid following erection; £1,200 balance on strike.
A7: Materials (pooled) | B7: Merchant trade accounts | C7: Materials (chimney estimate — pooled 20 Jul) | F7: 480 | G7: Inc VAT | H7: Trade accounts — cleared on receipts
A8: Chimney repair | B8: LG Building | C8: Rubbish removal | F8: 0 | G8: Inc VAT | H8: LG invoice | I8: TRANSFERRED 10 Aug to pooled Rubbish removal (skips) fund — family now supplies skips directly rather than Luke arranging disposal. No longer owed to Luke.
A9: Coping stones repair | B9: LG Building | C9: Labour — remove/reset copings, slate cap, render, lead flashings to parapet rear | F9: 3610 | G9: No VAT | H9: LG invoice | I9: CONFIRMED 7 Aug, based on original £3,800 quote: 50% cash (£1710.00 @ 10% discount) due same day, 50% invoiced (£1900.00 full price) due next week, timed after back gutters are complete — see Invoicing Schedule. RISK: coping-stone damage on removal could substantially increase cost. Condensation-prep addition (£250) reclassified to Contingency 13 Aug — no longer part of this total.
A10: Coping stones repair | B10: Scaffolder (direct) | C10: Tubular scaffolding with winch system | F10: 1700 | G10: Inc VAT | H10: Paid directly | I10: Combined £3,200, cash terms (20 Jul): £2,000 paid following erection; £1,200 balance on strike.
A11: Materials (pooled) | B11: Merchant trade accounts | C11: Materials (coping estimate — pooled 20 Jul) | F11: 650 | G11: Inc VAT | H11: Trade accounts — cleared on receipts
A12: Coping stones repair | B12: LG Building | C12: Rubbish removal | F12: 0 | G12: Inc VAT | H12: LG invoice | I12: TRANSFERRED 10 Aug to pooled Rubbish removal (skips) fund. Removed from next week's invoice (now £1,900, not £1,980).
A13: Decking labour | B13: LG Building | C13: Labour — remove old decking & frame, construct composite frame, install deck to spec | F13: 17600 | G13: No VAT | H13: LG invoice | I13: RISK: pending structure/ground assessment. Cash payments get the 10% discount (same as chimney/coping) — only invoiced stages are full price. Progress: Stage 1 (£4,400) invoiced 20 Aug + two £2,000 cash instalments (4 Sep, 18 Sep) — £8,400 cash paid to date, £8,844.44 quoted value retired, £8,755.56 quoted value remaining.
A14: Decking labour | B14: LG Building | C14: Rubbish removal (8-yard skips ×2, possibly 3) | F14: 0 | G14: Inc VAT | H14: LG invoice | I14: TRANSFERRED 10 Aug to pooled Rubbish removal (skips) fund.
A15: Decking materials (V4) | B15: V4 Wood Flooring | C15: Millboard Ashwood 176mm Moulded Lastane (144.90 m²) | D15: 230 | E15: 66.49 | F15: 15292.7 | G15: In net | H15: V4 invoice — PAID
A16: Decking materials (V4) | B16: V4 Wood Flooring | C16: Millboard Ashwood Moulded Lastane — MFN360H | D16: 18 | E16: 58.09 | F16: 1045.62 | G16: In net | H16: V4 invoice — PAID
A17: Decking materials (V4) | B17: V4 Wood Flooring | C17: Millboard Ashwood Moulded Lastane — MEBB360H (flexible bullnose) | D17: 15 | E17: 72.25 | F17: 1083.75 | G17: In net | H17: V4 invoice — PAID | I17: For curved upper level
A18: Decking materials (V4) | B18: V4 Wood Flooring | C18: Millboard Step Edge — Ashwood Moulded Lastane | D18: 15 | E18: 59.89 | F18: 898.35 | G18: In net | H18: V4 invoice — PAID
A19: Decking materials (V4) | B19: V4 Wood Flooring | C19: Stainless steel screws 45mm — boxes | D19: 24 | E19: 32.08 | F19: 770 | G19: In net | H19: V4 invoice — PAID
A20: Decking materials (V4) | B20: V4 Wood Flooring | C20: Durafix Trimhead 35mm SS screws — box of 100 (FT35P100) | D20: 6 | E20: 10.25 | F20: 61.5 | G20: In net | H20: V4 invoice — PAID
A21: Decking materials (V4) | B21: V4 Wood Flooring | C21: Plas-Pro bearer/joist black 3.0m 50×125mm composite (P1205B300) | D21: 266 | E21: 28.4 | F21: 7554.4 | G21: In net | H21: V4 invoice — PAID | I21: Subframe — the bulk of the tonnage
A22: Decking materials (V4) | B22: V4 Wood Flooring | C22: Subframe hexhead screws — box of 50 (FH90P050) | D22: 16 | E22: 7.87 | F22: 125.92 | G22: In net | H22: V4 invoice — PAID | I22: Original 16 boxes delivered in full, confirmed 12 Aug. TOP-UP REQUESTED 20 Aug: Luke has asked for 15 more boxes (same item, FH90P050) — substructure screw consumption running ahead of the original estimate. Not yet ordered/invoiced. Estimated cost £141.66 inc VAT (15 x £7.87 + 20% VAT, matching original per-unit price) — treat as V4 Phase 3 once ordered. Not yet added to committed total.
A23: Decking materials (V4) | B23: V4 Wood Flooring | C23: Millboard touch-up paint — Ashwood (AP500H) | D23: 1 | E23: 15 | F23: 15 | G23: In net | H23: V4 invoice — PAID
A24: Decking materials (V4) | B24: V4 Wood Flooring | C24: Millboard multi-spacer — pack of 10 (FP36P010) | D24: 1 | E24: 10.25 | F24: 10.25 | G24: In net | H24: V4 invoice — PAID
A25: Decking materials (V4) | B25: V4 Wood Flooring | C25: VAT on order | F25: 5371.5 | G25: VAT | H25: V4 invoice — PAID | I25: Net £26,857.49 + VAT = £32,228.99
A26: Contingency | B26: TBC | C26: Contingency pot — fence labour, garage drainage, curved-deck labour, cement & bricks, coping condensation-prep (£250, reclassified 13 Aug). Soakaway fix cancelled 1 Sep, nothing drawn. Pipe investigation resolved 4 Sep — no leak, no repair needed, no draw required. | F26: 5000 | G26: — | H26: As incurred | I26: Track on Contingency Drawdown sheet. Labour invoices from this pot at 10% discount (extended 20 Jul); materials (cement/bricks) full price. Curved-decking extra labour: discount status TBC with Luke. Coping condensation-prep (£250) added as named purpose #6, 13 Aug — payment method (cash vs invoice) pending confirmation.
A27: Contingency | B27: LG Building and Roofing Ltd | C27: Named purpose #6 — Coping condensation-escape prep: re-bed 3 bricks; reinforce parapet corners with fibreglass mesh; fit 4 weep holes to front face above internal damp-course membrane (slate DPC capped in plastic DPM). Reclassified from Coping 13 Aug — same item, moved to keep coping's committed total accurate rather than inflate it. | F27: 250 | G27: TBC | H27: Contingency drawdown | I27: PRICED 13 Aug via Luke's invoice INV-0288: £250. Terms originally agreed as 100% cash; confirmed 14 Aug instead paid via bank transfer, bundled with the coping £1,900 balance. PAID 14 Aug.
A28: Contingency | B28: StoveWorldUK | C28: Named purpose #7 — Chimney cowl upgrade: 5" Stainless Steel Chimney Pot Hanger Cowl (order #147399), replaces original spec | D28: 1 | E28: 62.9 | F28: 62.9 | G28: Inc VAT | H28: Paid direct by Ryan (project account) | I28: Decision logged 7 Aug (stainless steel, prevent rusting). Cost finalised 10 Aug, received 12 Aug, fitted 17 Aug. RECLASSIFIED 17 Aug from Chimney to Contingency — genuine scope addition beyond the original quote, same treatment as coping condensation-prep (#6). Paid direct by Ryan.
A29: Materials (pooled) | B29: LG Building and Roofing Ltd (Travis Perkins account) | C29: Luke's Travis Perkins account materials, 3 invoices 17 Jul-5 Aug (render/masonry consumables + lead flashing) — pooled with chimney+coping materials, same simplified treatment as Dry Lining Supplies. | F29: 481.26 | G29: Inc VAT | H29: Reimbursement to Luke | I29: SIMPLIFIED 18 Aug: previously split chimney/coping 50/50 — now pooled as one line, consistent with how Dry Lining Supplies purchases were always treated (not split by workstream). DPC roll (£26.42) stays separately in Contingency (purpose #6, condensation-prep) as it's additional scope, not pool materials.
C30: (merged into row above, 18 Aug) | F30: 0 | G30: Inc VAT | H30: Reimbursement to Luke | I30: RECLASSIFIED 17 Aug: lead flashing reattributed from chimney to coping (original quote explicitly scopes 'lead flashings to parapet rear' under coping's labour). Both items within originally-quoted scope, so routed through Materials pool per agreed rule rather than Coping's own Cost Lines.
A31: Contingency | B31: V4 Wood Flooring Ltd | C31: Named purpose #8 — V4 screw top-up: 15 more boxes of Timberfix structural subframe screws (FH90P050), quote V4FQ-17702 | F31: 141.66 | G31: Inc VAT | H31: Bank transfer | I31: Requested by Luke 20 Aug, ordered 24 Aug, PAID. Substructure screw consumption ran ahead of the original 16-box estimate. Same item/supplier as the original V4 order, but treated as an additional-scope purchase per Ryan's direction — routed through Contingency rather than inflating the Decking materials (V4) line, which stays matched to its original proforma.
A32: Contingency | B32: V4 Wood Flooring Ltd | C32: Named purpose #9 — V4 screw top-up #2: 15 more boxes of Timberfix structural subframe screws (FH90P050), separate order from purpose #8 | F32: 141.66 | G32: Paid | H32: Paid, delivery scheduled 11 Sep | I32: PAID 10 Sep — invoice received. £141.66 used (matching purpose #8's confirmed rate: 15 x £7.87 + 20% VAT) — no invoice number/exact figure given this time, so this is inferred from the established pattern rather than confirmed from a document. Flag if the actual invoice differs. Delivery scheduled 11 Sep.
A33: Contingency | B33: Plant hire company (TBC) | C33: Named purpose #10 — digger + barrow loader hire, one week (on hire until Thu 10 Sep). Mixed purpose: excavation for decking widening, side (a), AND new shed area, perpendicular to side (a) | F33: 530 | G33: Estimate | H33: On hire, not yet invoiced | I33: 8 Sep: digger on hire until Thursday, used for both the side (a) decking excavation and the new shed area excavation. Cost is an estimate ("should be about £530") — actual invoice will confirm. Genuinely mixed-purpose, doesn't cleanly split between the two uses.
A34: Rubbish removal (pooled skips) | B34: TBC (cash) | C34: Old decking substructure wood collection — PAID 11 Sep, £680 cash (was estimated £350; charged per trip, 2 trips) | F34: 680 | G34: Cash | H34: Paid | I34: Original £350 estimate corrected 11 Sep — supplier charges per trip, and 2 trips were needed for this volume of wood. Same job, not a separate charge. From the decking quote scope, so pooled here per Ryan's confirmation.
A35: Roofline works | B35: LG Building and Roofing Ltd | C35: Labour — gutter replacement (both parapet sides + lower rear elevation), fascia/soffit extension, slate replacement, barge board trim | F35: 1600 | G35: No VAT | H35: Paid | I35: Estimate dated 4 Sep. Started 29 Sep. INV-0291 (2 Oct, £1,600, no VAT, labour only) confirmed correct and PAID 3 Oct by bank transfer — full price, so no cash discount applies. Matches the labour line of the estimate exactly.
A36: Roofline works | B36: LG Building and Roofing Ltd | C36: Scaffolding — portable tower | F36: 0 | G36: Inc VAT | H36: Not required | I36: Per estimate 4 Sep. NOT REQUIRED — Luke used his own ladder, so no tower was hired or paid (confirmed 3 Oct). Shown at £0 actual; the £150 benefit offsets the £40.40 of additional materials (net £109.60 under the £2,100 budget). The quote itself stays at £2,140.
A37: Roofline works | B37: LG Building and Roofing Ltd | C37: Materials | F37: 260 | G37: Cash | H37: Paid | I37: Invoice SI19670857 (Graham, 29 Sep): £256.78 (Net £213.98 + VAT £42.80). Luke topped up with £3.22 coin to round to £260 cash, which Ryan paid to Luke 29 Sep. Replaces the generic £350 materials estimate — further materials invoices may follow as the job extends to other elevations.
A38: Rubbish removal (pooled skips) | B38: LG Building and Roofing Ltd | C38: Roofline works rubbish removal — £40, paid directly per the 4 Sep estimate. Reclassified from Roofline works into the pooled fund, avoiding a separate cost centre for what is genuinely the same category of waste-removal spend. | F38: 40 | G38: Inc VAT | H38: Expected — not yet incurred | I38: Per estimate 4 Sep. RECLASSIFIED 8 Sep from Roofline works into the pooled Rubbish removal fund — same rationale as the other pooled items (chimney/coping/decking rubbish already share this fund). Not yet incurred as of 9 Oct (no rubbish removal invoice received) — expected, not drawn.
A39: Contingency | B39: LG Building and Roofing Ltd | C39: Named purpose #11 — extra digging: wider deck gate area (1 day x2 people) + additional deck/shed area (1 day x2 people) | F39: 1260 | G39: Cash (10% disc.) | H39: Paid | I39: Quoted £1,400, cash-discounted to £1,260. Tied to tasks 2.2 (wider gate area) + 2.6 (shed/additional deck) — mixed purpose, doesn't cleanly split between the two. Part of Luke's 11 Sep extras invoice, £2,115 total across 4 items.
A40: Contingency | B40: LG Building and Roofing Ltd | C40: Named purpose #12 — cleanup after machines (2hrs) + dig up small tree (2hrs) | F40: 180 | G40: Cash (10% disc.) | H40: Paid | I40: Quoted £200, cash-discounted to £180. Tied to tasks 2.2/2.6 excavation cleanup. Small tree dig — distinct from task 3.4's external tree/bush clearing company. Part of the same 11 Sep extras invoice.
A41: Contingency | B41: LG Building and Roofing Ltd | C41: Named purpose #13 — fence move, chimney side (side a boundary reclaim from neighbour, to enable the wider decking area) | F41: 315 | G41: Cash (10% disc.) | H41: Paid | I41: Quoted £700 for 'move fence and do spurs to make a full day', but spurs (task 3.3, side b) did NOT happen — only £350 charged for the fence move itself, cash-discounted to £315. NOT the same fence as 3.3 (side b, concrete spurs) or 3.5 (TPO/tree-dependent). New task — see Gantt.
A42: Contingency | B42: LG Building and Roofing Ltd | C42: Named purpose #14 — extra frame for wider deck gate area (1 person; no extra charge for boarding) | F42: 360 | G42: Cash (10% disc.) | H42: Paid | I42: Quoted £400, cash-discounted to £360. Tied to task 2.2 (decking side a widening substructure/framing).
... A74: Contingency | B74: LG Building and Roofing Ltd | C74: Named purpose #4 — additional curved-decking labour: preparing curved structures for the top level of decking. AGREED 24 Sep at £1,000 full price / £900 cash; INVOICED 9 Oct as £800 on INV-0293 (the curves), paid by bank transfer. | F74: 800 | G74: No VAT | H74: Paid 9 Oct (bank transfer) | I74: Luke billed £800 for the curves rather than the £1,000 agreed on 24 Sep; the other £200 is not expected unless Luke bills it later. Paid in full price by bank transfer, so no cash discount. See Invoice Register (INV-0293).
A75: Contingency | B75: V4 Wood Flooring Ltd | C75: Named purpose #24 — Millboard Enhanced Grain 176mm Ashwood decking boards (MDE176H) | D75: 35 | E75: 69.21 | F75: 2422.35 | G75: In net | H75: V4 (quote QUO-0031) — PAID by phone 29 Sep | I75: For the new shed-area / expanded decking scope
A76: Contingency | B76: V4 Wood Flooring Ltd | C76: Named purpose #24 — Plas-Pro Bearer, sub-frame (P1205B300) | D76: 44 | E76: 34.02 | F76: 1496.88 | G76: In net | H76: V4 (quote QUO-0031) — PAID by phone 29 Sep
A77: Contingency | B77: V4 Wood Flooring Ltd | C77: Named purpose #24 — Hexhead Screws 6.3x90mm, box of 50 (FH90P050) | D77: 5 | E77: 7.87 | F77: 39.35 | G77: In net | H77: V4 (quote QUO-0031) — PAID by phone 29 Sep | I77: Same unit price as the original July order — unchanged
A78: Contingency | B78: V4 Wood Flooring Ltd | C78: Named purpose #24 — Bullnose Board Ashwood (MEBB360H) | D78: 3 | E78: 75.46 | F78: 226.38 | G78: In net | H78: V4 (quote QUO-0031) — PAID by phone 29 Sep
A79: Contingency | B79: V4 Wood Flooring Ltd | C79: Named purpose #24 — DuoSpan 99 Flexible Bracket Sets, 10/box (K99FP010) | D79: 2 | E79: 35.95 | F79: 71.9 | G79: In net | H79: V4 (quote QUO-0031) — PAID by phone 29 Sep | I79: For the curved sections
A80: Contingency | B80: V4 Wood Flooring Ltd | C80: Named purpose #24 — DuoSpan-to-Plas-Pro Screws 5x25mm, 100/box (FD25P100) | D80: 1 | E80: 15.79 | F80: 15.79 | G80: In net | H80: V4 (quote QUO-0031) — PAID by phone 29 Sep
A81: Contingency | B81: V4 Wood Flooring Ltd | C81: Named purpose #24 — Flexible Bullnose Step Edge Ashwood (MEBF50H) | D81: 3 | E81: 54.32 | F81: 162.96 | G81: In net | H81: V4 (quote QUO-0031) — PAID by phone 29 Sep | I81: Qty 3 supplied vs 5 originally requested by Luke — flagged, not resolved
A82: Contingency | B82: V4 Wood Flooring Ltd | C82: Named purpose #24 — VAT on order | F82: 887.13 | G82: VAT | H82: V4 (quote QUO-0031) — PAID by phone 29 Sep | I82: Net £4,435.61 + VAT £887.13 = £5,322.74. Quote #QUO-0031 (28 Sep), actioned and paid by phone with Jon 29 Sep — no formal invoice/order confirmation received, quote number used as reference. Delivery expected 30 Sep or 1 Oct. Routed to Contingency (not Decking materials) per Ryan's steer 29 Sep: this order covers the EXPANDED scope — new shed-area decking plus the extra area freed up by the fence move — not the original quoted decking scope. This single draw alone exceeds the £5,000 Contingency pot; logged in full, not capped or hidden. See Contingency Drawdown sheet.
A83: Roofline works | B83: Graham (Plumbers' Merchant) | C83: Materials — Union Bracket (RUH1BL), additional guttering fitting | F83: 9.74 | G83: Inc VAT | H83: Cash | I83: Invoice SI19687572, 30 Sep. Reimbursed to Luke in cash 2 Oct as part of £90.
A84: Roofline works | B84: The Fascia Place (TFP) | C84: Materials — fascia board, soffit board, fascia joints, soffit trim (white) | F84: 78.01 | G84: Inc VAT | H84: Cash | I84: Invoice 0001458493, 30 Sep. Payment received with thanks (per invoice). Reimbursed to Luke in cash 2 Oct as part of £90.
A85: Roofline works | B85: Luke | C85: Cash rounding / coin top-up to make up £90 cash, covering invoices SI19687572 + 0001458493 | F85: 2.25 | G85: Rounding | H85: Cash | I85: Luke provided coins so the combined £87.75 across both invoices rounded to £90 cash. Paid 2 Oct.
A86: Roofline works | B86: The Fascia Place (TFP) | C86: Materials — 250mm x 9mm pre-vented soffit board, white (SM250WV). Invoice 0001458792 (1 Oct) | D86: 1 | F86: 40.4 | G86: Inc VAT | H86: Cash | I86: Net £33.67 + VAT £6.73. Invoice marked 'payment received' (Luke paid at TP counter). Reimbursed to Luke in cash 2 Oct. Roofline materials to date £390.40 cash vs the £350 allowance (£40.40 over).
A87: Contingency | B87: Travis Perkins (Luke's account) | C87: Named purpose #25 — Invoice 1049231418 (11 Aug): Sharp/grit sand trade pack | D87: 2 | F87: 8.86 | G87: Inc VAT | H87: Paid 11 Sep (from £500 TP receipt) | I87: On Luke's TP trade account (NH4276), Net Monthly terms. Cleared by the £500 TP receipt of 11 Sep.
A88: Contingency | B88: Travis Perkins (Luke's account) | C88: Named purpose #25 — Invoice 1049231418 (11 Aug): Building sand trade pack | D88: 4 | F88: 17.71 | G88: Inc VAT | H88: Paid 11 Sep (from £500 TP receipt) | I88: Same invoice/account as above.
A89: Contingency | B89: Travis Perkins (Luke's account) | C89: Named purpose #25 — Invoice 1049231418 (11 Aug): Blue Circle Snowcrete white Portland cement 25kg | D89: 2 | F89: 45.14 | G89: Inc VAT | H89: Paid 11 Sep (from £500 TP receipt) | I89: Same invoice/account as above.
A90: Contingency | B90: Travis Perkins (Luke's account) | C90: Named purpose #25 — Invoice 1049231418 (11 Aug): Bosch Pro multi-material demolition blade (5 pcs) | D90: 1 | F90: 36.43 | G90: Inc VAT | H90: Paid 11 Sep (from £500 TP receipt) | I90: Same invoice/account as above.
A91: Contingency | B91: Travis Perkins (Luke's account) | C91: Named purpose #26 — Invoice 1049595624 (17 Aug): Ballast bulk bag | D91: 1 | F91: 82.19 | G91: Inc VAT | H91: Paid: £247.01 on 11 Sep, £100.11 on 5 Oct (card) | I91: On Luke's TP trade account (NH4276), Net Monthly terms. Part payment of £247.01 inferred by elimination from TP's CSV; the £100.11 balance was paid by card on 5 Oct (TP settlement).
A92: Contingency | B92: Travis Perkins (Luke's account) | C92: Named purpose #26 — Invoice 1049595624 (17 Aug): Building sand bulk bag | D92: 1 | F92: 82.19 | G92: Inc VAT | H92: Paid: £247.01 on 11 Sep, £100.11 on 5 Oct (card) | I92: Same invoice/account as above.
A93: Contingency | B93: Travis Perkins (Luke's account) | C93: Named purpose #26 — Invoice 1049595624 (17 Aug): Solid dense block 100mm 7.3N | D93: 72 | F93: 182.74 | G93: Inc VAT | H93: Paid: £247.01 on 11 Sep, £100.11 on 5 Oct (card) | I93: Same invoice/account as above.
A94: Contingency | B94: Travis Perkins (Luke's account) | C94: Named purpose #27 — Invoice 1050655200 (03 Sep): Ballast bulk bag | D94: 2 | F94: 164.38 | G94: Inc VAT | H94: Paid 5 Oct (card, TP settlement) | I94: On Luke's TP trade account (NH4276), Net Monthly terms. Paid 5 Oct by card as part of the TP settlement.
A95: Contingency | B95: Travis Perkins (Luke's account) | C95: Named purpose #27 — Invoice 1050655200 (03 Sep): Mastercrete cement 25kg | D95: 10 | F95: 85.08 | G95: Inc VAT | H95: Paid 5 Oct (card, TP settlement) | I95: Same invoice/account as above. Paid 5 Oct by card as part of the TP settlement.
A96: Contingency | B96: Travis Perkins Hire (Luke's account) | C96: Named purpose #28 — Invoice 1051287675 (14 Sep): Tracked dumper 500kg, 7 days (2–8 Sep) | D96: 1 | F96: 163.3 | G96: Inc VAT | H96: Paid 5 Oct (card, TP settlement) | I96: On Luke's TP trade account (NH4276), Net Monthly terms. Paid 5 Oct by card as part of the TP settlement.
A97: Contingency | B97: Travis Perkins Hire (Luke's account) | C97: Named purpose #28 — Invoice 1051287675 (14 Sep): Loss and damage waiver | D97: 1 | F97: 24.49 | G97: Inc VAT | H97: Paid 5 Oct (card, TP settlement) | I97: Same invoice/account as above. Paid 5 Oct by card as part of the TP settlement.
... A105: Contingency | B105: Travis Perkins (Luke's account) | C105: Named purpose #30 — Invoice 1051708772 (21 Sep): Solid dense block 100mm | D105: 20 | F105: 50.76 | G105: Inc VAT | H105: Paid 5 Oct (card, TP settlement) | I105: On Luke's TP trade account (NH4276), Net Monthly terms. Paid 5 Oct by card as part of the TP settlement.
A106: Contingency | B106: LG Building and Roofing Ltd | C106: Named purpose #31 — additional lead work: chase lead into walls so the gutters work properly (issue found during the Roofline works) | F106: 200 | G106: Estimate | H106: Work complete Fri 16 Oct — awaiting invoice | I106: Luke's estimate 2 Oct (WhatsApp), approx £200; job completed Fri 16 Oct (lead flashing confirmed included). Additional scope arising from the Roofline works, to be drawn from Contingency (Ryan, 3 Oct). Gantt task 1.5a — part of Gate 2, must finish before decking boards are laid. Logged in Cost Lines only — not in the Invoice Register or Drawdown until invoiced.
A107: Contingency | B107: LG Building and Roofing Ltd | C107: Named purpose #32 — additional deck labour (extended deck & shed base): the additional decking carried out, part of INV-0293 (curve and additional decking) | F107: 1050 | G107: No VAT | H107: Paid 9 Oct (bank transfer) | I107: Invoiced 9 Oct as part of INV-0293 (£1,850: £800 curves + £1,050 additional deck) and paid the same day by bank transfer. Separate from the £17,600 main decking labour draws.
A108: Contingency | B108: Toolstation Ltd (bought by Luke) | C108: Named purpose #33 — Invoice YAC545477716 (6 Oct): Freud mitre saw blade | D108: 1 | F108: 71.99 | G108: Inc VAT | H108: Paid 13 Oct (cash to Luke) | I108: Bought by Luke on his card 6 Oct; repaid in cash 13 Oct. Scope Main deck, though the tools will be used throughout.
A109: Contingency | B109: Toolstation Ltd (bought by Luke) | C109: Named purpose #33 — Invoice YAC545477716 (6 Oct): ROKTOR HSS titanium multi-material drill bits | D109: 1 | F109: 2.99 | G109: Inc VAT | H109: Paid 13 Oct (cash to Luke) | I109: Bought by Luke on his card 6 Oct; repaid in cash 13 Oct. Scope Main deck, though the tools will be used throughout.
A110: Contingency | B110: Toolstation Ltd (bought by Luke) | C110: Named purpose #33 — Invoice YAC545477716 (6 Oct): DeWalt construction circular saw blade | D110: 1 | F110: 9.99 | G110: Inc VAT | H110: Paid 13 Oct (cash to Luke) | I110: Bought by Luke on his card 6 Oct; repaid in cash 13 Oct. Scope Main deck, though the tools will be used throughout.
A111: Contingency | B111: Gorgeous Cleaning Services | C111: Named purpose #34 — whole-house soft wash: gutters, soffits, roof tiles, roof solar panels, render, windows etc. | F111: 1200 | G111: Actual | H111: Paid 19 Oct (cash) | I111: £1,200 cash, drawn from Contingency (Ryan, 13 Oct). Starts Mon 19 Oct. Replaces the chimney + coping-only soft wash (Gantt 1.6): cheaper to use a previous supplier for the whole house than to spot clean with Luke. Roofline works were completed Fri 16 Oct, ahead of the soft wash. Logged in Cost Lines only until paid. COMPLETED: started and finished Mon 19 Oct (very successful). PAID £1,200 cash Mon 19 Oct (now in the Invoice Register).
A112: Contingency | B112: LG Building and Roofing Ltd | C112: Named purpose #35 — driveway channel: lift cobbles, dig waste channel, connect water-softener discharge to natural drainage, reinstate cobbles (LG INV-0294) | F112: 350 | G112: No VAT | H112: Paid 17 Oct (bank transfer) | I112: Half a day, Luke and Max, Wed 14 Oct (Gantt task 3.1). Part of LG INV-0294 (£1,350, paid 17 Oct). Softener discharge confirmed working; cobbles reinstated.
A113: Contingency | B113: LG Building and Roofing Ltd | C113: Named purpose #36 — extra decking labour, extended deck & shed base (LG INV-0294) | F113: 1000 | G113: No VAT | H113: Paid 17 Oct (bank transfer) | I113: Extra decking labour, as discussed. Part of LG INV-0294 (£1,350, paid 17 Oct). Luke has not yet agreed any further extended-deck labour.
A114: Contingency | B114: Buy Insulation Online | C114: Named purpose #37 — Order INV842429677 (20 Oct): Stornch outdoor pipe insulation 2m x 22mm bore x 19mm thick, 7 x £21.14 (£147.98 + £29.60 VAT) | D114: 7 | E114: 21.14 | F114: 177.58 | G114: Inc VAT | H114: Paid 20 Oct (Ryan's card) | I114: Pipe lagging for the outside tap/pipework (Gantt 2.4, Gate 3). Free standard delivery; delivery date to follow. Scope Shared / site-wide (main deck).
A115: Contingency | B115: V4 Wood Flooring Ltd | C115: Named purpose #38 — QUO-0040: materials to complete the decking substructure (delivered Mon 19 Oct) | F115: 1268 | G115: Inc VAT | H115: Paid 22 Oct (card) | I115: Paid by card to V4 on Thu 22 Oct. Scope Extended deck & shed base; some Plas-Pro will likely be used on the main decking. Itemised lines not yet captured.
C116: TOTAL (all lines) | F116: =SUM(F5:F115) -> 86571.42

Sheet TP Account
A1: Travis Perkins (TP) account — invoices, payments and settlement
A2: Luke's TP trade account NH4276. Amounts inc VAT. Built 3 Oct 2026 from the paper invoices and TP's transaction history CSV (2 Oct). Updated 9 Oct 2026: account settled (5 Oct card payment; 6 Oct repayment from Luke).
A4: # | B4: Invoice no. | C4: Invoice date | D4: Description | E4: Amount £ | F4: Paid £ | G4: Balance £ | H4: Status | I4: Cost centre / purpose | J4: Line items check £ (must be 0.00) | K4: Notes | L4: Scope
A5: 1–3 | B5: 1047678330 / 1047972816 / 1048887075 | C5: 17 Jul – 5 Aug | D5: Render/masonry consumables + lead flashing; DPC roll (grouped, not itemised) | E5: 507.7 | F5: 507.7 | G5: =ROUND(E5-F5,2) -> 0 | H5: =IF(G5=0,"Paid",IF(F5>0,"Part paid","Invoiced, ON HOLD")) -> Paid | I5: Materials (pooled) £481.28; Contingency #6 £26.42 | J5: =ROUND(E5-SUMIFS('TP Line Items'!$F:$F,'TP Line Items'!$A:$A,$B5),2) -> 0 | K5: Paid 18 Aug — part of £547.88 settlement (bank transfer) | L5: Chimney & coping
A6: 4 | B6: 1049120278 | C6: 46244 | D6: Cleaning/finishing consumables (pooled, not itemised) | E6: 40.18 | F6: 40.18 | G6: =ROUND(E6-F6,2) -> 0 | H6: =IF(G6=0,"Paid",IF(F6>0,"Part paid","Invoiced, ON HOLD")) -> Paid | I6: Materials (pooled) | J6: =ROUND(E6-SUMIFS('TP Line Items'!$F:$F,'TP Line Items'!$A:$A,$B6),2) -> 0 | K6: Paid 18 Aug — part of £547.88 settlement (bank transfer) | L6: Chimney & coping
A7: 5 | B7: 1049231418 | C7: 46245 | D7: Sand, white Snowcrete cement, Bosch blade | E7: 108.14 | F7: 108.14 | G7: =ROUND(E7-F7,2) -> 0 | H7: =IF(G7=0,"Paid",IF(F7>0,"Part paid","Invoiced, ON HOLD")) -> Paid | I7: Contingency #25 | J7: =ROUND(E7-SUMIFS('TP Line Items'!$F:$F,'TP Line Items'!$A:$A,$B7),2) -> 0 | K7: Paid 11 Sep from the £500 TP receipt (TP CSV) | L7: Main deck
A8: 6 | B8: 1049595624 | C8: 46251 | D8: Ballast, building sand (bulk bags), 72 blocks | E8: 347.12 | F8: 347.12 | G8: =ROUND(E8-F8,2) -> 0 | H8: =IF(G8=0,"Paid",IF(F8>0,"Part paid","Invoiced, ON HOLD")) -> Paid | I8: Contingency #26 | J8: =ROUND(E8-SUMIFS('TP Line Items'!$F:$F,'TP Line Items'!$A:$A,$B8),2) -> 0 | K8: £247.01 paid 11 Sep from the £500 receipt (inferred by elimination); the £100.11 balance was paid by card 5 Oct. | L8: Main deck
A9: 7 | B9: 1049651867 | C9: 46252 | D9: Mastercrete cement x12, Trend blade | E9: 144.58 | F9: 144.58 | G9: =ROUND(E9-F9,2) -> 0 | H9: =IF(G9=0,"Paid",IF(F9>0,"Part paid","Invoiced, ON HOLD")) -> Paid | I9: Contingency #16 | J9: =ROUND(E9-SUMIFS('TP Line Items'!$F:$F,'TP Line Items'!$A:$A,$B9),2) -> 0 | K9: Paid by card 5 Oct (settlement) | L9: Main deck
A10: 8 | B10: 1049757851 | C10: 46253 | D10: Plywood 18mm, drill bit, woodscrews, gloves | E10: 74.34 | F10: 74.34 | G10: =ROUND(E10-F10,2) -> 0 | H10: =IF(G10=0,"Paid",IF(F10>0,"Part paid","Invoiced, ON HOLD")) -> Paid | I10: Contingency #17 | J10: =ROUND(E10-SUMIFS('TP Line Items'!$F:$F,'TP Line Items'!$A:$A,$B10),2) -> 0 | K10: Paid by card 5 Oct (settlement) | L10: Main deck
A11: 9 | B11: 1049844267 | C11: 46254 | D11: Broadfix flat packers | E11: 22.66 | F11: 22.66 | G11: =ROUND(E11-F11,2) -> 0 | H11: =IF(G11=0,"Paid",IF(F11>0,"Part paid","Invoiced, ON HOLD")) -> Paid | I11: Contingency #19 | J11: =ROUND(E11-SUMIFS('TP Line Items'!$F:$F,'TP Line Items'!$A:$A,$B11),2) -> 0 | K11: Paid by card 5 Oct (settlement) | L11: Main deck
A12: 10 | B12: 1049844268 | C12: 46254 | D12: Ballast x2, cement x10, 72 blocks, pallet deposit | E12: 462.5 | F12: 462.5 | G12: =ROUND(E12-F12,2) -> 0 | H12: =IF(G12=0,"Paid",IF(F12>0,"Part paid","Invoiced, ON HOLD")) -> Paid | I12: Contingency #18 | J12: =ROUND(E12-SUMIFS('TP Line Items'!$F:$F,'TP Line Items'!$A:$A,$B12),2) -> 0 | K12: Includes £30.30 refundable pallet deposit. Paid by card 5 Oct (settlement) | L12: Main deck
A13: 11 | B13: 1050655200 | C13: 46268 | D13: Ballast x2, Mastercrete x10 | E13: 249.46 | F13: 249.46 | G13: =ROUND(E13-F13,2) -> 0 | H13: =IF(G13=0,"Paid",IF(F13>0,"Part paid","Invoiced, ON HOLD")) -> Paid | I13: Contingency #27 | J13: =ROUND(E13-SUMIFS('TP Line Items'!$F:$F,'TP Line Items'!$A:$A,$B13),2) -> 0 | K13: Paid by card 5 Oct (settlement) | L13: Main deck
A14: 12 | B14: 1050903283 | C14: 46273 | D14: Plywood 12mm x2, line marker | E14: 58.62 | F14: 58.62 | G14: =ROUND(E14-F14,2) -> 0 | H14: =IF(G14=0,"Paid",IF(F14>0,"Part paid","Invoiced, ON HOLD")) -> Paid | I14: Contingency #20 | J14: =ROUND(E14-SUMIFS('TP Line Items'!$F:$F,'TP Line Items'!$A:$A,$B14),2) -> 0 | K14: Paid by card 5 Oct (settlement) | L14: Main deck
A15: 13 | B15: 1051011143 | C15: 46274 | D15: Digger hire 3–8 Sep (1.5T excavator) | E15: 378.58 | F15: 378.58 | G15: =ROUND(E15-F15,2) -> 0 | H15: =IF(G15=0,"Paid",IF(F15>0,"Part paid","Invoiced, ON HOLD")) -> Paid | I15: Contingency #10 | J15: =ROUND(E15-SUMIFS('TP Line Items'!$F:$F,'TP Line Items'!$A:$A,$B15),2) -> 0 | K15: Paid by card 5 Oct (settlement) | L15: Groundworks (digger & dumper)
A16: 14 | B16: 1051072869 | C16: 46275 | D16: Ballast, Mastercrete x5 | E16: 124.73 | F16: 124.73 | G16: =ROUND(E16-F16,2) -> 0 | H16: =IF(G16=0,"Paid",IF(F16>0,"Part paid","Invoiced, ON HOLD")) -> Paid | I16: Contingency #21 | J16: =ROUND(E16-SUMIFS('TP Line Items'!$F:$F,'TP Line Items'!$A:$A,$B16),2) -> 0 | K16: Paid by card 5 Oct (settlement) | L16: Main deck
A17: 15 | B17: 1051142985 | C17: 46276 | D17: Fence materials | E17: 291.17 | F17: 291.17 | G17: =ROUND(E17-F17,2) -> 0 | H17: =IF(G17=0,"Paid",IF(F17>0,"Part paid","Invoiced, ON HOLD")) -> Paid | I17: Contingency #23 | J17: =ROUND(E17-SUMIFS('TP Line Items'!$F:$F,'TP Line Items'!$A:$A,$B17),2) -> 0 | K17: The purchase the £500 receipt enabled. Paid by card 5 Oct (settlement) | L17: Fence relocation
... A21: 19 | B21: 1051708772 | C21: 46286 | D21: Blocks x20 | E21: 50.76 | F21: 50.76 | G21: =ROUND(E21-F21,2) -> 0 | H21: =IF(G21=0,"Paid",IF(F21>0,"Part paid","Invoiced, ON HOLD")) -> Paid | I21: Contingency #30 | J21: =ROUND(E21-SUMIFS('TP Line Items'!$F:$F,'TP Line Items'!$A:$A,$B21),2) -> 0 | K21: Paid by card 5 Oct (settlement) | L21: Extended deck & shed base
B22: TOTAL (17 lines = 19 invoices) | E22: =SUM(E5:E21) -> 3216.92 | F22: =SUM(F5:F21) -> 3216.92 | G22: =SUM(G5:G21) -> 0 | J22: =SUM(J5:J21) -> 0
A24: Payments to TP
B25: Date | C25: Payment | D25: Detail | E25: Amount £ | F25: Method
B26: 46252 | C26: TP account settlement | D26: Covers invoices #1–4 (bank transfer) | E26: 547.88 | F26: Bank transfer
B27: 46276 | C27: TP account receipt | D27: Ref 3357*NH4276*21439*1; taken from bank 12 Sep. Allocated below (TP transaction history CSV) | E27: 500 | F27: Bank transfer
B28: 46300 | C28: TP settlement payment | D28: Balance of #6 (£100.11) plus #7–#19 (£2,213.78). Card. Settles the account | E28: 2313.89 | F28: Card
B29: TOTAL PAID TO TP (gross) | E29: =E26+E27+E28 -> 3361.77
B30: 46301 | C30: Repayment from Luke | D30: The part of the 11 Sep £500 that cleared other jobs' invoices (Chris / Wendy), repaid to us | E30: -144.85 | F30: Repayment
B31: NET PAID TO TP (gross less repayment) | E31: =E29+E30 -> 3216.92
A34: How the £500 (11 Sep) was applied — per TP's CSV
B35: Invoice no. | C35: Invoice date | D35: PO ref on invoice | E35: Amount applied £ | F35: Project invoice?
B36: 1047365656 | C36: 46216 | D36: CHRIS | E36: 69.8 | F36: No — other job
B37: 1047453677 | C37: 46217 | D37: CHRIS | E37: 30.65 | F37: No — other job
B38: 1047531278 | C38: 46218 | D38: WENDY | E38: 30.69 | F38: No — other job
B39: 1047531279 | C39: 46218 | D39: WENDY | E39: 13.71 | F39: No — other job
B40: 1049231418 | C40: 46245 | D40: LARA | E40: =F7 -> 108.14 | F40: Yes — our #5
B41: 1049595624 | C41: 46251 | D41: LARA | E41: 247.01 | F41: Yes — part payment on our #6 (inferred by elimination; CSV does not list #6)
B42: TOTAL APPLIED | E42: =SUM(E36:E41) -> 500
B43: Check: £500 less total applied (must be 0.00) | E43: =ROUND(E27-E42,2) -> 0
B44: Of which: other jobs (not project spend) | E44: =SUMIF(F36:F41,"No*",E36:E41) -> 144.85
B45: Of which: this project | E45: =SUMIF(F36:F41,"Yes*",E36:E41) -> 355.15
A48: Settlement of our TP involvement — SETTLED 5–6 Oct (approach agreed with Luke, 3 Oct)
B49: Item | E49: Amount £
B50: Balance still owing on #6 (invoice less the £247.01 paid 11 Sep) | E50: =ROUND(E8-E41,2) -> 100.11
B51: Plus: total of invoices #7 to #19 | E51: =SUM(E9:E21) -> 2213.78
B52: Less: our £500 used on other jobs' invoices (Wendy / Chris) | E52: =-E44 -> -144.85
B53: AMOUNT TO SETTLE | E53: =SUM(E50:E52) -> 2169.04
B54: If the £30.30 pallet deposit is refunded (possible credit still to come) | E54: =E53-SUMIFS('TP Line Items'!$F:$F,'TP Line Items'!$D:$D,"Refundable pallet deposit") -> 2138.74
B55: Net paid in settlement: 5 Oct card payment less 6 Oct repayment from Luke | E55: =E28+E30 -> 2169.04
B56: Check: amount to settle less net paid in settlement (must be 0.00) | E56: =ROUND(E53-E55,2) -> 0
B57: Check: Invoice Register total for Travis Perkins suppliers less ledger total (must be 0.00) | E57: =ROUND(SUMIF('Invoice Register'!$C:$C,"*Travis Perkins*",'Invoice Register'!$F:$F)-E22,2) -> 0
B58: Check: total invoiced less net paid to TP — balance outstanding (must be 0.00) | E58: =ROUND(E22-E31,2) -> 0
B59: Covers the 19 invoices held at 3 Oct. Settled in full 5 Oct; any further TP invoices from Luke would be additional.

Sheet TP Spend by Item
A1: TP Spend by Item — combined spend on each material across all TP invoices
A2: Calculated from the TP Line Items tab. Amounts inc VAT; 'spend' = invoiced, regardless of payment status. First/last dates are invoice dates.
A4: Item | B4: What's in it | C4: Spend £ (inc VAT) | D4: First invoice | E4: Last invoice | F4: Invoices (# in TP Account) | G4: Qty / detail
A5: Ballast | B5: Bulk bags | C5: =SUMIFS('TP Line Items'!$F:$F,'TP Line Items'!$D:$D,$A5) -> 493.14 | D5: =_xlfn.MINIFS('TP Line Items'!$B:$B,'TP Line Items'!$D:$D,$A5) -> 46251 | E5: =_xlfn.MAXIFS('TP Line Items'!$B:$B,'TP Line Items'!$D:$D,$A5) -> 46275 | F5: #6, #10, #11, #14 | G5: 6 bulk bags (~£82.19 each)
A6: Concrete blocks | B6: 100mm solid dense | C6: =SUMIFS('TP Line Items'!$F:$F,'TP Line Items'!$D:$D,$A6) -> 431.47 | D6: =_xlfn.MINIFS('TP Line Items'!$B:$B,'TP Line Items'!$D:$D,$A6) -> 46251 | E6: =_xlfn.MAXIFS('TP Line Items'!$B:$B,'TP Line Items'!$D:$D,$A6) -> 46286 | F6: #6, #10, #18, #19 | G6: 170 blocks (72 + 72 + 6 + 20)
A7: Cement | B7: Mastercrete 25kg and white Snowcrete | C7: =SUMIFS('TP Line Items'!$F:$F,'TP Line Items'!$D:$D,$A7) -> 393.97 | D7: =_xlfn.MINIFS('TP Line Items'!$B:$B,'TP Line Items'!$D:$D,$A7) -> 46245 | E7: =_xlfn.MAXIFS('TP Line Items'!$B:$B,'TP Line Items'!$D:$D,$A7) -> 46286 | F7: #5, #7, #10, #11, #14, #18 | G7: 43 bags: 41 Mastercrete (~£8.51) + 2 Snowcrete (~£22.57)
A8: Fence materials | B8: Posts, rail brackets, Postcrete, pegs, treated timber | C8: =SUMIFS('TP Line Items'!$F:$F,'TP Line Items'!$D:$D,$A8) -> 283.32 | D8: =_xlfn.MINIFS('TP Line Items'!$B:$B,'TP Line Items'!$D:$D,$A8) -> 46276 | E8: =_xlfn.MAXIFS('TP Line Items'!$B:$B,'TP Line Items'!$D:$D,$A8) -> 46276 | F8: #15 | G8: One invoice, 11 Sep
A9: Tools, PPE, screws & small consumables | B9: Blades, drill bit, mallet, line markers, gloves, woodscrews, flat packers | C9: =SUMIFS('TP Line Items'!$F:$F,'TP Line Items'!$D:$D,$A9) -> 187.66 | D9: =_xlfn.MINIFS('TP Line Items'!$B:$B,'TP Line Items'!$D:$D,$A9) -> 46245 | E9: =_xlfn.MAXIFS('TP Line Items'!$B:$B,'TP Line Items'!$D:$D,$A9) -> 46286 | F9: #5, #7, #8, #9, #12, #15, #16, #18 | G9: Small items across 8 invoices
A10: Sand | B10: Building, sharp/grit sand; bulk bag | C10: =SUMIFS('TP Line Items'!$F:$F,'TP Line Items'!$D:$D,$A10) -> 108.76 | D10: =_xlfn.MINIFS('TP Line Items'!$B:$B,'TP Line Items'!$D:$D,$A10) -> 46245 | E10: =_xlfn.MAXIFS('TP Line Items'!$B:$B,'TP Line Items'!$D:$D,$A10) -> 46251 | F10: #5, #6 | G10: 7 units (1 bulk bag, 4 + 2 trade packs)
A11: Shuttering plywood | B11: 18mm and 12mm CE2 | C11: =SUMIFS('TP Line Items'!$F:$F,'TP Line Items'!$D:$D,$A11) -> 84.05 | D11: =_xlfn.MINIFS('TP Line Items'!$B:$B,'TP Line Items'!$D:$D,$A11) -> 46253 | E11: =_xlfn.MAXIFS('TP Line Items'!$B:$B,'TP Line Items'!$D:$D,$A11) -> 46273 | F11: #8, #12 | G11: 18mm + 2 x 12mm
A12: Plant hire | B12: Digger £378.58 (hired 3–8 Sep) + tracked dumper £277.79 (hired 2–8 Sep) | C12: =SUMIFS('TP Line Items'!$F:$F,'TP Line Items'!$D:$D,$A12) -> 656.37 | D12: =_xlfn.MINIFS('TP Line Items'!$B:$B,'TP Line Items'!$D:$D,$A12) -> 46274 | E12: =_xlfn.MAXIFS('TP Line Items'!$B:$B,'TP Line Items'!$D:$D,$A12) -> 46279 | F12: #13, #17 | G12: Invoice dates, not hire dates
A13: Refundable pallet deposit | B13: Block pallet deposit — not a final cost if the pallet is returned | C13: =SUMIFS('TP Line Items'!$F:$F,'TP Line Items'!$D:$D,$A13) -> 30.3 | D13: =_xlfn.MINIFS('TP Line Items'!$B:$B,'TP Line Items'!$D:$D,$A13) -> 46254 | E13: =_xlfn.MAXIFS('TP Line Items'!$B:$B,'TP Line Items'!$D:$D,$A13) -> 46254 | F13: #10 | G13: Refundable
A14: SUBTOTAL — invoices #5–19 | C14: =SUM(C5:C13) -> 2669.04
A15: Invoices #1–4 (not itemised) | B15: Render/masonry consumables + lead flashing £481.28; DPC roll £26.42; cleaning/finishing consumables £40.18 | C15: =SUMIFS('TP Line Items'!$F:$F,'TP Line Items'!$D:$D,$A15) -> 547.88 | D15: 17 Jul 2026 | E15: 10 Aug 2026 | F15: #1–#4 | G15: Settled 18 Aug; no item breakdown held
A16: TOTAL INVOICED | C16: =C14+C15 -> 3216.92
A17: Check: TP Account total less this total (must be 0.00) | C17: =ROUND('TP Account'!E22-C16,2) -> 0

Sheet TP Line Items
A1: TP Line Items — every item on every Travis Perkins invoice
A2: Source for the TP Account and TP Spend by Item tabs. Amounts inc VAT. Invoices #1–4 were settled as a group and are not itemised. Built 3 Oct 2026 from paper invoices and the tracker.
A4: Invoice no. | B4: Invoice date | C4: Item | D4: Category | E4: Qty | F4: Amount £ (inc VAT) | G4: Scope | H4: Scope basis
A5: 1047678330 / 1047972816 / 1048887075 | B5: 17 Jul – 5 Aug | C5: Render/masonry consumables + lead flashing (pooled, not itemised) | D5: Invoices #1–4 (not itemised) | F5: 481.28 | G5: Chimney & coping | H5: Cost centre (chimney/coping pools).
A6: 1047678330 / 1047972816 / 1048887075 | B6: 17 Jul – 5 Aug | C6: Damplas DPC roll (invoice 1048887075) | D6: Invoices #1–4 (not itemised) | F6: 26.42 | G6: Chimney & coping | H6: Cost centre (chimney/coping pools).
A7: 1049120278 | B7: 46244 | C7: Cleaning/finishing consumables (pooled, not itemised) | D7: Invoices #1–4 (not itemised) | F7: 40.18 | G7: Chimney & coping | H7: Cost centre (chimney/coping pools).
A8: 1049231418 | B8: 46245 | C8: Sharp/grit sand trade pack | D8: Sand | E8: 2 | F8: 8.86 | G8: Main deck | H8: Date rule: invoiced before 21 Sep → main deck. Luke (2 Oct): only 1 day (2 people) spent on the extended deck so far — half last week, half this week. INFERRED — confirm with Luke.
A9: 1049231418 | B9: 46245 | C9: Building sand trade pack | D9: Sand | E9: 4 | F9: 17.71 | G9: Main deck | H9: Date rule: invoiced before 21 Sep → main deck. Luke (2 Oct): only 1 day (2 people) spent on the extended deck so far — half last week, half this week. INFERRED — confirm with Luke.
A10: 1049231418 | B10: 46245 | C10: Blue Circle Snowcrete white Portland cement 25kg | D10: Cement | E10: 2 | F10: 45.14 | G10: Main deck | H10: Date rule: invoiced before 21 Sep → main deck. Luke (2 Oct): only 1 day (2 people) spent on the extended deck so far — half last week, half this week. INFERRED — confirm with Luke.
A11: 1049231418 | B11: 46245 | C11: Bosch Pro multi-material demolition blade (5 pcs) | D11: Tools, PPE, screws & small consumables | E11: 1 | F11: 36.43 | G11: Main deck | H11: Date rule: invoiced before 21 Sep → main deck. Luke (2 Oct): only 1 day (2 people) spent on the extended deck so far — half last week, half this week. INFERRED — confirm with Luke.
A12: 1049595624 | B12: 46251 | C12: Ballast bulk bag | D12: Ballast | E12: 1 | F12: 82.19 | G12: Main deck | H12: Date rule: invoiced before 21 Sep → main deck. Luke (2 Oct): only 1 day (2 people) spent on the extended deck so far — half last week, half this week. INFERRED — confirm with Luke.
A13: 1049595624 | B13: 46251 | C13: Building sand bulk bag | D13: Sand | E13: 1 | F13: 82.19 | G13: Main deck | H13: Date rule: invoiced before 21 Sep → main deck. Luke (2 Oct): only 1 day (2 people) spent on the extended deck so far — half last week, half this week. INFERRED — confirm with Luke.
A14: 1049595624 | B14: 46251 | C14: Solid dense block 100mm 7.3N | D14: Concrete blocks | E14: 72 | F14: 182.74 | G14: Main deck | H14: Date rule: invoiced before 21 Sep → main deck. Luke (2 Oct): only 1 day (2 people) spent on the extended deck so far — half last week, half this week. INFERRED — confirm with Luke.
A15: 1049651867 | B15: 46252 | C15: Blue Circle Mastercrete cement 25kg | D15: Cement | E15: 12 | F15: 102.1 | G15: Main deck | H15: Date rule: invoiced before 21 Sep → main deck. Luke (2 Oct): only 1 day (2 people) spent on the extended deck so far — half last week, half this week. INFERRED — confirm with Luke.
A16: 1049651867 | B16: 46252 | C16: Trend Craft blade CC 305mm | D16: Tools, PPE, screws & small consumables | E16: 1 | F16: 42.48 | G16: Main deck | H16: Date rule: invoiced before 21 Sep → main deck. Luke (2 Oct): only 1 day (2 people) spent on the extended deck so far — half last week, half this week. INFERRED — confirm with Luke.
A17: 1049757851 | B17: 46253 | C17: Shuttering plywood 18mm CE2 | D17: Shuttering plywood | F17: 30.79 | G17: Main deck | H17: Date rule: invoiced before 21 Sep → main deck. Luke (2 Oct): only 1 day (2 people) spent on the extended deck so far — half last week, half this week. INFERRED — confirm with Luke.
A18: 1049757851 | B18: 46253 | C18: Dewalt drill bit | D18: Tools, PPE, screws & small consumables | E18: 1 | F18: 10.86 | G18: Main deck | H18: Date rule: invoiced before 21 Sep → main deck. Luke (2 Oct): only 1 day (2 people) spent on the extended deck so far — half last week, half this week. INFERRED — confirm with Luke.
A19: 1049757851 | B19: 46253 | C19: Stick-Fit woodscrews 5.0x80mm (pack of 200) | D19: Tools, PPE, screws & small consumables | E19: 1 | F19: 17.88 | G19: Main deck | H19: Date rule: invoiced before 21 Sep → main deck. Luke (2 Oct): only 1 day (2 people) spent on the extended deck so far — half last week, half this week. INFERRED — confirm with Luke.
A20: 1049757851 | B20: 46253 | C20: Wonder Grip gloves size 9 | D20: Tools, PPE, screws & small consumables | E20: 1 | F20: 14.81 | G20: Main deck | H20: Date rule: invoiced before 21 Sep → main deck. Luke (2 Oct): only 1 day (2 people) spent on the extended deck so far — half last week, half this week. INFERRED — confirm with Luke.
A21: 1049844267 | B21: 46254 | C21: Broadfix flat packers, tub of 300 | D21: Tools, PPE, screws & small consumables | E21: 1 | F21: 22.66 | G21: Main deck | H21: Date rule: invoiced before 21 Sep → main deck. Luke (2 Oct): only 1 day (2 people) spent on the extended deck so far — half last week, half this week. INFERRED — confirm with Luke.
A22: 1049844268 | B22: 46254 | C22: Ballast bulk bag | D22: Ballast | E22: 1 | F22: 82.19 | G22: Main deck | H22: Date rule: invoiced before 21 Sep → main deck. Luke (2 Oct): only 1 day (2 people) spent on the extended deck so far — half last week, half this week. INFERRED — confirm with Luke.
A23: 1049844268 | B23: 46254 | C23: Mastercrete cement 25kg | D23: Cement | E23: 10 | F23: 85.08 | G23: Main deck | H23: Date rule: invoiced before 21 Sep → main deck. Luke (2 Oct): only 1 day (2 people) spent on the extended deck so far — half last week, half this week. INFERRED — confirm with Luke.
A24: 1049844268 | B24: 46254 | C24: Solid dense block 100mm | D24: Concrete blocks | E24: 72 | F24: 182.74 | G24: Main deck | H24: Date rule: invoiced before 21 Sep → main deck. Luke (2 Oct): only 1 day (2 people) spent on the extended deck so far — half last week, half this week. INFERRED — confirm with Luke.
A25: 1049844268 | B25: 46254 | C25: Block pallet deposit — REFUNDABLE | D25: Refundable pallet deposit | E25: 1 | F25: 30.3 | G25: Main deck | H25: Date rule: invoiced before 21 Sep → main deck. Luke (2 Oct): only 1 day (2 people) spent on the extended deck so far — half last week, half this week. INFERRED — confirm with Luke.
A26: 1049844268 | B26: 46254 | C26: Ballast bulk bag (2nd) | D26: Ballast | E26: 1 | F26: 82.19 | G26: Main deck | H26: Date rule: invoiced before 21 Sep → main deck. Luke (2 Oct): only 1 day (2 people) spent on the extended deck so far — half last week, half this week. INFERRED — confirm with Luke.
A27: 1050655200 | B27: 46268 | C27: Ballast bulk bag | D27: Ballast | E27: 2 | F27: 164.38 | G27: Main deck | H27: Date rule: invoiced before 21 Sep → main deck. Luke (2 Oct): only 1 day (2 people) spent on the extended deck so far — half last week, half this week. INFERRED — confirm with Luke.
A28: 1050655200 | B28: 46268 | C28: Mastercrete cement 25kg | D28: Cement | E28: 10 | F28: 85.08 | G28: Main deck | H28: Date rule: invoiced before 21 Sep → main deck. Luke (2 Oct): only 1 day (2 people) spent on the extended deck so far — half last week, half this week. INFERRED — confirm with Luke.
A29: 1050903283 | B29: 46273 | C29: Shuttering plywood 12mm CE2 | D29: Shuttering plywood | E29: 2 | F29: 53.26 | G29: Main deck | H29: Date rule: invoiced before 21 Sep → main deck. Luke (2 Oct): only 1 day (2 people) spent on the extended deck so far — half last week, half this week. INFERRED — confirm with Luke.
... A44: 1051142985 | B44: 46276 | C44: Wonder Grip Duo Gloves (XL) | D44: Tools, PPE, screws & small consumables | E44: 1 | F44: 7.85 | G44: Fence relocation | H44: Item: fence materials.
A45: 1051162218 | B45: 46276 | C45: Wonder Grip gloves (L) + Stick-Fit woodscrews 5.0x40mm (x200) — combined line | D45: Tools, PPE, screws & small consumables | F45: 18.29 | G45: Shared / site-wide | H45: Small consumables — cannot be split between projects. INFERRED.
A46: 1051287675 | B46: 46279 | C46: Tracked dumper 500kg, 7 days (2–8 Sep) | D46: Plant hire | E46: 1 | F46: 163.3 | G46: Groundworks (digger & dumper) | H46: Hire used for both the main deck widening and the new shed area (Luke, 8 Sep) — mixed, not split.
A47: 1051287675 | B47: 46279 | C47: Loss and damage waiver | D47: Plant hire | E47: 1 | F47: 24.49 | G47: Groundworks (digger & dumper) | H47: Hire used for both the main deck widening and the new shed area (Luke, 8 Sep) — mixed, not split.
A48: 1051287675 | B48: 46279 | C48: Wear charge, fleeted refuel | D48: Plant hire | E48: 1 | F48: 6 | G48: Groundworks (digger & dumper) | H48: Hire used for both the main deck widening and the new shed area (Luke, 8 Sep) — mixed, not split.
A49: 1051287675 | B49: 46279 | C49: Hire delivery | D49: Plant hire | E49: 1 | F49: 42 | G49: Groundworks (digger & dumper) | H49: Hire used for both the main deck widening and the new shed area (Luke, 8 Sep) — mixed, not split.
A50: 1051287675 | B50: 46279 | C50: Hire collection | D50: Plant hire | E50: 1 | F50: 42 | G50: Groundworks (digger & dumper) | H50: Hire used for both the main deck widening and the new shed area (Luke, 8 Sep) — mixed, not split.
A51: 1051688095 | B51: 46286 | C51: Solid dense block 100mm | D51: Concrete blocks | E51: 6 | F51: 15.23 | G51: Extended deck & shed base | H51: Concrete/blocks dated 21 Sep — fits the first extended-deck work (Luke, 2 Oct: 1 day x2 people so far, half last week, half this week). INFERRED — confirm with Luke.
A52: 1051688095 | B52: 46286 | C52: Blue Circle Mastercrete cement 25kg | D52: Cement | E52: 4 | F52: 34.03 | G52: Extended deck & shed base | H52: Concrete/blocks dated 21 Sep — fits the first extended-deck work (Luke, 2 Oct: 1 day x2 people so far, half last week, half this week). INFERRED — confirm with Luke.
A53: 1051688095 | B53: 46286 | C53: Minotaur rubber mallet 16oz | D53: Tools, PPE, screws & small consumables | E53: 1 | F53: 5.68 | G53: Extended deck & shed base | H53: Concrete/blocks dated 21 Sep — fits the first extended-deck work (Luke, 2 Oct: 1 day x2 people so far, half last week, half this week). INFERRED — confirm with Luke.
A54: 1051688095 | B54: 46286 | C54: Prosolve line marker 750ml | D54: Tools, PPE, screws & small consumables | E54: 1 | F54: 5.36 | G54: Extended deck & shed base | H54: Concrete/blocks dated 21 Sep — fits the first extended-deck work (Luke, 2 Oct: 1 day x2 people so far, half last week, half this week). INFERRED — confirm with Luke.
A55: 1051708772 | B55: 46286 | C55: Solid dense block 100mm | D55: Concrete blocks | E55: 20 | F55: 50.76 | G55: Extended deck & shed base | H55: Concrete/blocks dated 21 Sep — fits the first extended-deck work (Luke, 2 Oct: 1 day x2 people so far, half last week, half this week). INFERRED — confirm with Luke.
A56: TOTAL | C56: 51 lines | F56: =SUM(F5:F55) -> 3216.92

Sheet Skip Hire Log
A1: Skip Hire Log — pooled rubbish-removal drawdown
A2: Provisional pooled budget £1,360 (transferred 10 Aug from chimney £80 + coping £80 + decking £1,200 rubbish-removal quotes). Family now supplies skips directly rather than Luke arranging disposal. Log every skip here AND on the Invoice Register (cost centre: Rubbish removal (pooled skips)) — this sheet is skip detail, the Register is the money record. Unlike the materials pool, more skips are expected — budget may need topping up. £40 Roofline works rubbish removal is expected but not yet incurred, so it is shown on its own row and not drawn.
A4: Opening pool: | B4: 1360 | C4: Remaining: | D4: =B4-SUM(E8:E40) -> -100
A7: Date | B7: Provider | C7: Skip details | D7: Phase / use | E7: Amount £ | F7: Running remaining £
A8: 46244 | B8: Skip Hire Comparison Ltd | C8: 8 cubic yard, general waste, delivery 11 Aug (ref D81F29CE-0002) — CANCELLED 11 Aug (supplier delayed), refunded in full (receipt 3362-9782) | D8: Above-ground works (chimney/coping) | E8: 344.16 | F8: =IF(E8="","",$B$4-SUM($E$8:E8)) -> 1015.84
A9: 46245 | B9: Skip Hire Comparison Ltd | C9: Refund — cancelled booking, receipt 3362-9782, 5-10 working days to clear | D9: Refund (cancelled skip) | E9: -344.16 | F9: =IF(E9="","",$B$4-SUM($E$8:E9)) -> 1360
A10: 46245 | B10: Elmbridge Mini Skips | C10: 8 cubic yard, delivery — filled, awaiting exchange (INV-11373, ref 25996) | D10: Above-ground works (chimney/coping) | E10: 390 | F10: =IF(E10="","",$B$4-SUM($E$8:E10)) -> 970
A11: 46246 | B11: Elmbridge Mini Skips | C11: 8 cubic yard, exchange — collects filled skip, delivers empty (INV-11375, ref 26030) | D11: Above-ground works (chimney/coping) | E11: 390 | F11: =IF(E11="","",$B$4-SUM($E$8:E11)) -> 580
A12: 46276 | B12: TBC (cash) | C12: Old decking substructure wood collection — PAID 11 Sep, £680 cash (was estimated £350; supplier charges per trip, 2 trips required) | D12: Decking substructure, both sides | E12: 680 | F12: =IF(E12="","",$B$4-SUM($E$8:E12)) -> -100
A13: 46269 | B13: LG Building and Roofing Ltd | C13: EXPECTED, NOT YET INCURRED — Roofline works rubbish removal, £40 per the 4 Sep estimate. Reclassified 8 Sep from Roofline works into this pooled fund. Not counted in the running balance until incurred; if it is, the pool would be £140 over. | D13: Roofline works | F13: =IF(E13="","",$B$4-SUM($E$8:E13))
F14: =IF(E14="","",$B$4-SUM($E$8:E14))
F15: =IF(E15="","",$B$4-SUM($E$8:E15))
F16: =IF(E16="","",$B$4-SUM($E$8:E16))
F17: =IF(E17="","",$B$4-SUM($E$8:E17))
F18: =IF(E18="","",$B$4-SUM($E$8:E18))
F19: =IF(E19="","",$B$4-SUM($E$8:E19))
F20: =IF(E20="","",$B$4-SUM($E$8:E20))
F21: =IF(E21="","",$B$4-SUM($E$8:E21))
F22: =IF(E22="","",$B$4-SUM($E$8:E22))
F23: =IF(E23="","",$B$4-SUM($E$8:E23))
F24: =IF(E24="","",$B$4-SUM($E$8:E24))
F25: =IF(E25="","",$B$4-SUM($E$8:E25))

Sheet Materials Receipts
A1: Materials Receipts — pooled budget drawdown
A2: Pooled budget £1,130 (chimney £480 + coping £650, pooled 20 Jul). Log every merchant receipt here AND on the Invoice Register (cost centre: Materials (pooled)) — this sheet is the pool detail, the Register is the money record. NOTE: pool is over cap after adding Luke's Travis Perkins account materials (now paid in full, 18 Aug) — flagged deliberately, not hidden; cap left at £1,130 rather than raised. PENDING 18 Aug: 5 bags of unused monocouche (Weber Pral M) returned to Dry Lining Supplies — refund expected within a couple of working days. Calculated from receipts: Weber Pral M Silver Pearl consistently £12.62/bag inc VAT (£126.20/10 on 22 Jul, £50.48/4 on 4 Aug) × 5 bags = £63.10 expected refund. Not yet logged as received — add Paid date once the credit note actually lands.
A4: Opening pool: | B4: 1130 | C4: Remaining: | D4: =B4-SUM(E8:E40) -> -62.9
A7: Date | B7: Merchant | C7: Items (summary) | D7: Phase / use | E7: Amount £ | F7: Running remaining £
A8: 46223 | B8: Dry Lining Supplies Ltd | C8: Render mesh, Weberend Aid ×6, angle/stop beads, rubble sacks, Bond It SBR 5l (project share; £111.71 platform excluded — Luke's equipment) | D8: Render (chimney + coping, shared) | E8: 311.98 | F8: =IF(E8="","",$B$4-SUM($E$8:E8)) -> 818.02
A9: 46225 | B9: Dry Lining Supplies | C9: Weber Pral M Silver Pearl x10 (£126.20), Plastic 15mm Stop Bead 3m x3 (£9.60), inc VAT | D9: Render finish (chimney + coping, shared) | E9: 162.96 | F9: =IF(E9="","",$B$4-SUM($E$8:E9)) -> 655.06
A10: 46238 | B10: Dry Lining Supplies Ltd | C10: Weberend Ocr x3 (£29.13), Weber Pral M Silver Pearl x4 (£50.48), Stop Bead x6 (£19.20), Drip Bead x2 (£7.42), Sikabond SBR (£17.54), inc VAT | D10: Render (coping stones) | E10: 148.53 | F10: =IF(E10="","",$B$4-SUM($E$8:E10)) -> 506.53
A11: 46250 | B11: SoftWash UK | C11: Render Cleaner Gel X Pro, 5 Litres (order F4UJ62VLQ) | D11: Render cleanup (chimney + coping, shared) | E11: 47.99 | F11: =IF(E11="","",$B$4-SUM($E$8:E11)) -> 458.54
A12: 46251 | B12: LG Building and Roofing Ltd (Travis Perkins account) | C12: Render/masonry consumables + lead flashing, 3 invoices 17 Jul-5 Aug (1047678330 / 1047972816 / 1048887075) — pooled, not split by workstream | D12: Render (chimney + coping, pooled) | E12: 481.26 | F12: =IF(E12="","",$B$4-SUM($E$8:E12)) -> -22.72
F13: =IF(E13="","",$B$4-SUM($E$8:E13))
A14: 46244 | B14: LG Building and Roofing Ltd (Travis Perkins account, INV 1049120278) | C14: Cleaning/finishing consumables (trigger spray, decorating cloth) — pooled, not split by workstream | D14: Render (chimney + coping, pooled) | E14: 40.18 | F14: =IF(E14="","",$B$4-SUM($E$8:E14)) -> -62.9
F15: =IF(E15="","",$B$4-SUM($E$8:E15))
F16: =IF(E16="","",$B$4-SUM($E$8:E16))
F17: =IF(E17="","",$B$4-SUM($E$8:E17))
F18: =IF(E18="","",$B$4-SUM($E$8:E18))
F19: =IF(E19="","",$B$4-SUM($E$8:E19))
F20: =IF(E20="","",$B$4-SUM($E$8:E20))
F21: =IF(E21="","",$B$4-SUM($E$8:E21))
F22: =IF(E22="","",$B$4-SUM($E$8:E22))
F23: =IF(E23="","",$B$4-SUM($E$8:E23))
F24: =IF(E24="","",$B$4-SUM($E$8:E24))
F25: =IF(E25="","",$B$4-SUM($E$8:E25))
